Workbook

Sheet 📋 Instrucciones
B2: Modelo TIME — Plantilla de Racionalización de Portfolio
B3: Arquitectura Empresarial | Basado en framework Gartner TIME + 6R
B5: ¿CÓMO USAR ESTA PLANTILLA?
B6: Paso 1: Ir a la hoja 📊 Portfolio | C6: Ingresa cada aplicación en una fila. Llena las columnas azules (datos de entrada).
B7: Paso 2: Valor de Negocio | C7: Selecciona del desplegable: Alto = la aplicación es estratégica o crítica para el negocio. Bajo = soporta procesos secundarios o tiene pocos usuarios.
B8: Paso 3: Salud Técnica | C8: Selecciona del desplegable: Alta = arquitectura moderna, mantenible, bien documentada. Baja = deuda técnica alta, tecnología obsoleta, difícil de mantener.
B9: Paso 4: Cuadrante y 6R | C9: Se calculan automáticamente con fórmulas. NO modificar esas columnas.
B10: Paso 5: Ver resumen | C10: Ir a la hoja 📈 Dashboard para ver conteos y distribución del portfolio.
B11: Paso 6: Subir a Claude | C11: Guarda el archivo y súbelo en el chat de Claude.ai para análisis profundo de portfolio, roadmap de migración y recomendaciones.
B13: CUADRANTES TIME
B14: T — TOLERATE | C14: Salud Alta + Valor Bajo | D14: Funciona bien pero no aporta valor estratégico. Mantener con inversión mínima, reducir costos.
B15: I — INVEST | C15: Salud Alta + Valor Alto | D15: Sistema estratégico en buen estado. Invertir, escalar y evolucionar activamente.
B16: M — MIGRATE | C16: Salud Baja + Valor Alto | D16: Crítico para el negocio pero con deuda técnica. Modernizar con urgencia (6R).
B17: E — ELIMINATE | C17: Salud Baja + Valor Bajo | D17: Sin valor y en mal estado técnico. Planificar descomisión con fecha fija.
B19: ESTRATEGIAS 6R (sugeridas automáticamente)
B20: R3 — Rehost (Lift & Shift) | C20: Mover la aplicación a nueva infra sin cambios. Rápido y barato. No aprovecha cloud.
B21: R4 — Replatform | C21: Ajustes mínimos al migrar (ej: contenedores). Equilibrio costo/beneficio.
B22: R5 — Repurchase (Drop & Shop) | C22: Reemplazar por SaaS o producto estándar. Ej: CRM propio → Salesforce.
B23: R6 — Refactor / Re-architect | C23: Rediseño profundo. El más costoso y riesgoso. Justificado solo si el valor de negocio es muy alto.
B24: Retire | C24: Descomisionar. Comunicar fecha, migrar datos residuales, apagar.
B25: Retain | C25: Mantener sin cambios por ahora. Revisar en el próximo ciclo de portfolio.

Sheet 📊 Portfolio
A1: PORTFOLIO DE APLICACIONES — MODELO TIME
A2: # | B2: Aplicación / Sistema | C2: Área / Dominio | D2: Capa | E2: Tipo | F2: Valor de Negocio (Alto / Bajo) | G2: Salud Técnica (Alta / Baja) | H2: Cuadrante TIME (automático) | I2: Estrategia 6R (automática) | J2: Prioridad (automática) | K2: Propuesta Santander | L2: Notas / Observaciones
A3: 1 | B3: SAP by Design | C3: Cross | D3: Transversal | E3: ERP | F3: Alto | G3: Baja | H3: =IF(OR(F3="",G3=""),"",IF(F3="Alto",IF(G3="Alta","I — Invest","M — Migrate"),IF(G3="Alta","T — Tolerate","E — Eliminate"))) -> M — Migrate | I3: =IF(H3="","",IF(H3="I — Invest","R6 — Refactor",IF(H3="M — Migrate","R4 — Replatform",IF(H3="T — Tolerate","Retain","Retire")))) -> R4 — Replatform | J3: =IF(H3="","",IF(H3="M — Migrate","🔴 Alta",IF(H3="I — Invest","🟡 Media-Alta",IF(H3="T — Tolerate","🟢 Baja","⚪ Descomisionar")))) -> 🔴 Alta | K3: Tolerate
A4: 2 | B4: App Surgir | C4: Surgir | D4: Business | E4: App Móvil | F4: Bajo | G4: Alta | H4: =IF(OR(F4="",G4=""),"",IF(F4="Alto",IF(G4="Alta","I — Invest","M — Migrate"),IF(G4="Alta","T — Tolerate","E — Eliminate"))) -> T — Tolerate | I4: =IF(H4="","",IF(H4="I — Invest","R6 — Refactor",IF(H4="M — Migrate","R4 — Replatform",IF(H4="T — Tolerate","Retain","Retire")))) -> Retain | J4: =IF(H4="","",IF(H4="M — Migrate","🔴 Alta",IF(H4="I — Invest","🟡 Media-Alta",IF(H4="T — Tolerate","🟢 Baja","⚪ Descomisionar")))) -> 🟢 Baja | K4: Migrate
A5: 3 | B5: App Cliente | C5: Surgir | D5: Front | E5: CANALES DIGITALES | H5: =IF(OR(F5="",G5=""),"",IF(F5="Alto",IF(G5="Alta","I — Invest","M — Migrate"),IF(G5="Alta","T — Tolerate","E — Eliminate"))) | I5: =IF(H5="","",IF(H5="I — Invest","R6 — Refactor",IF(H5="M — Migrate","R4 — Replatform",IF(H5="T — Tolerate","Retain","Retire")))) | J5: =IF(H5="","",IF(H5="M — Migrate","🔴 Alta",IF(H5="I — Invest","🟡 Media-Alta",IF(H5="T — Tolerate","🟢 Baja","⚪ Descomisionar")))) | K5: Migrate
A6: 4 | B6: AMLUpdate - Name Screening | C6: Surgir | D6: Transversal | E6: FCC | H6: =IF(OR(F6="",G6=""),"",IF(F6="Alto",IF(G6="Alta","I — Invest","M — Migrate"),IF(G6="Alta","T — Tolerate","E — Eliminate"))) | I6: =IF(H6="","",IF(H6="I — Invest","R6 — Refactor",IF(H6="M — Migrate","R4 — Replatform",IF(H6="T — Tolerate","Retain","Retire")))) | J6: =IF(H6="","",IF(H6="M — Migrate","🔴 Alta",IF(H6="I — Invest","🟡 Media-Alta",IF(H6="T — Tolerate","🟢 Baja","⚪ Descomisionar")))) | K6: Tolerate
A7: 5 | B7: Portal Web Público | C7: Surgir | D7: Front | E7: CANALES DIGITALES | H7: =IF(OR(F7="",G7=""),"",IF(F7="Alto",IF(G7="Alta","I — Invest","M — Migrate"),IF(G7="Alta","T — Tolerate","E — Eliminate"))) | I7: =IF(H7="","",IF(H7="I — Invest","R6 — Refactor",IF(H7="M — Migrate","R4 — Replatform",IF(H7="T — Tolerate","Retain","Retire")))) | J7: =IF(H7="","",IF(H7="M — Migrate","🔴 Alta",IF(H7="I — Invest","🟡 Media-Alta",IF(H7="T — Tolerate","🟢 Baja","⚪ Descomisionar"))))
A8: 6 | B8: Anura | C8: Surgir | D8: Front | E8: Portal Web | F8: Alto | G8: Baja | H8: =IF(OR(F8="",G8=""),"",IF(F8="Alto",IF(G8="Alta","I — Invest","M — Migrate"),IF(G8="Alta","T — Tolerate","E — Eliminate"))) -> M — Migrate | I8: =IF(H8="","",IF(H8="I — Invest","R6 — Refactor",IF(H8="M — Migrate","R4 — Replatform",IF(H8="T — Tolerate","Retain","Retire")))) -> R4 — Replatform | J8: =IF(H8="","",IF(H8="M — Migrate","🔴 Alta",IF(H8="I — Invest","🟡 Media-Alta",IF(H8="T — Tolerate","🟢 Baja","⚪ Descomisionar")))) -> 🔴 Alta | K8: Migrate
A9: 7 | B9: ERP Contanet | C9: Surgir | D9: Transversal | E9: ERP | F9: Alto | G9: Baja | H9: =IF(OR(F9="",G9=""),"",IF(F9="Alto",IF(G9="Alta","I — Invest","M — Migrate"),IF(G9="Alta","T — Tolerate","E — Eliminate"))) -> M — Migrate | I9: =IF(H9="","",IF(H9="I — Invest","R6 — Refactor",IF(H9="M — Migrate","R4 — Replatform",IF(H9="T — Tolerate","Retain","Retire")))) -> R4 — Replatform | J9: =IF(H9="","",IF(H9="M — Migrate","🔴 Alta",IF(H9="I — Invest","🟡 Media-Alta",IF(H9="T — Tolerate","🟢 Baja","⚪ Descomisionar")))) -> 🔴 Alta | K9: Migrate
A10: 8 | B10: Datalake | C10: Surgir | D10: Transversal | E10: DATALAKE | H10: =IF(OR(F10="",G10=""),"",IF(F10="Alto",IF(G10="Alta","I — Invest","M — Migrate"),IF(G10="Alta","T — Tolerate","E — Eliminate"))) | I10: =IF(H10="","",IF(H10="I — Invest","R6 — Refactor",IF(H10="M — Migrate","R4 — Replatform",IF(H10="T — Tolerate","Retain","Retire")))) | J10: =IF(H10="","",IF(H10="M — Migrate","🔴 Alta",IF(H10="I — Invest","🟡 Media-Alta",IF(H10="T — Tolerate","🟢 Baja","⚪ Descomisionar"))))
A11: 9 | B11: Cobis | C11: Surgir | D11: Business | E11: CORE BANKING | F11: Alto | G11: Baja | H11: =IF(OR(F11="",G11=""),"",IF(F11="Alto",IF(G11="Alta","I — Invest","M — Migrate"),IF(G11="Alta","T — Tolerate","E — Eliminate"))) -> M — Migrate | I11: =IF(H11="","",IF(H11="I — Invest","R6 — Refactor",IF(H11="M — Migrate","R4 — Replatform",IF(H11="T — Tolerate","Retain","Retire")))) -> R4 — Replatform | J11: =IF(H11="","",IF(H11="M — Migrate","🔴 Alta",IF(H11="I — Invest","🟡 Media-Alta",IF(H11="T — Tolerate","🟢 Baja","⚪ Descomisionar")))) -> 🔴 Alta | K11: Migrate
A12: 10 | B12: Emblue | C12: Santander Fondos Colectivos | D12: Front | E12: Canal Asistido | F12: Bajo | G12: Alta | H12: =IF(OR(F12="",G12=""),"",IF(F12="Alto",IF(G12="Alta","I — Invest","M — Migrate"),IF(G12="Alta","T — Tolerate","E — Eliminate"))) -> T — Tolerate | I12: =IF(H12="","",IF(H12="I — Invest","R6 — Refactor",IF(H12="M — Migrate","R4 — Replatform",IF(H12="T — Tolerate","Retain","Retire")))) -> Retain | J12: =IF(H12="","",IF(H12="M — Migrate","🔴 Alta",IF(H12="I — Invest","🟡 Media-Alta",IF(H12="T — Tolerate","🟢 Baja","⚪ Descomisionar")))) -> 🟢 Baja | K12: Migrate
A13: 11 | B13: Facephi | C13: Santander Fondos Colectivos | D13: Business | E13: CUSTOMER IDENTITY | F13: Alto | G13: Alta | H13: =IF(OR(F13="",G13=""),"",IF(F13="Alto",IF(G13="Alta","I — Invest","M — Migrate"),IF(G13="Alta","T — Tolerate","E — Eliminate"))) -> I — Invest | I13: =IF(H13="","",IF(H13="I — Invest","R6 — Refactor",IF(H13="M — Migrate","R4 — Replatform",IF(H13="T — Tolerate","Retain","Retire")))) -> R6 — Refactor | J13: =IF(H13="","",IF(H13="M — Migrate","🔴 Alta",IF(H13="I — Invest","🟡 Media-Alta",IF(H13="T — Tolerate","🟢 Baja","⚪ Descomisionar")))) -> 🟡 Media-Alta | K13: Tolerate
A14: 12 | B14: Mapfre | C14: Santander Fondos Colectivos | D14: Business | E14: Insurance (Vehicular) | F14: Bajo | G14: Alta | H14: =IF(OR(F14="",G14=""),"",IF(F14="Alto",IF(G14="Alta","I — Invest","M — Migrate"),IF(G14="Alta","T — Tolerate","E — Eliminate"))) -> T — Tolerate | I14: =IF(H14="","",IF(H14="I — Invest","R6 — Refactor",IF(H14="M — Migrate","R4 — Replatform",IF(H14="T — Tolerate","Retain","Retire")))) -> Retain | J14: =IF(H14="","",IF(H14="M — Migrate","🔴 Alta",IF(H14="I — Invest","🟡 Media-Alta",IF(H14="T — Tolerate","🟢 Baja","⚪ Descomisionar")))) -> 🟢 Baja
A15: 13 | B15: Tracklink | C15: Santander Fondos Colectivos | D15: Transversal | E15: Externo | F15: Bajo | G15: Baja | H15: =IF(OR(F15="",G15=""),"",IF(F15="Alto",IF(G15="Alta","I — Invest","M — Migrate"),IF(G15="Alta","T — Tolerate","E — Eliminate"))) -> E — Eliminate | I15: =IF(H15="","",IF(H15="I — Invest","R6 — Refactor",IF(H15="M — Migrate","R4 — Replatform",IF(H15="T — Tolerate","Retain","Retire")))) -> Retire | J15: =IF(H15="","",IF(H15="M — Migrate","🔴 Alta",IF(H15="I — Invest","🟡 Media-Alta",IF(H15="T — Tolerate","🟢 Baja","⚪ Descomisionar")))) -> ⚪ Descomisionar | K15: Tolerate
A16: 14 | B16: Docuclass | C16: Santander Fondos Colectivos | D16: Transversal | E16: Procesos | F16: Alto | G16: Baja | H16: =IF(OR(F16="",G16=""),"",IF(F16="Alto",IF(G16="Alta","I — Invest","M — Migrate"),IF(G16="Alta","T — Tolerate","E — Eliminate"))) -> M — Migrate | I16: =IF(H16="","",IF(H16="I — Invest","R6 — Refactor",IF(H16="M — Migrate","R4 — Replatform",IF(H16="T — Tolerate","Retain","Retire")))) -> R4 — Replatform | J16: =IF(H16="","",IF(H16="M — Migrate","🔴 Alta",IF(H16="I — Invest","🟡 Media-Alta",IF(H16="T — Tolerate","🟢 Baja","⚪ Descomisionar")))) -> 🔴 Alta | K16: Tolerate
A17: 15 | B17: Diloo | C17: Cross | D17: Transversal | E17: Canal Asistido | F17: Bajo | G17: Baja | H17: =IF(OR(F17="",G17=""),"",IF(F17="Alto",IF(G17="Alta","I — Invest","M — Migrate"),IF(G17="Alta","T — Tolerate","E — Eliminate"))) -> E — Eliminate | I17: =IF(H17="","",IF(H17="I — Invest","R6 — Refactor",IF(H17="M — Migrate","R4 — Replatform",IF(H17="T — Tolerate","Retain","Retire")))) -> Retire | J17: =IF(H17="","",IF(H17="M — Migrate","🔴 Alta",IF(H17="I — Invest","🟡 Media-Alta",IF(H17="T — Tolerate","🟢 Baja","⚪ Descomisionar")))) -> ⚪ Descomisionar | K17: Migrate
A18: 16 | B18: Izipay Pagos en línea | C18: Santander Fondos Colectivos | D18: Business | E18: PAGOS | F18: Alto | G18: Alta | H18: =IF(OR(F18="",G18=""),"",IF(F18="Alto",IF(G18="Alta","I — Invest","M — Migrate"),IF(G18="Alta","T — Tolerate","E — Eliminate"))) -> I — Invest | I18: =IF(H18="","",IF(H18="I — Invest","R6 — Refactor",IF(H18="M — Migrate","R4 — Replatform",IF(H18="T — Tolerate","Retain","Retire")))) -> R6 — Refactor | J18: =IF(H18="","",IF(H18="M — Migrate","🔴 Alta",IF(H18="I — Invest","🟡 Media-Alta",IF(H18="T — Tolerate","🟢 Baja","⚪ Descomisionar")))) -> 🟡 Media-Alta | K18: Tolerate
A19: 17 | B19: IBK Recaudación | C19: Santander Fondos Colectivos | D19: Business | E19: PAGOS | H19: =IF(OR(F19="",G19=""),"",IF(F19="Alto",IF(G19="Alta","I — Invest","M — Migrate"),IF(G19="Alta","T — Tolerate","E — Eliminate"))) | I19: =IF(H19="","",IF(H19="I — Invest","R6 — Refactor",IF(H19="M — Migrate","R4 — Replatform",IF(H19="T — Tolerate","Retain","Retire")))) | J19: =IF(H19="","",IF(H19="M — Migrate","🔴 Alta",IF(H19="I — Invest","🟡 Media-Alta",IF(H19="T — Tolerate","🟢 Baja","⚪ Descomisionar"))))
A21: 19 | B21: Portal Web Público | C21: Santander Fondos Colectivos | D21: Front | E21: CANALES DIGITALES | H21: =IF(OR(F21="",G21=""),"",IF(F21="Alto",IF(G21="Alta","I — Invest","M — Migrate"),IF(G21="Alta","T — Tolerate","E — Eliminate"))) | I21: =IF(H21="","",IF(H21="I — Invest","R6 — Refactor",IF(H21="M — Migrate","R4 — Replatform",IF(H21="T — Tolerate","Retain","Retire")))) | J21: =IF(H21="","",IF(H21="M — Migrate","🔴 Alta",IF(H21="I — Invest","🟡 Media-Alta",IF(H21="T — Tolerate","🟢 Baja","⚪ Descomisionar"))))
A22: 20 | B22: AMLUpdate - Name Screening | C22: Santander Fondos Colectivos | D22: Transversal | E22: FCC | H22: =IF(OR(F22="",G22=""),"",IF(F22="Alto",IF(G22="Alta","I — Invest","M — Migrate"),IF(G22="Alta","T — Tolerate","E — Eliminate"))) | I22: =IF(H22="","",IF(H22="I — Invest","R6 — Refactor",IF(H22="M — Migrate","R4 — Replatform",IF(H22="T — Tolerate","Retain","Retire")))) | J22: =IF(H22="","",IF(H22="M — Migrate","🔴 Alta",IF(H22="I — Invest","🟡 Media-Alta",IF(H22="T — Tolerate","🟢 Baja","⚪ Descomisionar"))))
A23: 21 | B23: Santo | C23: Santander Fondos Colectivos | D23: Business | E23: CORE BANKING | H23: =IF(OR(F23="",G23=""),"",IF(F23="Alto",IF(G23="Alta","I — Invest","M — Migrate"),IF(G23="Alta","T — Tolerate","E — Eliminate"))) | I23: =IF(H23="","",IF(H23="I — Invest","R6 — Refactor",IF(H23="M — Migrate","R4 — Replatform",IF(H23="T — Tolerate","Retain","Retire")))) | J23: =IF(H23="","",IF(H23="M — Migrate","🔴 Alta",IF(H23="I — Invest","🟡 Media-Alta",IF(H23="T — Tolerate","🟢 Baja","⚪ Descomisionar"))))
A24: 22 | B24: Nuevo Office Banking | C24: SCIB Perú | D24: Front | E24: CANALES DIGITALES | H24: =IF(OR(F24="",G24=""),"",IF(F24="Alto",IF(G24="Alta","I — Invest","M — Migrate"),IF(G24="Alta","T — Tolerate","E — Eliminate"))) | I24: =IF(H24="","",IF(H24="I — Invest","R6 — Refactor",IF(H24="M — Migrate","R4 — Replatform",IF(H24="T — Tolerate","Retain","Retire")))) | J24: =IF(H24="","",IF(H24="M — Migrate","🔴 Alta",IF(H24="I — Invest","🟡 Media-Alta",IF(H24="T — Tolerate","🟢 Baja","⚪ Descomisionar"))))
A25: 23 | B25: CEEFFC | C25: SCIB Perú | D25: Transversal | E25: MIS | F25: Bajo | G25: Baja | H25: =IF(OR(F25="",G25=""),"",IF(F25="Alto",IF(G25="Alta","I — Invest","M — Migrate"),IF(G25="Alta","T — Tolerate","E — Eliminate"))) -> E — Eliminate | I25: =IF(H25="","",IF(H25="I — Invest","R6 — Refactor",IF(H25="M — Migrate","R4 — Replatform",IF(H25="T — Tolerate","Retain","Retire")))) -> Retire | J25: =IF(H25="","",IF(H25="M — Migrate","🔴 Alta",IF(H25="I — Invest","🟡 Media-Alta",IF(H25="T — Tolerate","🟢 Baja","⚪ Descomisionar")))) -> ⚪ Descomisionar | K25: Migrate
A26: 24 | B26: Lbtr | C26: SCIB Perú | D26: Business | E26: PAGOS | F26: Alto | G26: Alta | H26: =IF(OR(F26="",G26=""),"",IF(F26="Alto",IF(G26="Alta","I — Invest","M — Migrate"),IF(G26="Alta","T — Tolerate","E — Eliminate"))) -> I — Invest | I26: =IF(H26="","",IF(H26="I — Invest","R6 — Refactor",IF(H26="M — Migrate","R4 — Replatform",IF(H26="T — Tolerate","Retain","Retire")))) -> R6 — Refactor | J26: =IF(H26="","",IF(H26="M — Migrate","🔴 Alta",IF(H26="I — Invest","🟡 Media-Alta",IF(H26="T — Tolerate","🟢 Baja","⚪ Descomisionar")))) -> 🟡 Media-Alta | K26: Migrate
A27: 25 | B27: Cash Nexus | C27: SCIB Perú | D27: Front | E27: PAGOS | H27: =IF(OR(F27="",G27=""),"",IF(F27="Alto",IF(G27="Alta","I — Invest","M — Migrate"),IF(G27="Alta","T — Tolerate","E — Eliminate"))) | I27: =IF(H27="","",IF(H27="I — Invest","R6 — Refactor",IF(H27="M — Migrate","R4 — Replatform",IF(H27="T — Tolerate","Retain","Retire")))) | J27: =IF(H27="","",IF(H27="M — Migrate","🔴 Alta",IF(H27="I — Invest","🟡 Media-Alta",IF(H27="T — Tolerate","🟢 Baja","⚪ Descomisionar"))))
A28: 26 | B28: Host to Host | C28: SCIB Perú | D28: Front | E28: PAGOS | F28: Alto | G28: Baja | H28: =IF(OR(F28="",G28=""),"",IF(F28="Alto",IF(G28="Alta","I — Invest","M — Migrate"),IF(G28="Alta","T — Tolerate","E — Eliminate"))) -> M — Migrate | I28: =IF(H28="","",IF(H28="I — Invest","R6 — Refactor",IF(H28="M — Migrate","R4 — Replatform",IF(H28="T — Tolerate","Retain","Retire")))) -> R4 — Replatform | J28: =IF(H28="","",IF(H28="M — Migrate","🔴 Alta",IF(H28="I — Invest","🟡 Media-Alta",IF(H28="T — Tolerate","🟢 Baja","⚪ Descomisionar")))) -> 🔴 Alta | K28: Migrate
A29: 27 | B29: Sistema Office Banking | C29: SCIB Perú | D29: Front | E29: CANALES DIGITALES | F29: Alto | G29: Baja | H29: =IF(OR(F29="",G29=""),"",IF(F29="Alto",IF(G29="Alta","I — Invest","M — Migrate"),IF(G29="Alta","T — Tolerate","E — Eliminate"))) -> M — Migrate | I29: =IF(H29="","",IF(H29="I — Invest","R6 — Refactor",IF(H29="M — Migrate","R4 — Replatform",IF(H29="T — Tolerate","Retain","Retire")))) -> R4 — Replatform | J29: =IF(H29="","",IF(H29="M — Migrate","🔴 Alta",IF(H29="I — Invest","🟡 Media-Alta",IF(H29="T — Tolerate","🟢 Baja","⚪ Descomisionar")))) -> 🔴 Alta | K29: Migrate
A30: 29 | B30: Plataforma de Facturacion Electronica | C30: Santander Consumer Perú | D30: Transversal | E30: MIS | F30: Bajo | G30: Baja | H30: =IF(OR(F30="",G30=""),"",IF(F30="Alto",IF(G30="Alta","I — Invest","M — Migrate"),IF(G30="Alta","T — Tolerate","E — Eliminate"))) -> E — Eliminate | I30: =IF(H30="","",IF(H30="I — Invest","R6 — Refactor",IF(H30="M — Migrate","R4 — Replatform",IF(H30="T — Tolerate","Retain","Retire")))) -> Retire | J30: =IF(H30="","",IF(H30="M — Migrate","🔴 Alta",IF(H30="I — Invest","🟡 Media-Alta",IF(H30="T — Tolerate","🟢 Baja","⚪ Descomisionar")))) -> ⚪ Descomisionar | K30: Invest
A31: 30 | B31: Contáctanos | C31: Santander Consumer Perú | D31: Front | E31: RECLAMOS | F31: Bajo | G31: Baja | H31: =IF(OR(F31="",G31=""),"",IF(F31="Alto",IF(G31="Alta","I — Invest","M — Migrate"),IF(G31="Alta","T — Tolerate","E — Eliminate"))) -> E — Eliminate | I31: =IF(H31="","",IF(H31="I — Invest","R6 — Refactor",IF(H31="M — Migrate","R4 — Replatform",IF(H31="T — Tolerate","Retain","Retire")))) -> Retire | J31: =IF(H31="","",IF(H31="M — Migrate","🔴 Alta",IF(H31="I — Invest","🟡 Media-Alta",IF(H31="T — Tolerate","🟢 Baja","⚪ Descomisionar")))) -> ⚪ Descomisionar | K31: Invest
A32: 31 | B32: Visor Cobranzas | C32: Santander Consumer Perú | D32: Business | E32: COBRANZAS | F32: Alto | G32: Baja | H32: =IF(OR(F32="",G32=""),"",IF(F32="Alto",IF(G32="Alta","I — Invest","M — Migrate"),IF(G32="Alta","T — Tolerate","E — Eliminate"))) -> M — Migrate | I32: =IF(H32="","",IF(H32="I — Invest","R6 — Refactor",IF(H32="M — Migrate","R4 — Replatform",IF(H32="T — Tolerate","Retain","Retire")))) -> R4 — Replatform | J32: =IF(H32="","",IF(H32="M — Migrate","🔴 Alta",IF(H32="I — Invest","🟡 Media-Alta",IF(H32="T — Tolerate","🟢 Baja","⚪ Descomisionar")))) -> 🔴 Alta
A33: 32 | B33: Api Market | C33: Santander Consumer Perú | D33: Business | E33: Canal Asistido | F33: Alto | G33: Alta | H33: =IF(OR(F33="",G33=""),"",IF(F33="Alto",IF(G33="Alta","I — Invest","M — Migrate"),IF(G33="Alta","T — Tolerate","E — Eliminate"))) -> I — Invest | I33: =IF(H33="","",IF(H33="I — Invest","R6 — Refactor",IF(H33="M — Migrate","R4 — Replatform",IF(H33="T — Tolerate","Retain","Retire")))) -> R6 — Refactor | J33: =IF(H33="","",IF(H33="M — Migrate","🔴 Alta",IF(H33="I — Invest","🟡 Media-Alta",IF(H33="T — Tolerate","🟢 Baja","⚪ Descomisionar")))) -> 🟡 Media-Alta | K33: Invest
A34: 33 | B34: AMLUpdate - Name Screening | C34: Santander Consumer Perú | D34: Transversal | E34: FCC | F34: Alto | G34: Baja | H34: =IF(OR(F34="",G34=""),"",IF(F34="Alto",IF(G34="Alta","I — Invest","M — Migrate"),IF(G34="Alta","T — Tolerate","E — Eliminate"))) -> M — Migrate | I34: =IF(H34="","",IF(H34="I — Invest","R6 — Refactor",IF(H34="M — Migrate","R4 — Replatform",IF(H34="T — Tolerate","Retain","Retire")))) -> R4 — Replatform | J34: =IF(H34="","",IF(H34="M — Migrate","🔴 Alta",IF(H34="I — Invest","🟡 Media-Alta",IF(H34="T — Tolerate","🟢 Baja","⚪ Descomisionar")))) -> 🔴 Alta | K34: Migrate
A35: 34 | B35: Facturación Electrónica - Auto | C35: Santander Consumer Perú | D35: Transversal | E35: MIS | F35: Bajo | G35: Alta | H35: =IF(OR(F35="",G35=""),"",IF(F35="Alto",IF(G35="Alta","I — Invest","M — Migrate"),IF(G35="Alta","T — Tolerate","E — Eliminate"))) -> T — Tolerate | I35: =IF(H35="","",IF(H35="I — Invest","R6 — Refactor",IF(H35="M — Migrate","R4 — Replatform",IF(H35="T — Tolerate","Retain","Retire")))) -> Retain | J35: =IF(H35="","",IF(H35="M — Migrate","🔴 Alta",IF(H35="I — Invest","🟡 Media-Alta",IF(H35="T — Tolerate","🟢 Baja","⚪ Descomisionar")))) -> 🟢 Baja | K35: Invest
A36: 35 | B36: Portal Web Público | C36: Santander Consumer Perú | D36: Front | E36: CANALES DIGITALES | F36: Bajo | G36: Baja | H36: =IF(OR(F36="",G36=""),"",IF(F36="Alto",IF(G36="Alta","I — Invest","M — Migrate"),IF(G36="Alta","T — Tolerate","E — Eliminate"))) -> E — Eliminate | I36: =IF(H36="","",IF(H36="I — Invest","R6 — Refactor",IF(H36="M — Migrate","R4 — Replatform",IF(H36="T — Tolerate","Retain","Retire")))) -> Retire | J36: =IF(H36="","",IF(H36="M — Migrate","🔴 Alta",IF(H36="I — Invest","🟡 Media-Alta",IF(H36="T — Tolerate","🟢 Baja","⚪ Descomisionar")))) -> ⚪ Descomisionar | K36: Migrate
A38: 37 | B38: Bantotal - Core Bancario | C38: Santander Consumer Perú | D38: Business | E38: CORE BANKING | F38: Alto | G38: Alta | H38: =IF(OR(F38="",G38=""),"",IF(F38="Alto",IF(G38="Alta","I — Invest","M — Migrate"),IF(G38="Alta","T — Tolerate","E — Eliminate"))) -> I — Invest | I38: =IF(H38="","",IF(H38="I — Invest","R6 — Refactor",IF(H38="M — Migrate","R4 — Replatform",IF(H38="T — Tolerate","Retain","Retire")))) -> R6 — Refactor | J38: =IF(H38="","",IF(H38="M — Migrate","🔴 Alta",IF(H38="I — Invest","🟡 Media-Alta",IF(H38="T — Tolerate","🟢 Baja","⚪ Descomisionar")))) -> 🟡 Media-Alta | K38: Tolerate
A39: 38 | B39: Motor de Crédito | C39: Santander Consumer Perú | D39: Business | E39: Riesgos | F39: Alto | G39: Alta | H39: =IF(OR(F39="",G39=""),"",IF(F39="Alto",IF(G39="Alta","I — Invest","M — Migrate"),IF(G39="Alta","T — Tolerate","E — Eliminate"))) -> I — Invest | I39: =IF(H39="","",IF(H39="I — Invest","R6 — Refactor",IF(H39="M — Migrate","R4 — Replatform",IF(H39="T — Tolerate","Retain","Retire")))) -> R6 — Refactor | J39: =IF(H39="","",IF(H39="M — Migrate","🔴 Alta",IF(H39="I — Invest","🟡 Media-Alta",IF(H39="T — Tolerate","🟢 Baja","⚪ Descomisionar")))) -> 🟡 Media-Alta | K39: Invest
A40: 39 | B40: Santi | C40: Santander Consumer Perú | D40: Business | E40: Canal Asistido | F40: Alto | G40: Alta | H40: =IF(OR(F40="",G40=""),"",IF(F40="Alto",IF(G40="Alta","I — Invest","M — Migrate"),IF(G40="Alta","T — Tolerate","E — Eliminate"))) -> I — Invest | I40: =IF(H40="","",IF(H40="I — Invest","R6 — Refactor",IF(H40="M — Migrate","R4 — Replatform",IF(H40="T — Tolerate","Retain","Retire")))) -> R6 — Refactor | J40: =IF(H40="","",IF(H40="M — Migrate","🔴 Alta",IF(H40="I — Invest","🟡 Media-Alta",IF(H40="T — Tolerate","🟢 Baja","⚪ Descomisionar")))) -> 🟡 Media-Alta | K40: Invest
A41: 40 | B41: Seguros La Positiva | C41: Santander Consumer Perú | D41: Business | E41: Insurance (Vehicular) | H41: =IF(OR(F41="",G41=""),"",IF(F41="Alto",IF(G41="Alta","I — Invest","M — Migrate"),IF(G41="Alta","T — Tolerate","E — Eliminate"))) | I41: =IF(H41="","",IF(H41="I — Invest","R6 — Refactor",IF(H41="M — Migrate","R4 — Replatform",IF(H41="T — Tolerate","Retain","Retire")))) | J41: =IF(H41="","",IF(H41="M — Migrate","🔴 Alta",IF(H41="I — Invest","🟡 Media-Alta",IF(H41="T — Tolerate","🟢 Baja","⚪ Descomisionar"))))
A42: 41 | B42: Equifax | C42: Santander Consumer Perú | D42: Business | E42: Riesgos | F42: Bajo | G42: Alta | H42: =IF(OR(F42="",G42=""),"",IF(F42="Alto",IF(G42="Alta","I — Invest","M — Migrate"),IF(G42="Alta","T — Tolerate","E — Eliminate"))) -> T — Tolerate | I42: =IF(H42="","",IF(H42="I — Invest","R6 — Refactor",IF(H42="M — Migrate","R4 — Replatform",IF(H42="T — Tolerate","Retain","Retire")))) -> Retain | J42: =IF(H42="","",IF(H42="M — Migrate","🔴 Alta",IF(H42="I — Invest","🟡 Media-Alta",IF(H42="T — Tolerate","🟢 Baja","⚪ Descomisionar")))) -> 🟢 Baja | K42: Tolerate
A43: 42 | B43: Docuclass | C43: Santander Consumer Perú | D43: Business | E43: Procesos | F43: Bajo | G43: Alta | H43: =IF(OR(F43="",G43=""),"",IF(F43="Alto",IF(G43="Alta","I — Invest","M — Migrate"),IF(G43="Alta","T — Tolerate","E — Eliminate"))) -> T — Tolerate | I43: =IF(H43="","",IF(H43="I — Invest","R6 — Refactor",IF(H43="M — Migrate","R4 — Replatform",IF(H43="T — Tolerate","Retain","Retire")))) -> Retain | J43: =IF(H43="","",IF(H43="M — Migrate","🔴 Alta",IF(H43="I — Invest","🟡 Media-Alta",IF(H43="T — Tolerate","🟢 Baja","⚪ Descomisionar")))) -> 🟢 Baja | K43: Tolerate
A44: 43 | B44: Seir | C44: Santander Consumer Perú | D44: Transversal | E44: MIS | H44: =IF(OR(F44="",G44=""),"",IF(F44="Alto",IF(G44="Alta","I — Invest","M — Migrate"),IF(G44="Alta","T — Tolerate","E — Eliminate"))) | I44: =IF(H44="","",IF(H44="I — Invest","R6 — Refactor",IF(H44="M — Migrate","R4 — Replatform",IF(H44="T — Tolerate","Retain","Retire")))) | J44: =IF(H44="","",IF(H44="M — Migrate","🔴 Alta",IF(H44="I — Invest","🟡 Media-Alta",IF(H44="T — Tolerate","🟢 Baja","⚪ Descomisionar"))))
A45: 44 | B45: Pomelo | C45: Santander Consumer Perú | D45: Business | E45: TARJETAS CREDITO | F45: Alto | G45: Baja | H45: =IF(OR(F45="",G45=""),"",IF(F45="Alto",IF(G45="Alta","I — Invest","M — Migrate"),IF(G45="Alta","T — Tolerate","E — Eliminate"))) -> M — Migrate | I45: =IF(H45="","",IF(H45="I — Invest","R6 — Refactor",IF(H45="M — Migrate","R4 — Replatform",IF(H45="T — Tolerate","Retain","Retire")))) -> R4 — Replatform | J45: =IF(H45="","",IF(H45="M — Migrate","🔴 Alta",IF(H45="I — Invest","🟡 Media-Alta",IF(H45="T — Tolerate","🟢 Baja","⚪ Descomisionar")))) -> 🔴 Alta
A46: 45 | B46: Izypay | C46: Santander Consumer Perú | E46: PAGOS | H46: =IF(OR(F46="",G46=""),"",IF(F46="Alto",IF(G46="Alta","I — Invest","M — Migrate"),IF(G46="Alta","T — Tolerate","E — Eliminate"))) | I46: =IF(H46="","",IF(H46="I — Invest","R6 — Refactor",IF(H46="M — Migrate","R4 — Replatform",IF(H46="T — Tolerate","Retain","Retire")))) | J46: =IF(H46="","",IF(H46="M — Migrate","🔴 Alta",IF(H46="I — Invest","🟡 Media-Alta",IF(H46="T — Tolerate","🟢 Baja","⚪ Descomisionar"))))
A47: 46 | B47: Kasnet | C47: Santander Consumer Perú | D47: Business | E47: Corresponsalia | F47: Alto | G47: Alta | H47: =IF(OR(F47="",G47=""),"",IF(F47="Alto",IF(G47="Alta","I — Invest","M — Migrate"),IF(G47="Alta","T — Tolerate","E — Eliminate"))) -> I — Invest | I47: =IF(H47="","",IF(H47="I — Invest","R6 — Refactor",IF(H47="M — Migrate","R4 — Replatform",IF(H47="T — Tolerate","Retain","Retire")))) -> R6 — Refactor | J47: =IF(H47="","",IF(H47="M — Migrate","🔴 Alta",IF(H47="I — Invest","🟡 Media-Alta",IF(H47="T — Tolerate","🟢 Baja","⚪ Descomisionar")))) -> 🟡 Media-Alta
A48: 47 | B48: ChatBot | C48: Santander Consumer Perú | E48: CANALES DIGITALES | H48: =IF(OR(F48="",G48=""),"",IF(F48="Alto",IF(G48="Alta","I — Invest","M — Migrate"),IF(G48="Alta","T — Tolerate","E — Eliminate"))) | I48: =IF(H48="","",IF(H48="I — Invest","R6 — Refactor",IF(H48="M — Migrate","R4 — Replatform",IF(H48="T — Tolerate","Retain","Retire")))) | J48: =IF(H48="","",IF(H48="M — Migrate","🔴 Alta",IF(H48="I — Invest","🟡 Media-Alta",IF(H48="T — Tolerate","🟢 Baja","⚪ Descomisionar"))))
A49: 48 | B49: Data Riesgos | C49: Santander Consumer Perú | E49: Riesgos | H49: =IF(OR(F49="",G49=""),"",IF(F49="Alto",IF(G49="Alta","I — Invest","M — Migrate"),IF(G49="Alta","T — Tolerate","E — Eliminate"))) | I49: =IF(H49="","",IF(H49="I — Invest","R6 — Refactor",IF(H49="M — Migrate","R4 — Replatform",IF(H49="T — Tolerate","Retain","Retire")))) | J49: =IF(H49="","",IF(H49="M — Migrate","🔴 Alta",IF(H49="I — Invest","🟡 Media-Alta",IF(H49="T — Tolerate","🟢 Baja","⚪ Descomisionar"))))
A50: 49 | B50: API OTP | C50: Santander Consumer Perú | D50: Business | F50: Bajo | G50: Baja | H50: =IF(OR(F50="",G50=""),"",IF(F50="Alto",IF(G50="Alta","I — Invest","M — Migrate"),IF(G50="Alta","T — Tolerate","E — Eliminate"))) -> E — Eliminate | I50: =IF(H50="","",IF(H50="I — Invest","R6 — Refactor",IF(H50="M — Migrate","R4 — Replatform",IF(H50="T — Tolerate","Retain","Retire")))) -> Retire | J50: =IF(H50="","",IF(H50="M — Migrate","🔴 Alta",IF(H50="I — Invest","🟡 Media-Alta",IF(H50="T — Tolerate","🟢 Baja","⚪ Descomisionar")))) -> ⚪ Descomisionar | K50: Migrate
A51: 50 | B51: API Portal | C51: Santander Consumer Perú | D51: Business | F51: Bajo | G51: Alta | H51: =IF(OR(F51="",G51=""),"",IF(F51="Alto",IF(G51="Alta","I — Invest","M — Migrate"),IF(G51="Alta","T — Tolerate","E — Eliminate"))) -> T — Tolerate | I51: =IF(H51="","",IF(H51="I — Invest","R6 — Refactor",IF(H51="M — Migrate","R4 — Replatform",IF(H51="T — Tolerate","Retain","Retire")))) -> Retain | J51: =IF(H51="","",IF(H51="M — Migrate","🔴 Alta",IF(H51="I — Invest","🟡 Media-Alta",IF(H51="T — Tolerate","🟢 Baja","⚪ Descomisionar")))) -> 🟢 Baja | K51: Migrate
A52: =A51+1 -> 51 | B52: Venta Cartera | C52: Santander Consumer Perú | D52: Business | E52: FUERZA VENTA | F52: Bajo | G52: Baja | H52: =IF(OR(F52="",G52=""),"",IF(F52="Alto",IF(G52="Alta","I — Invest","M — Migrate"),IF(G52="Alta","T — Tolerate","E — Eliminate"))) -> E — Eliminate | I52: =IF(H52="","",IF(H52="I — Invest","R6 — Refactor",IF(H52="M — Migrate","R4 — Replatform",IF(H52="T — Tolerate","Retain","Retire")))) -> Retire | J52: =IF(H52="","",IF(H52="M — Migrate","🔴 Alta",IF(H52="I — Invest","🟡 Media-Alta",IF(H52="T — Tolerate","🟢 Baja","⚪ Descomisionar")))) -> ⚪ Descomisionar | K52: Migrate
A53: =A52+1 -> 52 | B53: Virtual Assistant P&C | C53: Santander Perú | D53: Front | E53: Help Desk | F53: Bajo | H53: =IF(OR(F53="",G53=""),"",IF(F53="Alto",IF(G53="Alta","I — Invest","M — Migrate"),IF(G53="Alta","T — Tolerate","E — Eliminate"))) | I53: =IF(H53="","",IF(H53="I — Invest","R6 — Refactor",IF(H53="M — Migrate","R4 — Replatform",IF(H53="T — Tolerate","Retain","Retire")))) | J53: =IF(H53="","",IF(H53="M — Migrate","🔴 Alta",IF(H53="I — Invest","🟡 Media-Alta",IF(H53="T — Tolerate","🟢 Baja","⚪ Descomisionar")))) | K53: Tolerate
A54: =A53+1 -> 53 | B54: Masterbase | C54: Santander Perú | D54: Front | E54: Canal Asistido | F54: Bajo | G54: Alta | H54: =IF(OR(F54="",G54=""),"",IF(F54="Alto",IF(G54="Alta","I — Invest","M — Migrate"),IF(G54="Alta","T — Tolerate","E — Eliminate"))) -> T — Tolerate | I54: =IF(H54="","",IF(H54="I — Invest","R6 — Refactor",IF(H54="M — Migrate","R4 — Replatform",IF(H54="T — Tolerate","Retain","Retire")))) -> Retain | J54: =IF(H54="","",IF(H54="M — Migrate","🔴 Alta",IF(H54="I — Invest","🟡 Media-Alta",IF(H54="T — Tolerate","🟢 Baja","⚪ Descomisionar")))) -> 🟢 Baja | K54: Migrate
A55: =A54+1 -> 54 | B55: Data Analytics | C55: Santander Perú | D55: Transversal | E55: DATALAKE | F55: Bajo | G55: Baja | H55: =IF(OR(F55="",G55=""),"",IF(F55="Alto",IF(G55="Alta","I — Invest","M — Migrate"),IF(G55="Alta","T — Tolerate","E — Eliminate"))) -> E — Eliminate | I55: =IF(H55="","",IF(H55="I — Invest","R6 — Refactor",IF(H55="M — Migrate","R4 — Replatform",IF(H55="T — Tolerate","Retain","Retire")))) -> Retire | J55: =IF(H55="","",IF(H55="M — Migrate","🔴 Alta",IF(H55="I — Invest","🟡 Media-Alta",IF(H55="T — Tolerate","🟢 Baja","⚪ Descomisionar")))) -> ⚪ Descomisionar | K55: Migrate
A56: =A55+1 -> 55 | B56: Gestión Portafolio PMO | C56: Santander Perú | D56: Transversal | E56: MIS | F56: Alto | G56: Alta | H56: =IF(OR(F56="",G56=""),"",IF(F56="Alto",IF(G56="Alta","I — Invest","M — Migrate"),IF(G56="Alta","T — Tolerate","E — Eliminate"))) -> I — Invest | I56: =IF(H56="","",IF(H56="I — Invest","R6 — Refactor",IF(H56="M — Migrate","R4 — Replatform",IF(H56="T — Tolerate","Retain","Retire")))) -> R6 — Refactor | J56: =IF(H56="","",IF(H56="M — Migrate","🔴 Alta",IF(H56="I — Invest","🟡 Media-Alta",IF(H56="T — Tolerate","🟢 Baja","⚪ Descomisionar")))) -> 🟡 Media-Alta | K56: Tolerate
A57: =A56+1 -> 56 | B57: Lynx | C57: Santander Perú | D57: Transversal | E57: Fraudes | F57: Alto | G57: Alta | H57: =IF(OR(F57="",G57=""),"",IF(F57="Alto",IF(G57="Alta","I — Invest","M — Migrate"),IF(G57="Alta","T — Tolerate","E — Eliminate"))) -> I — Invest | I57: =IF(H57="","",IF(H57="I — Invest","R6 — Refactor",IF(H57="M — Migrate","R4 — Replatform",IF(H57="T — Tolerate","Retain","Retire")))) -> R6 — Refactor | J57: =IF(H57="","",IF(H57="M — Migrate","🔴 Alta",IF(H57="I — Invest","🟡 Media-Alta",IF(H57="T — Tolerate","🟢 Baja","⚪ Descomisionar")))) -> 🟡 Media-Alta | K57: Invest
A58: =A57+1 -> 57 | B58: Astara/SK Berge | C58: Santander Perú | D58: Business | E58: Canal Asistido | H58: =IF(OR(F58="",G58=""),"",IF(F58="Alto",IF(G58="Alta","I — Invest","M — Migrate"),IF(G58="Alta","T — Tolerate","E — Eliminate"))) | I58: =IF(H58="","",IF(H58="I — Invest","R6 — Refactor",IF(H58="M — Migrate","R4 — Replatform",IF(H58="T — Tolerate","Retain","Retire")))) | J58: =IF(H58="","",IF(H58="M — Migrate","🔴 Alta",IF(H58="I — Invest","🟡 Media-Alta",IF(H58="T — Tolerate","🟢 Baja","⚪ Descomisionar"))))
A59: =A58+1 -> 58 | B59: Factoring Data Lake Leads | C59: Santander Perú | D59: Transversal | E59: DATALAKE | H59: =IF(OR(F59="",G59=""),"",IF(F59="Alto",IF(G59="Alta","I — Invest","M — Migrate"),IF(G59="Alta","T — Tolerate","E — Eliminate"))) | I59: =IF(H59="","",IF(H59="I — Invest","R6 — Refactor",IF(H59="M — Migrate","R4 — Replatform",IF(H59="T — Tolerate","Retain","Retire")))) | J59: =IF(H59="","",IF(H59="M — Migrate","🔴 Alta",IF(H59="I — Invest","🟡 Media-Alta",IF(H59="T — Tolerate","🟢 Baja","⚪ Descomisionar"))))
A60: =A59+1 -> 59 | B60: Monitor Plus (ETL) - Transaction Monitorig | C60: Santander Perú | D60: Transversal | E60: FCC | F60: Bajo | G60: Baja | H60: =IF(OR(F60="",G60=""),"",IF(F60="Alto",IF(G60="Alta","I — Invest","M — Migrate"),IF(G60="Alta","T — Tolerate","E — Eliminate"))) -> E — Eliminate | I60: =IF(H60="","",IF(H60="I — Invest","R6 — Refactor",IF(H60="M — Migrate","R4 — Replatform",IF(H60="T — Tolerate","Retain","Retire")))) -> Retire | J60: =IF(H60="","",IF(H60="M — Migrate","🔴 Alta",IF(H60="I — Invest","🟡 Media-Alta",IF(H60="T — Tolerate","🟢 Baja","⚪ Descomisionar")))) -> ⚪ Descomisionar | K60: Migrate
A61: =A60+1 -> 60 | B61: Dashboards Analytics | C61: Santander Perú | D61: Transversal | E61: DATALAKE | H61: =IF(OR(F61="",G61=""),"",IF(F61="Alto",IF(G61="Alta","I — Invest","M — Migrate"),IF(G61="Alta","T — Tolerate","E — Eliminate"))) | I61: =IF(H61="","",IF(H61="I — Invest","R6 — Refactor",IF(H61="M — Migrate","R4 — Replatform",IF(H61="T — Tolerate","Retain","Retire")))) | J61: =IF(H61="","",IF(H61="M — Migrate","🔴 Alta",IF(H61="I — Invest","🟡 Media-Alta",IF(H61="T — Tolerate","🟢 Baja","⚪ Descomisionar"))))
A62: =A61+1 -> 61 | B62: Loan Tape | C62: Santander Perú | D62: Transversal | E62: MIS | F62: Bajo | G62: Baja | H62: =IF(OR(F62="",G62=""),"",IF(F62="Alto",IF(G62="Alta","I — Invest","M — Migrate"),IF(G62="Alta","T — Tolerate","E — Eliminate"))) -> E — Eliminate | I62: =IF(H62="","",IF(H62="I — Invest","R6 — Refactor",IF(H62="M — Migrate","R4 — Replatform",IF(H62="T — Tolerate","Retain","Retire")))) -> Retire | J62: =IF(H62="","",IF(H62="M — Migrate","🔴 Alta",IF(H62="I — Invest","🟡 Media-Alta",IF(H62="T — Tolerate","🟢 Baja","⚪ Descomisionar")))) -> ⚪ Descomisionar | K62: Migrate
A63: =A62+1 -> 62 | B63: Hiperfirmas | C63: Santander Perú | D63: Front | E63: Procesos | H63: =IF(OR(F63="",G63=""),"",IF(F63="Alto",IF(G63="Alta","I — Invest","M — Migrate"),IF(G63="Alta","T — Tolerate","E — Eliminate"))) | I63: =IF(H63="","",IF(H63="I — Invest","R6 — Refactor",IF(H63="M — Migrate","R4 — Replatform",IF(H63="T — Tolerate","Retain","Retire")))) | J63: =IF(H63="","",IF(H63="M — Migrate","🔴 Alta",IF(H63="I — Invest","🟡 Media-Alta",IF(H63="T — Tolerate","🟢 Baja","⚪ Descomisionar"))))
A64: =A63+1 -> 63 | B64: Web Onboarding | C64: Santander Perú | D64: Front | E64: CANALES DIGITALES | F64: Bajo | G64: Baja | H64: =IF(OR(F64="",G64=""),"",IF(F64="Alto",IF(G64="Alta","I — Invest","M — Migrate"),IF(G64="Alta","T — Tolerate","E — Eliminate"))) -> E — Eliminate | I64: =IF(H64="","",IF(H64="I — Invest","R6 — Refactor",IF(H64="M — Migrate","R4 — Replatform",IF(H64="T — Tolerate","Retain","Retire")))) -> Retire | J64: =IF(H64="","",IF(H64="M — Migrate","🔴 Alta",IF(H64="I — Invest","🟡 Media-Alta",IF(H64="T — Tolerate","🟢 Baja","⚪ Descomisionar")))) -> ⚪ Descomisionar | K64: Migrate
A65: =A64+1 -> 64 | B65: LBTR Novatronic | C65: Santander Perú | D65: Business | E65: PAGOS | F65: Alto | G65: Alta | H65: =IF(OR(F65="",G65=""),"",IF(F65="Alto",IF(G65="Alta","I — Invest","M — Migrate"),IF(G65="Alta","T — Tolerate","E — Eliminate"))) -> I — Invest | I65: =IF(H65="","",IF(H65="I — Invest","R6 — Refactor",IF(H65="M — Migrate","R4 — Replatform",IF(H65="T — Tolerate","Retain","Retire")))) -> R6 — Refactor | J65: =IF(H65="","",IF(H65="M — Migrate","🔴 Alta",IF(H65="I — Invest","🟡 Media-Alta",IF(H65="T — Tolerate","🟢 Baja","⚪ Descomisionar")))) -> 🟡 Media-Alta | K65: Invest
A66: =A65+1 -> 65 | B66: Web Pago Interno | C66: Santander Perú | D66: Business | E66: PAGOS | F66: Bajo | G66: Alta | H66: =IF(OR(F66="",G66=""),"",IF(F66="Alto",IF(G66="Alta","I — Invest","M — Migrate"),IF(G66="Alta","T — Tolerate","E — Eliminate"))) -> T — Tolerate | I66: =IF(H66="","",IF(H66="I — Invest","R6 — Refactor",IF(H66="M — Migrate","R4 — Replatform",IF(H66="T — Tolerate","Retain","Retire")))) -> Retain | J66: =IF(H66="","",IF(H66="M — Migrate","🔴 Alta",IF(H66="I — Invest","🟡 Media-Alta",IF(H66="T — Tolerate","🟢 Baja","⚪ Descomisionar")))) -> 🟢 Baja | K66: Tolerate
A67: =A66+1 -> 66 | B67: Retenciones SUNAT | C67: Santander Perú | D67: Transversal | E67: Riesgos | F67: Bajo | G67: Baja | H67: =IF(OR(F67="",G67=""),"",IF(F67="Alto",IF(G67="Alta","I — Invest","M — Migrate"),IF(G67="Alta","T — Tolerate","E — Eliminate"))) -> E — Eliminate | I67: =IF(H67="","",IF(H67="I — Invest","R6 — Refactor",IF(H67="M — Migrate","R4 — Replatform",IF(H67="T — Tolerate","Retain","Retire")))) -> Retire | J67: =IF(H67="","",IF(H67="M — Migrate","🔴 Alta",IF(H67="I — Invest","🟡 Media-Alta",IF(H67="T — Tolerate","🟢 Baja","⚪ Descomisionar")))) -> ⚪ Descomisionar | K67: Tolerate
A68: =A67+1 -> 67 | B68: Facturas Negociables | C68: Santander Perú | D68: Business | E68: CANALES DIGITALES | F68: Bajo | G68: Alta | H68: =IF(OR(F68="",G68=""),"",IF(F68="Alto",IF(G68="Alta","I — Invest","M — Migrate"),IF(G68="Alta","T — Tolerate","E — Eliminate"))) -> T — Tolerate | I68: =IF(H68="","",IF(H68="I — Invest","R6 — Refactor",IF(H68="M — Migrate","R4 — Replatform",IF(H68="T — Tolerate","Retain","Retire")))) -> Retain | J68: =IF(H68="","",IF(H68="M — Migrate","🔴 Alta",IF(H68="I — Invest","🟡 Media-Alta",IF(H68="T — Tolerate","🟢 Baja","⚪ Descomisionar")))) -> 🟢 Baja | K68: Migrate
A69: =A68+1 -> 68 | B69: GDS Modellica | C69: Santander Perú | D69: Transversal | E69: Riesgos | F69: Alto | G69: Alta | H69: =IF(OR(F69="",G69=""),"",IF(F69="Alto",IF(G69="Alta","I — Invest","M — Migrate"),IF(G69="Alta","T — Tolerate","E — Eliminate"))) -> I — Invest | I69: =IF(H69="","",IF(H69="I — Invest","R6 — Refactor",IF(H69="M — Migrate","R4 — Replatform",IF(H69="T — Tolerate","Retain","Retire")))) -> R6 — Refactor | J69: =IF(H69="","",IF(H69="M — Migrate","🔴 Alta",IF(H69="I — Invest","🟡 Media-Alta",IF(H69="T — Tolerate","🟢 Baja","⚪ Descomisionar")))) -> 🟡 Media-Alta | K69: Tolerate
A70: =A69+1 -> 69 | B70: Qlik Sense | C70: Santander Perú | D70: Transversal | E70: MIS | F70: Bajo | G70: Baja | H70: =IF(OR(F70="",G70=""),"",IF(F70="Alto",IF(G70="Alta","I — Invest","M — Migrate"),IF(G70="Alta","T — Tolerate","E — Eliminate"))) -> E — Eliminate | I70: =IF(H70="","",IF(H70="I — Invest","R6 — Refactor",IF(H70="M — Migrate","R4 — Replatform",IF(H70="T — Tolerate","Retain","Retire")))) -> Retire | J70: =IF(H70="","",IF(H70="M — Migrate","🔴 Alta",IF(H70="I — Invest","🟡 Media-Alta",IF(H70="T — Tolerate","🟢 Baja","⚪ Descomisionar")))) -> ⚪ Descomisionar | K70: Tolerate
A71: =A70+1 -> 70 | B71: Qlikview | C71: Santander Perú | D71: Transversal | E71: MIs | F71: Bajo | G71: Baja | H71: =IF(OR(F71="",G71=""),"",IF(F71="Alto",IF(G71="Alta","I — Invest","M — Migrate"),IF(G71="Alta","T — Tolerate","E — Eliminate"))) -> E — Eliminate | I71: =IF(H71="","",IF(H71="I — Invest","R6 — Refactor",IF(H71="M — Migrate","R4 — Replatform",IF(H71="T — Tolerate","Retain","Retire")))) -> Retire | J71: =IF(H71="","",IF(H71="M — Migrate","🔴 Alta",IF(H71="I — Invest","🟡 Media-Alta",IF(H71="T — Tolerate","🟢 Baja","⚪ Descomisionar")))) -> ⚪ Descomisionar | K71: Tolerate
A72: =A71+1 -> 71 | B72: DATATEC | C72: Santander Perú | D72: Front | E72: Tesorería | F72: Bajo | G72: Alta | H72: =IF(OR(F72="",G72=""),"",IF(F72="Alto",IF(G72="Alta","I — Invest","M — Migrate"),IF(G72="Alta","T — Tolerate","E — Eliminate"))) -> T — Tolerate | I72: =IF(H72="","",IF(H72="I — Invest","R6 — Refactor",IF(H72="M — Migrate","R4 — Replatform",IF(H72="T — Tolerate","Retain","Retire")))) -> Retain | J72: =IF(H72="","",IF(H72="M — Migrate","🔴 Alta",IF(H72="I — Invest","🟡 Media-Alta",IF(H72="T — Tolerate","🟢 Baja","⚪ Descomisionar")))) -> 🟢 Baja | K72: Tolerate
A73: =A72+1 -> 72 | B73: Data Lakehouse Corporativo | C73: Santander Perú | D73: Transversal | E73: DATALAKE | H73: =IF(OR(F73="",G73=""),"",IF(F73="Alto",IF(G73="Alta","I — Invest","M — Migrate"),IF(G73="Alta","T — Tolerate","E — Eliminate"))) | I73: =IF(H73="","",IF(H73="I — Invest","R6 — Refactor",IF(H73="M — Migrate","R4 — Replatform",IF(H73="T — Tolerate","Retain","Retire")))) | J73: =IF(H73="","",IF(H73="M — Migrate","🔴 Alta",IF(H73="I — Invest","🟡 Media-Alta",IF(H73="T — Tolerate","🟢 Baja","⚪ Descomisionar"))))
A74: =A73+1 -> 73 | B74: Lista Negativa | C74: Santander Perú | D74: Business | E74: Riesgos | F74: Bajo | G74: Alta | H74: =IF(OR(F74="",G74=""),"",IF(F74="Alto",IF(G74="Alta","I — Invest","M — Migrate"),IF(G74="Alta","T — Tolerate","E — Eliminate"))) -> T — Tolerate | I74: =IF(H74="","",IF(H74="I — Invest","R6 — Refactor",IF(H74="M — Migrate","R4 — Replatform",IF(H74="T — Tolerate","Retain","Retire")))) -> Retain | J74: =IF(H74="","",IF(H74="M — Migrate","🔴 Alta",IF(H74="I — Invest","🟡 Media-Alta",IF(H74="T — Tolerate","🟢 Baja","⚪ Descomisionar")))) -> 🟢 Baja | K74: Eliminate
A75: =A74+1 -> 74 | B75: Reporte Helios | C75: Santander Perú | D75: Transversal | E75: MIS | H75: =IF(OR(F75="",G75=""),"",IF(F75="Alto",IF(G75="Alta","I — Invest","M — Migrate"),IF(G75="Alta","T — Tolerate","E — Eliminate"))) | I75: =IF(H75="","",IF(H75="I — Invest","R6 — Refactor",IF(H75="M — Migrate","R4 — Replatform",IF(H75="T — Tolerate","Retain","Retire")))) | J75: =IF(H75="","",IF(H75="M — Migrate","🔴 Alta",IF(H75="I — Invest","🟡 Media-Alta",IF(H75="T — Tolerate","🟢 Baja","⚪ Descomisionar"))))
A76: =A75+1 -> 75 | B76: WorldSys | C76: Santander Perú | D76: Transversal | E76: FCC | H76: =IF(OR(F76="",G76=""),"",IF(F76="Alto",IF(G76="Alta","I — Invest","M — Migrate"),IF(G76="Alta","T — Tolerate","E — Eliminate"))) | I76: =IF(H76="","",IF(H76="I — Invest","R6 — Refactor",IF(H76="M — Migrate","R4 — Replatform",IF(H76="T — Tolerate","Retain","Retire")))) | J76: =IF(H76="","",IF(H76="M — Migrate","🔴 Alta",IF(H76="I — Invest","🟡 Media-Alta",IF(H76="T — Tolerate","🟢 Baja","⚪ Descomisionar"))))
A77: =A76+1 -> 76 | B77: AMLUpdate - Name Screening | C77: Santander Perú | D77: Transversal | E77: FCC | H77: =IF(OR(F77="",G77=""),"",IF(F77="Alto",IF(G77="Alta","I — Invest","M — Migrate"),IF(G77="Alta","T — Tolerate","E — Eliminate"))) | I77: =IF(H77="","",IF(H77="I — Invest","R6 — Refactor",IF(H77="M — Migrate","R4 — Replatform",IF(H77="T — Tolerate","Retain","Retire")))) | J77: =IF(H77="","",IF(H77="M — Migrate","🔴 Alta",IF(H77="I — Invest","🟡 Media-Alta",IF(H77="T — Tolerate","🟢 Baja","⚪ Descomisionar"))))
A78: =A77+1 -> 77 | B78: RatingPlus | C78: Santander Perú | D78: Transversal | E78: Riesgos | H78: =IF(OR(F78="",G78=""),"",IF(F78="Alto",IF(G78="Alta","I — Invest","M — Migrate"),IF(G78="Alta","T — Tolerate","E — Eliminate"))) | I78: =IF(H78="","",IF(H78="I — Invest","R6 — Refactor",IF(H78="M — Migrate","R4 — Replatform",IF(H78="T — Tolerate","Retain","Retire")))) | J78: =IF(H78="","",IF(H78="M — Migrate","🔴 Alta",IF(H78="I — Invest","🟡 Media-Alta",IF(H78="T — Tolerate","🟢 Baja","⚪ Descomisionar"))))
A79: =A78+1 -> 78 | B79: Zapier | C79: Santander Perú | D79: Transversal | E79: COBRANZAS | H79: =IF(OR(F79="",G79=""),"",IF(F79="Alto",IF(G79="Alta","I — Invest","M — Migrate"),IF(G79="Alta","T — Tolerate","E — Eliminate"))) | I79: =IF(H79="","",IF(H79="I — Invest","R6 — Refactor",IF(H79="M — Migrate","R4 — Replatform",IF(H79="T — Tolerate","Retain","Retire")))) | J79: =IF(H79="","",IF(H79="M — Migrate","🔴 Alta",IF(H79="I — Invest","🟡 Media-Alta",IF(H79="T — Tolerate","🟢 Baja","⚪ Descomisionar"))))
A81: =A80+1 -> 1 | B81: Web Institucional | C81: Santander Perú | D81: Front | E81: CANALES DIGITALES
A82: =A81+1 -> 2 | B82: Motor TOP | C82: Santander Perú | D82: Transversal | E82: Riesgos
A83: =A82+1 -> 3 | B83: Reporte Crediticio de Deudores | C83: Santander Perú | D83: Transversal | E83: Riesgos
A84: =A83+1 -> 4 | B84: Nazca AS400 | C84: Santander Perú | D84: Business | E84: CORE BANKING
A85: =A84+1 -> 5 | B85: Genesys Cloud | C85: Santander Perú | E85: MIS

Sheet 📈 Dashboard
B1: DASHBOARD — Resumen del Portfolio TIME
B3: Cuadrante | C3: Aplicaciones | D3: % del Total | E3: Estrategia | F3: Prioridad
B4: I — Invest | C4: =COUNTIF('📊 Portfolio'!H3:H51,"I — Invest") -> 8 | D4: =IF(C4=0,"—",TEXT(C4/COUNTA('📊 Portfolio'!F3:F51),"0%")) -> 25% | E4: R6 — Refactor | F4: Media-Alta
B5: M — Migrate | C5: =COUNTIF('📊 Portfolio'!H3:H51,"M — Migrate") -> 10 | D5: =IF(C5=0,"—",TEXT(C5/COUNTA('📊 Portfolio'!F3:F51),"0%")) -> 31% | E5: R4 — Replatform | F5: Alta
B6: T — Tolerate | C6: =COUNTIF('📊 Portfolio'!H3:H51,"T — Tolerate") -> 7 | D6: =IF(C6=0,"—",TEXT(C6/COUNTA('📊 Portfolio'!F3:F51),"0%")) -> 22% | E6: Retain | F6: Baja
B7: E — Eliminate | C7: =COUNTIF('📊 Portfolio'!H3:H51,"E — Eliminate") -> 7 | D7: =IF(C7=0,"—",TEXT(C7/COUNTA('📊 Portfolio'!F3:F51),"0%")) -> 22% | E7: Retire | F7: Descomisionar
B8: TOTAL | C8: =SUM(C4:C7) -> 32
B10: 📤 ¿CÓMO ANALIZAR CON CLAUDE?
B11: 1. Guarda este archivo Excel (Ctrl+S)
B12: 2. Abre Claude.ai en el navegador
B13: 3. Adjunta el archivo usando el ícono de clip (📎)
B14: 4. Escribe: "Analiza este portfolio TIME, dame un roadmap de migración priorizado, identifica riesgos y sugiere secuencia de implementación"
B15: 5. Claude leerá los datos, clasificará las apps y entregará recomendaciones concretas con argumentos técnicos
