Workbook
Name Applicatino_response: [1]Usage!$GE$2:$GE$7
Name Application_Age: '[1]Application Info'!$GF$2:$GF$7
Name Application_Age: '[1]Application Info'!$GF$2:$GF$7
Name Application_Age: '[1]Application Info'!$GF$2:$GF$7
Name Application_Age: '[1]Application Info'!$GF$2:$GF$7
Name Application_Age: '[1]Application Info'!$GF$2:$GF$7
Name Application_Age: '[1]Application Info'!$GF$2:$GF$7
Name Application_Age: '[1]Application Info'!$GF$2:$GF$7
Name Application_Age: 'Application Info'!$GF$2:$GF$7
Name Application_Complexity: '[1]Technical Info'!$GH$2:$GH$6
Name Application_Criticality: '[1]Business Info'!$GE$2:$GE$6
Name Application_Dev_Tech: '[1]Technical Info'!$GE$2:$GE$60
Name Application_last_accessed: [1]Maintenance!$GD$2:$GD$5
Name Application_Load_Variation: [1]Usage!$GG$2:$GG$4
Name Application_Type_EY: '[1]Application Info'!$GE$2:$GE$6
Name Application_Type_EY: '[1]Application Info'!$GE$2:$GE$6
Name Application_Type_EY: '[1]Application Info'!$GE$2:$GE$6
Name Application_Type_EY: '[1]Application Info'!$GE$2:$GE$6
Name Application_Type_EY: '[1]Application Info'!$GE$2:$GE$6
Name Application_Type_EY: '[1]Application Info'!$GE$2:$GE$6
Name Application_Type_EY: '[1]Application Info'!$GE$2:$GE$6
Name Application_Type_EY: 'Application Info'!$GE$2:$GE$6
Name Architecture_Style: '[1]Technical Info'!$GB$2:$GB$10
Name Audience: [1]Usage!$GC$2:$GC$5
Name Business_change_3_months: [1]Maintenance!$GC$2:$GC$7
Name business_layer: '[1]Technical Platforms'!$GB$2:$GB$91
Name Business_User_satisfication: '[1]Business Info'!$GI$2:$GI$6
Name Criticality_Interface: '[1]Technical Info'!$GG$2:$GG$9
Name data_layer: '[1]Technical Platforms'!$GC$2:$GC$58
Name Functional_Fitness: '[1]Business Info'!$GH$2:$GH$6
Name hardware_plat: '[1]Technical Platforms'!$GD$2:$GD$74
Name Infosec_Classification: '[1]Business Info'!$GF$2:$GF$6
Name Integration_architecture: '[1]Technical Info'!$GD$2:$GD$15
Name IT_portfolio: '[1]Application Info'!$GD$2:$GD$6
Name IT_portfolio: '[1]Application Info'!$GD$2:$GD$6
Name IT_portfolio: '[1]Application Info'!$GD$2:$GD$6
Name IT_portfolio: '[1]Application Info'!$GD$2:$GD$6
Name IT_portfolio: '[1]Application Info'!$GD$2:$GD$6
Name IT_portfolio: '[1]Application Info'!$GD$2:$GD$6
Name IT_portfolio: '[1]Application Info'!$GD$2:$GD$6
Name IT_portfolio: 'Application Info'!$GD$2:$GD$6
Name Line_Of_Business: '[1]Business Info'!$GC$2:$GC$2
Name Names: #REF!
Name Namess: #REF!
Name No_of_App_Users: [1]Usage!$GB$2:$GB$11
Name operating_sys: '[1]Technical Platforms'!$GE$2:$GE$38
Name Pace_Layer: '[1]Technical Info'!$GI$2:$GI$7
Name Presentation_Layer: '[1]Technical Info'!$GC$2:$GC$10
Name Programmin_tech: '[1]Technical Platforms'!$GF$2:$GF$67
Name Red_box: '[1]Application Info'!$GC$2:$GC$7
Name Red_box: '[1]Application Info'!$GC$2:$GC$7
Name Red_box: '[1]Application Info'!$GC$2:$GC$7
Name Red_box: '[1]Application Info'!$GC$2:$GC$7
Name Red_box: '[1]Application Info'!$GC$2:$GC$7
Name Red_box: '[1]Application Info'!$GC$2:$GC$7
Name Red_box: '[1]Application Info'!$GC$2:$GC$7
Name Red_box: 'Application Info'!$GC$2:$GC$7
Name Region: '[1]Application Info'!$GB$2:$GB$6
Name Region: '[1]Application Info'!$GB$2:$GB$6
Name Region: '[1]Application Info'!$GB$2:$GB$6

Sheet Application Info
A1: Tool Id | B1: Business Unit Name | C1: Application Name | D1: Application ID | E1: Application Name | F1: Application Description | G1: Region | H1: Hosting | I1: IT Portfolio | J1: IT Portfolio Owner | K1: Application Business SME | L1: Application Source | M1: Application Age (In Years) | N1: Application Status | O1: Vendor Name | P1: EOL (End of Life) for product | Q1: EOVS (End of Vendor Support) | FY1: Field Names | GB1: <b>Region</b> | GC1: <strong>Hosting</strong> | GD1: <b>IT Portfolio</b> | GE1: <b>Application Source</b> | GF1: <b>Application Age (In Years)</b> | GG1: <strong>Application Status</strong>
B2: Surgir | C2: SAP by Design | D2: APMF0001067852 | E2: =C2 -> SAP by Design | F2: Sistema ERP SAP para la gestión de procesos administrativos, financieros, contables y operativos. URL: https://my430488.businessbydesign.cloud.sap/sap/public/ap/ui/repository/SAP_UI/HTMLOBERON5/client.html | G2: Azure | H2: 5. SaaS | I2: Enterprise App | K2: =Stakeholders!E2 -> RENZO ALFREDO HUAYLLASCO CÁCERES | L2: Vendor Custom | M2: 0-3 yrs | N2: In Active | O2: =LOOKUP(C2,[2]APMT_Detalle!$B$82:$B$521,[2]APMT_Detalle!$S$2:$S$521) -> Santander Digital Services | R2: =LOOKUP(C2,[2]APMT_Detalle!$B$2:$B$521,[2]APMT_Detalle!$AP$2:$AP$521) -> External | FY2: ICTO_ID_App | GB2: Local Country | GC2: 1. Cloud | GD2: Infrastructure | GE2: COTS OOB | GF2: 0-3 yrs | GG2: Decommissioned
B3: Surgir | C3: App Surgir | D3: APMF0001066860 | E3: =C3 -> App Surgir | F3: Aplicativo utilizado por la red comercial para el ingreso de las solicitudes de créditos. | G3: Local Country | H3: 3. Hybrid cloud | I3: IT Application | K3: =Stakeholders!E3 -> RENZO ALFREDO HUAYLLASCO CÁCERES | L3: In House Developed | N3: In Active | O3: =LOOKUP(C3,[2]APMT_Detalle!$B$82:$B$521,[2]APMT_Detalle!$S$2:$S$521) -> #N/A | R3: =LOOKUP(C3,[2]APMT_Detalle!$B$2:$B$521,[2]APMT_Detalle!$AP$2:$AP$521) -> External | FY3: Business_Solution_App | GB3: US | GC3: 2. Desktop | GD3: Security | GE3: COTS Customized | GF3: 4-6 yrs | GG3: Duplicate
B4: Surgir | C4: App Cliente | D4: APMF0001065929 | E4: =C4 -> App Cliente | F4: App Cliente es una aplicación móvil que centraliza servicios bancarios y financieros, permitiendo a los usuarios gestionar su dinero, realizar transacciones, consultar saldos, pagar servicios desde un smartphone, ofreciendo comodidad, seguridad y ahorro de tiempo al reducir la necesidad de ir a oficinas físicas. | G4: Local Country | H4: 3. Hybrid cloud | I4: Enterprise App | K4: =Stakeholders!E4 -> YELTSIN ANTONY ALAN SOTELO CAMONES | L4: In House Developed | N4: In Active | O4: =LOOKUP(C4,[2]APMT_Detalle!$B$82:$B$521,[2]APMT_Detalle!$S$2:$S$521) -> #N/A | R4: =LOOKUP(C4,[2]APMT_Detalle!$B$2:$B$521,[2]APMT_Detalle!$AP$2:$AP$521) -> External | FY4: Business_Solution_Description | GB4: AWS | GC4: 3. Hybrid cloud | GD4: End User Computing | GE4: Vendor Custom | GF4: 7-10 yrs | GG4: In-Scope
B5: Surgir | C5: AMLUpdate - Name Screening | D5: APMF0001049960 | E5: =C5 -> AMLUpdate - Name Screening | F5: Plataforma para el cumplimiento de FCC utilizada para el cruce y migrar a One FCC verificación de listas de sanciones, personas y entidades restringidas, consumido por los procesos de AML del negocio de Surgir a través de: - API llamada por los procesos que requieren consultas de AML. - Portal donde el área usuaria local (PLAFT) consulta el histórico de llamadas. URL: https://new.amlupdate.com/ | G5: Mexico | H5: 8. On-Premise | K5: =Stakeholders!E5 -> RENZO ALFREDO HUAYLLASCO CÁCERES | L5: Vendor Custom | N5: In Active | O5: GESINTEL | R5: =LOOKUP(C5,[2]APMT_Detalle!$B$2:$B$521,[2]APMT_Detalle!$AP$2:$AP$521) -> #N/A | FY5: Red_box | GB5: Azure | GC5: 5. SaaS | GD5: Enterprise App | GE5: Not Applicable | GF5: >15 yrs | GG5: Out-of Scope
B6: Surgir | C6: Portal Web Público | D6: APMF0001022615 | E6: =C6 -> Portal Web Público | F6: Sitio web público del negocio de Surgir, que facilita informarción institucional de la compañía, muestra el catálogo de productos y permite a los clientes solicitar una llamada para iniciar su contratación. Es un sitio no transaccional. Se migrará a Landing Zone. https://www.surgir.com.pe/ | G6: Local Country | H6: 8. On-Premise | K6: =Stakeholders!E6 -> RENZO ALFREDO HUAYLLASCO CÁCERES | L6: In House Developed | N6: In Active | O6: =LOOKUP(C6,[2]APMT_Detalle!$B$82:$B$521,[2]APMT_Detalle!$S$2:$S$521) -> Santander Digital Services | R6: =LOOKUP(C6,[2]APMT_Detalle!$B$2:$B$521,[2]APMT_Detalle!$AP$2:$AP$521) -> Internal Cloud | FY6: IT_portfolio | GB6: Mexico | GC6: 6. Sharepoint | GD6: IT Application | GE6: In House Developed | GF6: Not Applicable | GG6: In Active
B7: Surgir | C7: Anura | D7: APMF0001022614 | E7: =C7 -> Anura | F7: Servicio de atención telefónica en la nube del proveedor ANURA, incluye el personal. Es un SaaS arrendado al proveedor. | G7: Local Country | H7: 5. SaaS | K7: =Stakeholders!E7 -> RENZO ALFREDO HUAYLLASCO CÁCERES | L7: COTS OOB | N7: In Active | O7: =LOOKUP(C7,[2]APMT_Detalle!$B$82:$B$521,[2]APMT_Detalle!$S$2:$S$521) -> #N/A | R7: =LOOKUP(C7,[2]APMT_Detalle!$B$2:$B$521,[2]APMT_Detalle!$AP$2:$AP$521) -> External | FY7: IT_portfolio_Owner | GB7: España | GC7: 7.Vendor sit | GF7: Not Available | GG7: Already on Cloud
B8: Surgir | C8: ERP Contanet | D8: APMF0001022612 | E8: =C8 -> ERP Contanet | F8: Sistema ERP utilizado por Surgir, el negocio de microemprendedores de Santander en Perú, para la gestión contable, financiera y administrativa. Permite registrar y controlar las operaciones del negocio, asegurando la trazabilidad, la integridad de la información y el cumplimiento de las normativas locales y corporativas. La BBDD se encuentra en la Nube de SURGIR, se encuentra en planes de migración a SAP Contanet. | G8: Azure | H8: 5. SaaS | K8: =Stakeholders!E8 -> RENZO ALFREDO HUAYLLASCO CÁCERES | L8: In House Developed | N8: In Active | O8: =LOOKUP(C8,[2]APMT_Detalle!$B$82:$B$521,[2]APMT_Detalle!$S$2:$S$521) -> Vector | R8: =LOOKUP(C8,[2]APMT_Detalle!$B$2:$B$521,[2]APMT_Detalle!$AP$2:$AP$521) -> Internal Cloud | FY8: Application_SME | GC8: 8. On-Premise | GG8: To be Retired
B9: Surgir | C9: Datalake | D9: APMF0001022613 | E9: =C9 -> Datalake | F9: Datalake en el que se almacenan datos generados por el core COBIS para generar informes regulatorios de pagos. Se encuentra en la Nube de SURGIR y se encuentra en el plan de migración a Landing Zone. | G9: Local Country | H9: 3. Hybrid cloud | K9: =Stakeholders!E9 -> RENZO ALFREDO HUAYLLASCO CÁCERES | L9: In House Developed | N9: In Active | O9: =LOOKUP(C9,[2]APMT_Detalle!$B$82:$B$521,[2]APMT_Detalle!$S$2:$S$521) -> Santander Digital Services | R9: =LOOKUP(C9,[2]APMT_Detalle!$B$2:$B$521,[2]APMT_Detalle!$AP$2:$AP$521) -> External | FY9: Application_Type_EY
B10: Surgir | C10: Cobis | D10: APMF0001022611 | E10: =C10 -> Cobis | F10: Sistema Core Bancario modular permite gestionar los productos y servicios financieros del negocio Surgir (cuentas de ahorro, seguros de ahorro, depósitos a plazo y créditos), dirigidas a negocios de emprendedores unipersonales. Es un SaaS en AWS del propio proveedro COBIS TOPAZ. URL: https://www.web.surgir-pe.cobiscloud.com/CWC/services/cobis/web/bank/views/commons/login.html? | G10: AWS | H10: 3. Hybrid cloud | K10: =Stakeholders!E10 -> RENZO ALFREDO HUAYLLASCO CÁCERES | L10: Vendor Custom | N10: In Active | O10: =LOOKUP(C10,[2]APMT_Detalle!$B$82:$B$521,[2]APMT_Detalle!$S$2:$S$521) -> Sentinel Peru | R10: =LOOKUP(C10,[2]APMT_Detalle!$B$2:$B$521,[2]APMT_Detalle!$AP$2:$AP$521) -> External | FY10: Application_Age
B11: Santander Fondos Colectivos | C11: Emblue | D11: APMF0001067771 | E11: =C11 -> Emblue | F11: Servicio de Plantillas para envío de correo electrónico del proveedor Emblue, que permite la captura de acciones del usuario final (abrir mensaje - similar a Danna Connect) | G11: Local Country | H11: 7.Vendor sit | K11: =Stakeholders!E11 -> Luis Alberto Barandiaran | L11: Vendor Custom | N11: In Active | O11: =LOOKUP(C11,[2]APMT_Detalle!$B$82:$B$521,[2]APMT_Detalle!$S$2:$S$521) -> Vector | R11: =LOOKUP(C11,[2]APMT_Detalle!$B$2:$B$521,[2]APMT_Detalle!$AP$2:$AP$521) -> Internal Cloud | FY11: TOPAZ_Indicator
B12: Santander Fondos Colectivos | C12: Facephi | D12: APMF0001067770 | E12: =C12 -> Facephi | F12: Servicio de validación de morfología de documentos de identidad, validación de identidad por biometría, y servicio de firma digital del proveedor Facephi, utilizado por la aplicación Core Santo. | G12: Local Country | H12: 7.Vendor sit | K12: =Stakeholders!E12 -> Luis Alberto Barandiaran | L12: Vendor Custom | N12: In Active | O12: =LOOKUP(C12,[2]APMT_Detalle!$B$82:$B$521,[2]APMT_Detalle!$S$2:$S$521) -> Vector | R12: =LOOKUP(C12,[2]APMT_Detalle!$B$2:$B$521,[2]APMT_Detalle!$AP$2:$AP$521) -> On Premises | FY12: End_of_life
B13: Santander Fondos Colectivos | C13: Mapfre | D13: APMF0001067527 | E13: =C13 -> Mapfre | F13: Servicio de emisión y gestión de seguros con el proveedor Seguros Mapfre (API y Plataforma de Servicios). | G13: Local Country | H13: 5. SaaS | K13: =Stakeholders!E13 -> LUIS BOULLON GARCIA | L13: In House Developed | N13: In Active | O13: =LOOKUP(C13,[2]APMT_Detalle!$B$82:$B$521,[2]APMT_Detalle!$S$2:$S$521) -> Externo | R13: =LOOKUP(C13,[2]APMT_Detalle!$B$2:$B$521,[2]APMT_Detalle!$AP$2:$AP$521) -> On Premises | FY13: End_of_Vendor_Support
B14: Santander Fondos Colectivos | C14: Tracklink | D14: APMF0001067523 | E14: =C14 -> Tracklink | F14: Servicio (API) de instalación y gestión de GPS con el proveedor Tracklink (Instalación de GPS a los vehiculos). | G14: Local Country | H14: 7.Vendor sit | K14: =Stakeholders!E14 -> LUIS BOULLON GARCIA | L14: Vendor Custom | N14: In Active | O14: =LOOKUP(C14,[2]APMT_Detalle!$B$82:$B$521,[2]APMT_Detalle!$S$2:$S$521) -> MICROSOFT | R14: =LOOKUP(C14,[2]APMT_Detalle!$B$2:$B$521,[2]APMT_Detalle!$AP$2:$AP$521) -> Internal Cloud
B15: Santander Fondos Colectivos | C15: Docuclass | D15: APMF0001067521 | E15: =C15 -> Docuclass | F15: Servicio de administración de documentos integrado del proveedor DocuClass. | G15: Local Country | H15: 8. On-Premise | K15: =Stakeholders!E15 -> LUIS BOULLON GARCIA | L15: In House Developed | N15: In Active | O15: =LOOKUP(C15,[2]APMT_Detalle!$B$82:$B$521,[2]APMT_Detalle!$S$2:$S$521) -> Santander Digital Services | R15: =LOOKUP(C15,[2]APMT_Detalle!$B$2:$B$521,[2]APMT_Detalle!$AP$2:$AP$521) -> External
B16: Santander Fondos Colectivos | C16: Diloo | D16: APMF0001067520 | E16: =C16 -> Diloo | F16: Servicio de envío de mensajería por SMS del proveedor Diloo. | G16: US | H16: 7.Vendor sit | K16: =Stakeholders!E16 -> LUIS BOULLON GARCIA | L16: Vendor Custom | N16: In Active | O16: =LOOKUP(C16,[2]APMT_Detalle!$B$82:$B$521,[2]APMT_Detalle!$S$2:$S$521) -> Santander Digital Services | R16: =LOOKUP(C16,[2]APMT_Detalle!$B$2:$B$521,[2]APMT_Detalle!$AP$2:$AP$521) -> External
B17: Santander Fondos Colectivos | C17: Izipay Pagos en línea | D17: APMF0001067419 | E17: =C17 -> Izipay Pagos en línea | F17: Servicio de pagos en línea del proveedor Izipay | G17: Local Country | H17: 3. Hybrid cloud | K17: =Stakeholders!E17 -> Luis Alberto Barandiaran | L17: COTS Customized | N17: In Active | O17: =LOOKUP(C17,[2]APMT_Detalle!$B$82:$B$521,[2]APMT_Detalle!$S$2:$S$521) -> Externo | R17: =LOOKUP(C17,[2]APMT_Detalle!$B$2:$B$521,[2]APMT_Detalle!$AP$2:$AP$521) -> On Premises
B18: Santander Fondos Colectivos | C18: IBK Recaudación | D18: APMF0001067418 | E18: =C18 -> IBK Recaudación | F18: Servicio de recaudación bancaria del proveedor Banco INTERBANK (Archivo con información enviado por FTP para la recaudación de Fondos Colectivos). | G18: Local Country | H18: 8. On-Premise | K18: =Stakeholders!E18 -> Luis Alberto Barandiaran | L18: COTS Customized | N18: In Active | O18: =LOOKUP(C18,[2]APMT_Detalle!$B$82:$B$521,[2]APMT_Detalle!$S$2:$S$521) -> Externo | R18: =LOOKUP(C18,[2]APMT_Detalle!$B$2:$B$521,[2]APMT_Detalle!$AP$2:$AP$521) -> On Premises
B19: Santander Fondos Colectivos | C19: SAP by Design | D19: APMF0001067032 | E19: =C19 -> SAP by Design | F19: Sistema ERP SAP para la gestión de procesos administrativos, financieros, contables y operativos. URL: https://my430488.businessbydesign.cloud.sap/sap/public/ap/ui/repository/SAP_UI/HTMLOBERON5/client.html | G19: Mexico | H19: 5. SaaS | K19: =Stakeholders!E19 -> Luis Alberto Barandiaran | L19: Vendor Custom | N19: In Active | O19: =LOOKUP(C19,[2]APMT_Detalle!$B$82:$B$521,[2]APMT_Detalle!$S$2:$S$521) -> Santander Digital Services | R19: =LOOKUP(C19,[2]APMT_Detalle!$B$2:$B$521,[2]APMT_Detalle!$AP$2:$AP$521) -> External
B20: Santander Fondos Colectivos | C20: Portal Web Público | D20: APMF0001065693 | E20: =C20 -> Portal Web Público | F20: Página Web Pública (Solo es informativo), solución táctica, en base al desarrollo de surgir 2024, alojado en Azure SURGIR, para realizar cambios es necesario la aprobación del comité. URL: http://www.santanderfondoscolectivos.com.pe/ | G20: Mexico | H20: 8. On-Premise | K20: =Stakeholders!E20 -> Luis Alberto Barandiaran | L20: In House Developed | N20: In Active | O20: =LOOKUP(C20,[2]APMT_Detalle!$B$82:$B$521,[2]APMT_Detalle!$S$2:$S$521) -> Santander Digital Services | R20: =LOOKUP(C20,[2]APMT_Detalle!$B$2:$B$521,[2]APMT_Detalle!$AP$2:$AP$521) -> Internal Cloud
B21: Santander Fondos Colectivos | C21: AMLUpdate - Name Screening | D21: APMF0001055717 | E21: =C21 -> AMLUpdate - Name Screening | F21: Plataforma para el cumplimiento de FCC utilizada para el cruce y migrar a One FCC verificación de listas de sanciones, personas y entidades restringidas, consumido por los procesos de AML del negocio de Fondos Colectivos a través de: - API llamada por los procesos que requieren consultas de AML. - Portal donde el área usuaria local (PLAFT) consulta el histórico de llamadas. URL: https://new.amlupdate.com/ | G21: Local Country | H21: 5. SaaS | K21: =Stakeholders!E21 -> ALONSO GUILLERMO SERRANO CARMONA | L21: In House Developed | N21: In Active | O21: GESINTEL | R21: =LOOKUP(C21,[2]APMT_Detalle!$B$2:$B$521,[2]APMT_Detalle!$AP$2:$AP$521) -> #N/A
B22: Santander Fondos Colectivos | C22: Santo | D22: APMF0001045007 | E22: =C22 -> Santo | F22: Sistema principal de Fondos Colectivos provisto por el proveedor SoftTek, integrado a Azure AD, base de datos Azure SQL (Costo de Infra + Costo de Servicio). - Core: Sistema utilizado por los equipos de operaciones y contabilidad - Front: Sistema utilizado por los ejecutivos de ventas y operaciones - Plaft: Sistema utilizado por el equipo de Plaft para la configuración de reglas y monitoreo de transacciones - Firma: Web donde los clientes se autentican con su usuario, documento de identidad e identificación biométrica para firmar digitalmente los documentos de la empresa - Pagos: Web donde los clientes visualizan los pagos pendientes a realizar y efectúan los pagos de sus obligaciones pendientes - Reclamos: Sistema utilizado por el equipo de operaciones para la gestión de requerimientos y reclamos | G22: Local Country | H22: 3. Hybrid cloud | K22: =Stakeholders!E22 -> LUIS BOULLON GARCIA | L22: COTS Customized | N22: In Active | O22: =LOOKUP(C22,[2]APMT_Detalle!$B$82:$B$521,[2]APMT_Detalle!$S$2:$S$521) -> Santander Digital Services | R22: =LOOKUP(C22,[2]APMT_Detalle!$B$2:$B$521,[2]APMT_Detalle!$AP$2:$AP$521) -> External
B23: SCIB Perú | C23: Nuevo Office Banking | D23: APMF0001038152 | E23: =C23 -> Nuevo Office Banking | F23: Herramienta del nuevo OOBB alojada en la LZONE. | G23: US | H23: 5. SaaS | K23: =Stakeholders!E23 -> ALFREDO LLONA ARIS | L23: In House Developed | N23: In Active | O23: =LOOKUP(C23,[2]APMT_Detalle!$B$82:$B$521,[2]APMT_Detalle!$S$2:$S$521) -> Externo | R23: =LOOKUP(C23,[2]APMT_Detalle!$B$2:$B$521,[2]APMT_Detalle!$AP$2:$AP$521) -> On Premises
B24: SCIB Perú | C24: CEEFFC | D24: APMF0001021795 | E24: =C24 -> CEEFFC | F24: Central de Estados financieros de clientes (Interno), Alberga los estados de cuenta de clientes gestionados por el área comercial para el área de Riesgos. | G24: Mexico | H24: 8. On-Premise | K24: =Stakeholders!E24 -> LUIS CONTRERAS AVILA | L24: In House Developed | N24: In Active | O24: =LOOKUP(C24,[2]APMT_Detalle!$B$82:$B$521,[2]APMT_Detalle!$S$2:$S$521) -> #N/A | R24: =LOOKUP(C24,[2]APMT_Detalle!$B$2:$B$521,[2]APMT_Detalle!$AP$2:$AP$521) -> External
B25: SCIB Perú | C25: Lbtr | D25: APMF0001013067 | E25: =C25 -> Lbtr | F25: Gestión y realización de transferencias interbancarias BCRP. | G25: Local Country | H25: 8. On-Premise | K25: =Stakeholders!E25 -> ALFREDO LLONA ARIS | L25: Vendor Custom | N25: In Active | O25: =LOOKUP(C25,[2]APMT_Detalle!$B$82:$B$521,[2]APMT_Detalle!$S$2:$S$521) -> Externo | R25: =LOOKUP(C25,[2]APMT_Detalle!$B$2:$B$521,[2]APMT_Detalle!$AP$2:$AP$521) -> On Premises
B26: SCIB Perú | C26: Cash Nexus | D26: APMF0001013065 | E26: =C26 -> Cash Nexus | F26: Solución tecnológica que actúa como capa de integración entre los sistemas internos del banco y la plataforma global Cash Nexus. Facilita la comunicación y el intercambio seguro de información relacionada con pagos, cuentas y servicios de tesorería internacional. El middleware gestiona el enrutamiento, transformación y validación de mensajes entre las aplicaciones locales y el ecosistema Cash Nexus, asegurando la interoperabilidad, la trazabilidad de las transacciones y el cumplimiento de los estándares corporativos de seguridad y conectividad. Propósito principal: Garantizar una conexión eficiente, segura y estandarizada entre los sistemas bancarios locales y la plataforma global Cash Nexus, optimizando la integración de servicios de tesorería y pagos internacionales. Usuarios principales: Equipos de Tesorería, Operaciones, Tecnología y Banca Transaccional. | G26: Local Country | H26: 3. Hybrid cloud | K26: =Stakeholders!E26 -> ALEXANDRA DIAZ FIGUEROA | L26: In House Developed | N26: In Active | O26: Softtek | R26: =LOOKUP(C26,[2]APMT_Detalle!$B$2:$B$521,[2]APMT_Detalle!$AP$2:$AP$521) -> External
B27: SCIB Perú | C27: Host to Host | D27: APMF0001013066 | E27: =C27 -> Host to Host | F27: Servicio de GTB para que los clientes que se conectan a través de su plataforma puedan enviar la información de los pagos a ejecutar. | G27: Local Country | H27: 8. On-Premise | K27: =Stakeholders!E27 -> JAVIER SAVAGE ZIMMERMANN | L27: In House Developed | N27: In Active | O27: =LOOKUP(C27,[2]APMT_Detalle!$B$82:$B$521,[2]APMT_Detalle!$S$2:$S$521) -> Externo | R27: =LOOKUP(C27,[2]APMT_Detalle!$B$2:$B$521,[2]APMT_Detalle!$AP$2:$AP$521) -> On Premises
B28: SCIB Perú | C28: Sistema Office Banking | D28: APMF0001013063 | E28: =C28 -> Sistema Office Banking | F28: Portal del banco Santander Perú que expone la banca privada de la organizacion. https://www.santander.com.pe/BSP/home/index2.html | G28: Azure | H28: 3. Hybrid cloud | K28: =Stakeholders!E28 -> ALEXANDRA DIAZ FIGUEROA | L28: In House Developed | N28: In Active | O28: =LOOKUP(C28,[2]APMT_Detalle!$B$82:$B$521,[2]APMT_Detalle!$S$2:$S$521) -> MICROSOFT | R28: =LOOKUP(C28,[2]APMT_Detalle!$B$2:$B$521,[2]APMT_Detalle!$AP$2:$AP$521) -> External
B29: Santander Consumer Perú | C29: Diloo | D29: APMF0001067859 | E29: =C29 -> Diloo | F29: SaaS para mensajeria hacia clientes mediante mensaje de SMS. https://dilootu.com | G29: US | H29: 7.Vendor sit | K29: =Stakeholders!E29 -> LUIS BOULLON GARCIA | N29: In Active | O29: =LOOKUP(C29,[2]APMT_Detalle!$B$82:$B$521,[2]APMT_Detalle!$S$2:$S$521) -> Santander Digital Services | R29: =LOOKUP(C29,[2]APMT_Detalle!$B$2:$B$521,[2]APMT_Detalle!$AP$2:$AP$521) -> External
B30: Santander Consumer Perú | C30: Plataforma de Facturacion Electronica | D30: APMF0001066833 | E30: =C30 -> Plataforma de Facturacion Electronica | F30: Plataforma de emisión de comprobantes a lo clientes que realizan pagos de sus créditos. | G30: AWS | H30: 8. On-Premise | K30: =Stakeholders!E30 -> JULIO EDUARDO NIÑO SUAREZ | L30: In House Developed | N30: In Active | O30: =LOOKUP(C30,[2]APMT_Detalle!$B$82:$B$521,[2]APMT_Detalle!$S$2:$S$521) -> Santander Digital Services | R30: =LOOKUP(C30,[2]APMT_Detalle!$B$2:$B$521,[2]APMT_Detalle!$AP$2:$AP$521) -> On Premises
B31: Santander Consumer Perú | C31: Contáctanos | D31: APMF0001066014 | E31: =C31 -> Contáctanos | F31: Página web para el registro de reclamos , requerimientos y quejas; que es usado por el Call Center. URL: http://180.194.16.208:81/#/reporte/contactanos | G31: Local Country | H31: 6. Sharepoint | K31: =Stakeholders!E31 -> RENZO ALFREDO HUAYLLASCO CÁCERES | L31: In House Developed | N31: In Active | O31: =LOOKUP(C31,[2]APMT_Detalle!$B$82:$B$521,[2]APMT_Detalle!$S$2:$S$521) -> Santander Digital Services | R31: =LOOKUP(C31,[2]APMT_Detalle!$B$2:$B$521,[2]APMT_Detalle!$AP$2:$AP$521) -> External
B32: Santander Consumer Perú | C32: Visor Cobranzas | D32: APMF0001062990 | E32: =C32 -> Visor Cobranzas | F32: Estado de Cliente morosos | G32: Local Country | H32: 6. Sharepoint | K32: =Stakeholders!E32 -> 0 | L32: In House Developed | N32: In Active | O32: =LOOKUP(C32,[2]APMT_Detalle!$B$82:$B$521,[2]APMT_Detalle!$S$2:$S$521) -> Santander Global Banking (GBM) | R32: =LOOKUP(C32,[2]APMT_Detalle!$B$2:$B$521,[2]APMT_Detalle!$AP$2:$AP$521) -> Internal Cloud
B33: Santander Consumer Perú | C33: Api Market | D33: APMF0001052967 | E33: =C33 -> Api Market | F33: Plataforma de APIS Públicas que serán expuestas a empresas del grupo Santander y otras empresas externas. Conjunto de apis , de evaluacion del cliente (devuelve si el cliente es apto para un credito vehicular y asi mismo inyecta en Santi) ; es una extencion de santi https://apimarket.santanderconsumer.com.pe/access-token/ https://apimarket.santanderconsumer.com.pe/api/int/v1/pre-assessment/evaluate https://apimarket.santanderconsumer.com.pe/api/int/v1/inquiry-disbursement/find-status | G33: Local Country | H33: 3. Hybrid cloud | K33: =Stakeholders!E33 -> RENZO ALFREDO HUAYLLASCO CÁCERES | L33: In House Developed | N33: In Active | O33: =LOOKUP(C33,[2]APMT_Detalle!$B$82:$B$521,[2]APMT_Detalle!$S$2:$S$521) -> #N/A | R33: =LOOKUP(C33,[2]APMT_Detalle!$B$2:$B$521,[2]APMT_Detalle!$AP$2:$AP$521) -> External
B34: Santander Consumer Perú | C34: AMLUpdate - Name Screening | D34: APMF0001049917 | E34: =C34 -> AMLUpdate - Name Screening | F34: Plataforma para el cumplimiento de FCC utilizada para el cruce y migrar a One FCC verificación de listas de sanciones, personas y entidades restringidas, consumido por los procesos de AML del negocio de Santander Consumer Perú a través de: - API llamada por los procesos que requieren consultas de AML. - Portal donde el área usuaria local (PLAFT) consulta el histórico de llamadas. URL: https://new.amlupdate.com/ | G34: Azure | H34: 5. SaaS | K34: =Stakeholders!E34 -> LUIS BOULLON GARCIA | L34: In House Developed | N34: In Active | O34: GESINTEL | R34: =LOOKUP(C34,[2]APMT_Detalle!$B$2:$B$521,[2]APMT_Detalle!$AP$2:$AP$521) -> #N/A
B35: Santander Consumer Perú | C35: Facturación Electrónica - Auto | D35: APMF0001042159 | E35: =C35 -> Facturación Electrónica - Auto | F35: Aplicación que permite la configuración y parametrización de la emisión, gestión y monitoreo de comprobantes electrónicos, ofreciendo una interfaz web para usuarios internos y externos. Facilita la trazabilidad del proceso de facturación y asegura el cumplimiento de los requisitos tributarios vigentes. Componentes Técnicos: - FE - Batch Emision. - FE - Batch Recepcion. - API de conexión a Base de Datos. - Batch de extracción de Datos. | G35: Mexico | H35: 8. On-Premise | K35: =Stakeholders!E35 -> LUIS BOULLON GARCIA | L35: In House Developed | N35: In Active | O35: =LOOKUP(C35,[2]APMT_Detalle!$B$82:$B$521,[2]APMT_Detalle!$S$2:$S$521) -> Vector | R35: =LOOKUP(C35,[2]APMT_Detalle!$B$2:$B$521,[2]APMT_Detalle!$AP$2:$AP$521) -> On Premises
B36: Santander Consumer Perú | C36: Portal Web Público | D36: APMF0001041864 | E36: =C36 -> Portal Web Público | F36: Portal web corporativo que ofrece información institucional, productos y servicios financieros para clientes de Santander Consumer Perú, permitiendo además la autogestión y solicitud en línea de créditos y otros servicios. La home solicita al usuario elegir a qué negocio quiere acceder: (1) Crédito vehicular -Auto-, transaccional: https://www.santanderconsumer.com.pe/autos (2) Soluciones crediticias -No auto- no transaccional: https://www.santanderconsumer.com.pe/personas | G36: Mexico | H36: 8. On-Premise | K36: =Stakeholders!E36 -> LUIS BOULLON GARCIA | L36: In House Developed | N36: In Active | O36: =LOOKUP(C36,[2]APMT_Detalle!$B$82:$B$521,[2]APMT_Detalle!$S$2:$S$521) -> Santander Digital Services | R36: =LOOKUP(C36,[2]APMT_Detalle!$B$2:$B$521,[2]APMT_Detalle!$AP$2:$AP$521) -> Internal Cloud
B37: Santander Consumer Perú | C37: SAP ByDesign - ERP | D37: APMF0001035655 | E37: =C37 -> SAP ByDesign - ERP | F37: Sistema ERP SAP para la gestión de procesos administrativos, financieros, contables y operativos del negocio de Auto. URL: https://my430488.businessbydesign.cloud.sap/sap/public/ap/ui/repository/SAP_UI/HTMLOBERON5/client.html | G37: Local Country | H37: 3. Hybrid cloud | K37: =Stakeholders!E37 -> LUIS BOULLON GARCIA | L37: Vendor Custom | N37: In Active | O37: =LOOKUP(C37,[2]APMT_Detalle!$B$82:$B$521,[2]APMT_Detalle!$S$2:$S$521) -> Santander Digital Services | R37: =LOOKUP(C37,[2]APMT_Detalle!$B$2:$B$521,[2]APMT_Detalle!$AP$2:$AP$521) -> External
B38: Santander Consumer Perú | C38: Bantotal - Core Bancario | D38: APMF0001035204 | E38: =C38 -> Bantotal - Core Bancario | F38: Core bancario Bantotal en modalidad SaaS, que da soporte a la actividad de créditos al consumo del negocio de Auto. URL: https://prod.scp.bantotal.com/bantotal/servlet/com.dlya.bantotal.hwelcome | G38: Azure | H38: 3. Hybrid cloud | K38: =Stakeholders!E38 -> LUIS BOULLON GARCIA | L38: Vendor Custom | N38: In Active | O38: Bantotal | R38: =LOOKUP(C38,[2]APMT_Detalle!$B$2:$B$521,[2]APMT_Detalle!$AP$2:$AP$521) -> External
B39: Santander Consumer Perú | C39: Motor de Crédito | D39: APMF0001035203 | E39: =C39 -> Motor de Crédito | F39: Motor de evaluación crediticia que analiza la capacidad y riesgo del solicitante para aprobación de créditos vehiculares del negocio Auto. | G39: Local Country | H39: 8. On-Premise | K39: =Stakeholders!E39 -> LUIS BOULLON GARCIA | L39: In House Developed | N39: In Active | O39: =LOOKUP(C39,[2]APMT_Detalle!$B$82:$B$521,[2]APMT_Detalle!$S$2:$S$521) -> Externo | R39: =LOOKUP(C39,[2]APMT_Detalle!$B$2:$B$521,[2]APMT_Detalle!$AP$2:$AP$521) -> On Premises
B40: Santander Consumer Perú | C40: Santi | D40: APMF0001035201 | E40: =C40 -> Santi | F40: Aplicación web que soporta el proceso originación y venta de créditos vehiculares, con agenda comercial para los ejecutivos comerciales del negocio. URL: https://nfsanti.santanderconsumer.com.pe/ | G40: Local Country | H40: 8. On-Premise | K40: =Stakeholders!E40 -> LUIS BOULLON GARCIA | L40: In House Developed | N40: In Active | O40: =LOOKUP(C40,[2]APMT_Detalle!$B$82:$B$521,[2]APMT_Detalle!$S$2:$S$521) -> Santander Digital Services | R40: =LOOKUP(C40,[2]APMT_Detalle!$B$2:$B$521,[2]APMT_Detalle!$AP$2:$AP$521) -> External
B41: Santander Consumer Perú | C41: Seguros La Positiva | D41: APMF0001016373 | E41: =C41 -> Seguros La Positiva | F41: Servicio externo de broker de seguros de auto en el que se endosan los seguros de los créditos vehiculares (cotización y oferta comercial de seguro del vehículo para el cliente). | G41: Local Country | H41: 8. On-Premise | K41: =Stakeholders!E41 -> LUIS BOULLON GARCIA | L41: In House Developed | N41: In Active | O41: =LOOKUP(C41,[2]APMT_Detalle!$B$82:$B$521,[2]APMT_Detalle!$S$2:$S$521) -> Santander Digital Services | R41: =LOOKUP(C41,[2]APMT_Detalle!$B$2:$B$521,[2]APMT_Detalle!$AP$2:$AP$521) -> External
B42: Santander Consumer Perú | C42: Equifax | D42: APMF0001016371 | E42: =C42 -> Equifax | F42: Portal de consulta del historial crediticio de clientes (para consultas manuales y contingencia). URL: https://ws.equifax.com.pe/efx-app-ws-expertosantandercv/cliente/datoscv | G42: Local Country | H42: 5. SaaS | K42: =Stakeholders!E42 -> Darwin Curisinche Rojas | L42: In House Developed | N42: In Active | O42: =LOOKUP(C42,[2]APMT_Detalle!$B$82:$B$521,[2]APMT_Detalle!$S$2:$S$521) -> Vector | R42: =LOOKUP(C42,[2]APMT_Detalle!$B$2:$B$521,[2]APMT_Detalle!$AP$2:$AP$521) -> Internal Cloud
B43: Santander Consumer Perú | C43: Docuclass | D43: APMF0001016370 | E43: =C43 -> Docuclass | F43: Aplicación de Gestión Documentaria para subir todas las solicitudes de créditos. URL: https://santander1.mydocuclass.com/home | G43: Mexico | H43: 8. On-Premise | K43: =Stakeholders!E43 -> LUIS BOULLON GARCIA | L43: COTS Customized | N43: In Active | O43: =LOOKUP(C43,[2]APMT_Detalle!$B$82:$B$521,[2]APMT_Detalle!$S$2:$S$521) -> Santander Digital Services | R43: =LOOKUP(C43,[2]APMT_Detalle!$B$2:$B$521,[2]APMT_Detalle!$AP$2:$AP$521) -> External
B44: Santander Consumer Perú | C44: Seir | D44: APMF0001016364 | E44: =C44 -> Seir | F44: Sistema Emisor de Informes Regulatorios - Auto. Aplicación que genera informes regulatorios periódicos en base a información del core (Bantotal), adicionales a los que genera Bantotal de serie. | H44: 3. Hybrid cloud | K44: =Stakeholders!E44 -> LUIS BOULLON GARCIA | N44: In Active | O44: =LOOKUP(C44,[2]APMT_Detalle!$B$82:$B$521,[2]APMT_Detalle!$S$2:$S$521) -> Santander Digital Services | R44: =LOOKUP(C44,[2]APMT_Detalle!$B$2:$B$521,[2]APMT_Detalle!$AP$2:$AP$521) -> External
B45: Santander Consumer Perú | C45: Pomelo | E45: =C45 -> Pomelo | F45: Administrador de tarjetas | G45: Local Country | H45: 8. On-Premise | K45: =Stakeholders!E45 -> 0 | N45: In Active | O45: =LOOKUP(C45,[2]APMT_Detalle!$B$82:$B$521,[2]APMT_Detalle!$S$2:$S$521) -> Santander Digital Services | R45: =LOOKUP(C45,[2]APMT_Detalle!$B$2:$B$521,[2]APMT_Detalle!$AP$2:$AP$521) -> On Premises
B46: Santander Consumer Perú | C46: Izypay | E46: =C46 -> Izypay | F46: Pasarela de pagos de la web de scp | G46: Mexico | H46: 8. On-Premise | K46: =Stakeholders!E46 -> 0 | L46: COTS Customized | N46: In Active | O46: =LOOKUP(C46,[2]APMT_Detalle!$B$82:$B$521,[2]APMT_Detalle!$S$2:$S$521) -> Externo | R46: =LOOKUP(C46,[2]APMT_Detalle!$B$2:$B$521,[2]APMT_Detalle!$AP$2:$AP$521) -> On Premises
B47: Santander Consumer Perú | C47: Kasnet | E47: =C47 -> Kasnet | F47: Recaudadora de pagos de cuota , cancelaciones y amortizaciones | G47: Mexico | H47: 8. On-Premise | K47: =Stakeholders!E47 -> 0 | L47: COTS Customized | N47: In Active | O47: =LOOKUP(C47,[2]APMT_Detalle!$B$82:$B$521,[2]APMT_Detalle!$S$2:$S$521) -> Externo | R47: =LOOKUP(C47,[2]APMT_Detalle!$B$2:$B$521,[2]APMT_Detalle!$AP$2:$AP$521) -> On Premises
B48: Santander Consumer Perú | C48: ChatBot | E48: =C48 -> ChatBot | F48: Servicio de WHATSAP | G48: US | H48: 5. SaaS | K48: =Stakeholders!E48 -> 0 | N48: In Active | O48: =LOOKUP(C48,[2]APMT_Detalle!$B$82:$B$521,[2]APMT_Detalle!$S$2:$S$521) -> #N/A | R48: =LOOKUP(C48,[2]APMT_Detalle!$B$2:$B$521,[2]APMT_Detalle!$AP$2:$AP$521) -> External
B49: Santander Consumer Perú | C49: Data Riesgos | E49: =C49 -> Data Riesgos | H49: 3. Hybrid cloud | K49: =Stakeholders!E49 -> 0 | N49: In Active | O49: =LOOKUP(C49,[2]APMT_Detalle!$B$82:$B$521,[2]APMT_Detalle!$S$2:$S$521) -> Santander Digital Services | R49: =LOOKUP(C49,[2]APMT_Detalle!$B$2:$B$521,[2]APMT_Detalle!$AP$2:$AP$521) -> External
B50: Santander Consumer Perú | C50: API OTP | E50: =C50 -> API OTP | G50: Mexico | H50: 3. Hybrid cloud | K50: =Stakeholders!E50 -> 0 | L50: In House Developed | N50: In Active | O50: TCS | R50: =LOOKUP(C50,[2]APMT_Detalle!$B$2:$B$521,[2]APMT_Detalle!$AP$2:$AP$521) -> External
B51: Santander Consumer Perú | C51: API Portal | E51: =C51 -> API Portal | G51: Mexico | H51: 3. Hybrid cloud | K51: =Stakeholders!E51 -> 0 | L51: In House Developed | N51: In Active | O51: TCS | R51: =LOOKUP(C51,[2]APMT_Detalle!$B$2:$B$521,[2]APMT_Detalle!$AP$2:$AP$521) -> External
B52: Santander Consumer Perú | C52: Venta Cartera | E52: =C52 -> Venta Cartera | G52: Mexico | H52: 3. Hybrid cloud | K52: =Stakeholders!E52 -> 0 | L52: In House Developed | N52: In Active | O52: =LOOKUP(C52,[2]APMT_Detalle!$B$82:$B$521,[2]APMT_Detalle!$S$2:$S$521) -> MICROSOFT | R52: =LOOKUP(C52,[2]APMT_Detalle!$B$2:$B$521,[2]APMT_Detalle!$AP$2:$AP$521) -> Internal Cloud
B53: Santander Perú | C53: Virtual Assistant P&C | D53: APMF0001067421 | E53: =C53 -> Virtual Assistant P&C | F53: Agente virtual (AV) para que los empleados mejoren el acceso a la información relacionada con aspectos de P, C&O (como políticas de P, C&O, procedimientos internos y comunicaciones con los empleados). La información se encuentra en Sharepoint. | H53: 3. Hybrid cloud | K53: =Stakeholders!E53 -> ADOLFO UNDA LAZARO | N53: In Active | O53: =LOOKUP(C53,[2]APMT_Detalle!$B$82:$B$521,[2]APMT_Detalle!$S$2:$S$521) -> MICROSOFT | R53: =LOOKUP(C53,[2]APMT_Detalle!$B$2:$B$521,[2]APMT_Detalle!$AP$2:$AP$521) -> Internal Cloud
B54: Santander Perú | C54: Masterbase | D54: APMF0001067295 | E54: =C54 -> Masterbase | F54: SaaS para mensajeria hacia clientes mediante mensaje de correo electrónico. https://api2024.masterbase.com | G54: Mexico | H54: 5. SaaS | K54: =Stakeholders!E54 -> ALFREDO LLONA ARIS | L54: In House Developed | N54: In Active | O54: =LOOKUP(C54,[2]APMT_Detalle!$B$82:$B$521,[2]APMT_Detalle!$S$2:$S$521) -> Externo | R54: =LOOKUP(C54,[2]APMT_Detalle!$B$2:$B$521,[2]APMT_Detalle!$AP$2:$AP$521) -> On Premises
B55: Santander Perú | C55: Data Analytics | D55: APMF0001066952 | E55: =C55 -> Data Analytics | F55: Sistema de reportes desarrollado en Power BI, que se alimentan de información de ETL's. | G55: Mexico | H55: 5. SaaS | K55: =Stakeholders!E55 -> ALFREDO LLONA ARIS | L55: In House Developed | N55: In Active | O55: =LOOKUP(C55,[2]APMT_Detalle!$B$82:$B$521,[2]APMT_Detalle!$S$2:$S$521) -> Santander Digital Services | R55: =LOOKUP(C55,[2]APMT_Detalle!$B$2:$B$521,[2]APMT_Detalle!$AP$2:$AP$521) -> External
B56: Santander Perú | C56: Gestión Portafolio PMO | D56: APMF0001066220 | E56: =C56 -> Gestión Portafolio PMO | F56: La solución consiste en una plataforma de Power-Apps diseñada para centralizar la información de los iniciativas gestionados por la PMO. La aplicación permite el registro actualización y consulta de la información del portafolio de iniciativas y también al registro, actualización y consulta de la información de cada propuesta relacionada al iniciativa, de manera que se asegure la consistencia y trazabilidad de la información. A través de la aplicación, los usuarios podrán registrar información de los iniciativas y propuestas, mantener actualizada la información de cada iniciativa y propuesta, adjuntar la documentación relevante para cada iniciativa y propuesta y visualizar el estado consolidado del portafolio mediante vistas centralizadas y de un dashboard con indicadores, y todo de ello bajo un control de accesos según los perfiles establecidos. La aplicación es de uso interno y se integra con los servicios proporcionados por Microsoft 365 tanto para el almacenamiento de información (SharePoint) y Soporte (Outlook). El aplicativo Power-Apps de Centralización de Información de la PMO apunta a convertirse en la plataforma única para el registro, seguimiento y consolidación de la información de los iniciativas y las propuestas de cada iniciativa El aplicativo busca eliminar la no consistencia de información entre las plataformas actuales donde completan la información (Excel de Alexandría y SharePoint), mejorar la trazabilidad de la información a lo largo de todo el ciclo de vida de los iniciativas. Esta dirigida a la PMO y a los stakeholders relacionados, proporcionando visibilidad del estado general del portafolio y detalle de cada iniciativa y propuestas de cada iniciativa, facilitando la toma de decisiones y fortaleciendo el gobierno de los iniciativas mediante reglas y controles definidos. | G56: Local Country | H56: 5. SaaS | K56: =Stakeholders!E56 -> MARIA FERNANDA HEROS CALLIRGOS | L56: Vendor Custom | N56: In Active | O56: TCS | R56: =LOOKUP(C56,[2]APMT_Detalle!$B$2:$B$521,[2]APMT_Detalle!$AP$2:$AP$521) -> On Premises
B57: Santander Perú | C57: Diloo | D57: APMF0001064392 | E57: =C57 -> Diloo | F57: SaaS para mensajeria hacia clientes mediante mensaje de SMS. https://dilootu.com | G57: US | H57: 7.Vendor sit | K57: =Stakeholders!E57 -> ALFREDO LLONA ARIS | L57: Vendor Custom | N57: In Active | O57: =LOOKUP(C57,[2]APMT_Detalle!$B$82:$B$521,[2]APMT_Detalle!$S$2:$S$521) -> Santander Digital Services | R57: =LOOKUP(C57,[2]APMT_Detalle!$B$2:$B$521,[2]APMT_Detalle!$M$2:$M$521) -> Datalake
B58: Santander Perú | C58: Lynx | D58: APMF0001063421 | E58: =C58 -> Lynx | F58: Plataforma para gestión de monitoreo y reglas de fraude. | G58: Mexico | H58: 8. On-Premise | K58: =Stakeholders!E58 -> ALFREDO LLONA ARIS | L58: Vendor Custom | N58: In Active | O58: =LOOKUP(C58,[2]APMT_Detalle!$B$82:$B$521,[2]APMT_Detalle!$S$2:$S$521) -> Externo | R58: =LOOKUP(C58,[2]APMT_Detalle!$B$2:$B$521,[2]APMT_Detalle!$M$2:$M$521) -> Data Analytics
B59: Santander Perú | C59: Astara/SK Berge | D59: APMF0001061398 | E59: =C59 -> Astara/SK Berge | F59: Servidor en DMZ donde se conecta ASTARA para consumir APIS publicadas por banco para el uso de floor plan. | G59: Local Country | H59: 3. Hybrid cloud | K59: =Stakeholders!E59 -> ALFREDO LLONA ARIS | L59: In House Developed | N59: In Active | O59: Vector | R59: =LOOKUP(C59,[2]APMT_Detalle!$B$2:$B$521,[2]APMT_Detalle!$M$2:$M$521) -> Anura
B60: Santander Perú | C60: Factoring Data Lake Leads | D60: APMF0001061386 | E60: =C60 -> Factoring Data Lake Leads | F60: Se mostrará la gestión de los leads desde que se ingesta al Data Lake y se visualiza en el Power BI. | G60: Local Country | H60: 3. Hybrid cloud | K60: =Stakeholders!E60 -> MARCO RISCO MEJIA | L60: In House Developed | N60: In Active | O60: =LOOKUP(C60,[2]APMT_Detalle!$B$82:$B$521,[2]APMT_Detalle!$S$2:$S$521) -> Vector | R60: =LOOKUP(C60,[2]APMT_Detalle!$B$2:$B$521,[2]APMT_Detalle!$M$2:$M$521) -> Modulo Negociación
B61: Santander Perú | C61: Monitor Plus (ETL) - Transaction Monitorig | D61: APMF0001061269 | E61: =C61 -> Monitor Plus (ETL) - Transaction Monitorig | F61: Servidor que tiene SQL Server y ETLs para realizar la extracción de información del AS400, procesarla y enviarla mediante api a MonitorPlus (SaaS). Para la comunicación cuenta con VPN SiteToSite. | G61: Azure | H61: 5. SaaS | K61: =Stakeholders!E61 -> ALFREDO LLONA ARIS | L61: In House Developed | N61: In Active | O61: =LOOKUP(C61,[2]APMT_Detalle!$B$82:$B$521,[2]APMT_Detalle!$S$2:$S$521) -> Externo | R61: =LOOKUP(C61,[2]APMT_Detalle!$B$2:$B$521,[2]APMT_Detalle!$M$2:$M$521) -> Data Analytics
B62: Santander Perú | C62: Dashboards Analytics | D62: APMF0001061268 | E62: =C62 -> Dashboards Analytics | F62: Lista de procesos extraen información de distintas base de datos y se muestra en distintas area de operación. | G62: Local Country | H62: 8. On-Premise | K62: =Stakeholders!E62 -> ALFREDO LLONA ARIS | L62: In House Developed | N62: In Active | O62: =LOOKUP(C62,[2]APMT_Detalle!$B$82:$B$521,[2]APMT_Detalle!$S$2:$S$521) -> Santander Digital Services | R62: =LOOKUP(C62,[2]APMT_Detalle!$B$2:$B$521,[2]APMT_Detalle!$M$2:$M$521) -> Anura
B63: Santander Perú | C63: Loan Tape | D63: APMF0001061267 | E63: =C63 -> Loan Tape | F63: Generación de reporteria con información general del banco al regulador europeo. | G63: Local Country | H63: 8. On-Premise | K63: =Stakeholders!E63 -> ALFREDO LLONA ARIS | L63: In House Developed | N63: In Active | O63: =LOOKUP(C63,[2]APMT_Detalle!$B$82:$B$521,[2]APMT_Detalle!$S$2:$S$521) -> Externo | R63: =LOOKUP(C63,[2]APMT_Detalle!$B$2:$B$521,[2]APMT_Detalle!$M$2:$M$521) -> Data Analytics
B64: Santander Perú | C64: Hiperfirmas | D64: APMF0001061265 | E64: =C64 -> Hiperfirmas | F64: Gestión y seguimiento de los requerimientos de Fiscalía: Módulos: Sociedades, Poderes y Garantías. Los dos primeros habilitados para funcionar en modalidad cliente/servior y WEB. Garantías se encuentra por desarrollar en la misma modal Funcionalidades: Lo más utilizado es la administración de la información de Poderes del Banco. Información habilitada para consulta por Intranet (todo el área Comercial) y específicamente para Cajas, Comercio Exterior, Cuentas Corrientes y los Centros de Proceso. | G64: Local Country | H64: 8. On-Premise | K64: =Stakeholders!E64 -> 0 | L64: COTS Customized | N64: In Active | O64: =LOOKUP(C64,[2]APMT_Detalle!$B$82:$B$521,[2]APMT_Detalle!$S$2:$S$521) -> Externo | R64: =LOOKUP(C64,[2]APMT_Detalle!$B$2:$B$521,[2]APMT_Detalle!$M$2:$M$521) -> Data Analytics
B65: Santander Perú | C65: Web Onboarding | D65: APMF0001061264 | E65: =C65 -> Web Onboarding | F65: Portal web alojado en el ambiente de OOBB que permite al usuario externo registrar la información necesaria para ser cliente del banco. El sistema realiza validaciones de Países Prohibidos, Scoring y consultas con Gesintel (listas negras, terrorismo, etc). La información es almacenada en la BD Intermedia (mismo servidor de BD que el OOBB) luego envía al Core para que operaciones confirmen la información y procedan a dar de alta como cliente. https://www.santander.com.pe/BSP/registrocliente/#/auth/login | G65: Mexico | H65: 3. Hybrid cloud | K65: =Stakeholders!E65 -> ALFREDO LLONA ARIS | L65: In House Developed | N65: In Active | O65: =LOOKUP(C65,[2]APMT_Detalle!$B$82:$B$521,[2]APMT_Detalle!$S$2:$S$521) -> Santander Global Banking (GBM) | R65: =LOOKUP(C65,[2]APMT_Detalle!$B$2:$B$521,[2]APMT_Detalle!$M$2:$M$521) -> Sailpoint
B66: Santander Perú | C66: LBTR Novatronic | D66: APMF0001061262 | E66: =C66 -> LBTR Novatronic | F66: Software que interactua entre LBTR rojo y CCE. Opera para las transaferenicas inmediatas. | G66: Mexico | H66: 8. On-Premise | K66: =Stakeholders!E66 -> ALFREDO LLONA ARIS | L66: Vendor Custom | N66: In Active | O66: =LOOKUP(C66,[2]APMT_Detalle!$B$82:$B$521,[2]APMT_Detalle!$S$2:$S$521) -> Externo | R66: =LOOKUP(C66,[2]APMT_Detalle!$B$2:$B$521,[2]APMT_Detalle!$M$2:$M$521) -> Data Analytics
B67: Santander Perú | C67: Web Pago Interno | D67: APMF0001061261 | E67: =C67 -> Web Pago Interno | F67: Pago de servicios Banbif, Conexión desde OOBB a dos máquina de salto hasta banbif, ida y vuelta. | G67: Local Country | H67: 8. On-Premise | K67: =Stakeholders!E67 -> ALFREDO LLONA ARIS | L67: In House Developed | N67: In Active | O67: =LOOKUP(C67,[2]APMT_Detalle!$B$82:$B$521,[2]APMT_Detalle!$S$2:$S$521) -> Santander Global Banking (GBM) | R67: =LOOKUP(C67,[2]APMT_Detalle!$B$2:$B$521,[2]APMT_Detalle!$M$2:$M$521) -> Sailpoint
B68: Santander Perú | C68: Retenciones SUNAT | D68: APMF0001061260 | E68: =C68 -> Retenciones SUNAT | F68: Mecanismo para asegurar el pago de impuestos a la renta (IR) y (IGV) | G68: Local Country | H68: 3. Hybrid cloud | K68: =Stakeholders!E68 -> 0 | L68: In House Developed | N68: In Active | O68: =LOOKUP(C68,[2]APMT_Detalle!$B$82:$B$521,[2]APMT_Detalle!$S$2:$S$521) -> Santander Digital Services | R68: =LOOKUP(C68,[2]APMT_Detalle!$B$2:$B$521,[2]APMT_Detalle!$M$2:$M$521) -> Quadrant
B69: Santander Perú | C69: Facturas Negociables | D69: APMF0001061254 | E69: =C69 -> Facturas Negociables | F69: Servidor de conexión entre BSP y Cavali para la funcionalidad de Factoring. | G69: Local Country | H69: 8. On-Premise | K69: =Stakeholders!E69 -> ALFREDO LLONA ARIS | L69: In House Developed | N69: In Active | O69: =LOOKUP(C69,[2]APMT_Detalle!$B$82:$B$521,[2]APMT_Detalle!$S$2:$S$521) -> Vector | R69: =LOOKUP(C69,[2]APMT_Detalle!$B$2:$B$521,[2]APMT_Detalle!$M$2:$M$521) -> Modulo Negociación
B70: Santander Perú | C70: GDS Modellica | D70: APMF0001061173 | E70: =C70 -> GDS Modellica | F70: Es un aplicativo de desición para provisiones globales, se hace mantenimiento por bolsa de horas el proveedor gds modellica de España. | G70: US | H70: 7.Vendor sit | K70: =Stakeholders!E70 -> ALFREDO LLONA ARIS | L70: In House Developed | N70: In Active | O70: =LOOKUP(C70,[2]APMT_Detalle!$B$82:$B$521,[2]APMT_Detalle!$S$2:$S$521) -> Vector | R70: =LOOKUP(C70,[2]APMT_Detalle!$B$2:$B$521,[2]APMT_Detalle!$M$2:$M$521) -> Modulo Negociación
B71: Santander Perú | C71: Qlik Sense | D71: APMF0001061172 | E71: =C71 -> Qlik Sense | F71: Herramienta de Inteligencia de Negocios para el análisis de información 2022. | G71: Local Country | H71: 8. On-Premise | K71: =Stakeholders!E71 -> ALFREDO LLONA ARIS | L71: COTS Customized | N71: In Active | O71: =LOOKUP(C71,[2]APMT_Detalle!$B$82:$B$521,[2]APMT_Detalle!$S$2:$S$521) -> Santander Digital Services | R71: =LOOKUP(C71,[2]APMT_Detalle!$B$2:$B$521,[2]APMT_Detalle!$M$2:$M$521) -> Portal Web Público
... B77: Santander Perú | C77: WorldSys | D77: APMF0001044383 | E77: =C77 -> WorldSys | F77: Aplicación utilizada para la verificación y control de personas y entidades frente a listas de sanciones, observación y cumplimiento normativo. Permite automatizar procesos de validación en línea, apoyar la prevención de delitos financieros y garantizar el cumplimiento de las políticas de Financial Crime Compliance (FCC) del banco. | G77: Local Country | H77: 8. On-Premise | K77: =Stakeholders!E77 -> ALFREDO LLONA ARIS | L77: Vendor Custom | N77: In Active | O77: =LOOKUP(C77,[2]APMT_Detalle!$B$82:$B$521,[2]APMT_Detalle!$S$2:$S$521) -> Santander Global Banking (GBM) | R77: =LOOKUP(C77,[2]APMT_Detalle!$B$2:$B$521,[2]APMT_Detalle!$M$2:$M$521) -> Sailpoint
B78: Santander Perú | C78: AMLUpdate - Name Screening | D78: APMF0001044226 | E78: =C78 -> AMLUpdate - Name Screening | F78: Plataforma para el cumplimiento de FCC utilizada para el cruce y migrar a One FCC verificación de listas de sanciones, personas y entidades restringidas, consumido por los procesos de AML del negocio de Santander Perú a través de: - API llamada por los procesos que requieren consultas de AML. - Portal donde el área usuaria local (PLAFT) consulta el histórico de llamadas. URL: https://new.amlupdate.com/ | G78: Mexico | H78: 5. SaaS | K78: =Stakeholders!E78 -> ALFREDO LLONA ARIS | L78: Vendor Custom | N78: In Active | O78: GESINTEL | R78: =LOOKUP(C78,[2]APMT_Detalle!$B$2:$B$521,[2]APMT_Detalle!$M$2:$M$521) -> #N/A
B79: Santander Perú | C79: RatingPlus | D79: APMF0001043386 | E79: =C79 -> RatingPlus | F79: Aplicación que calcula y gestiona el rating crediticio de los clientes del banco a nivel de cartera. Permite evaluar la calidad crediticia y el perfil de riesgo de cada cliente, integrando información financiera y comportamental para apoyar la gestión del riesgo y la toma de decisiones de crédito. | G79: Mexico | H79: 3. Hybrid cloud | K79: =Stakeholders!E79 -> ALFREDO LLONA ARIS | L79: Vendor Custom | N79: In Active | O79: =LOOKUP(C79,[2]APMT_Detalle!$B$82:$B$521,[2]APMT_Detalle!$S$2:$S$521) -> Santander Digital Services | R79: =LOOKUP(C79,[2]APMT_Detalle!$B$2:$B$521,[2]APMT_Detalle!$M$2:$M$521) -> Quadrant
B80: Santander Perú | C80: Zapier | D80: APMF0001040584 | E80: =C80 -> Zapier | F80: Plataforma de integración que permite automatizar flujos de trabajo (factoring) entre aplicaciones mediante la conexión de sistemas sin necesidad de desarrollo adicional. Facilita la sincronización de datos y tareas entre herramientas corporativas, mejorando la eficiencia operativa y reduciendo intervenciones manuales. | H80: 5. SaaS | K80: =Stakeholders!E80 -> 0 | N80: In Active | O80: =LOOKUP(C80,[2]APMT_Detalle!$B$82:$B$521,[2]APMT_Detalle!$S$2:$S$521) -> Santander Global Banking (GBM) | R80: =LOOKUP(C80,[2]APMT_Detalle!$B$2:$B$521,[2]APMT_Detalle!$M$2:$M$521) -> Sailpoint
B81: Santander Perú | C81: SAP ByDesign | D81: APMF0001040476 | E81: =C81 -> SAP ByDesign | F81: Sistema ERP que brinda buenas prácticas en la operativa de Administración, Finanzas, Contabilidad y Operaciones. | G81: US | H81: 5. SaaS | K81: =Stakeholders!E81 -> 0 | L81: Vendor Custom | N81: In Active | O81: =LOOKUP(C81,[2]APMT_Detalle!$B$82:$B$521,[2]APMT_Detalle!$S$2:$S$521) -> Santander Digital Services | R81: =LOOKUP(C81,[2]APMT_Detalle!$B$2:$B$521,[2]APMT_Detalle!$M$2:$M$521) -> Santo
B82: Santander Perú | C82: Web Institucional | D82: APMF0001021407 | F82: Portal web oficial que ofrece información corporativa, productos y servicios financieros del Banco Santander Perú. Sirve como canal de comunicación institucional y punto de acceso para clientes y usuarios interesados en los servicios del banco, garantizando disponibilidad, seguridad y cumplimiento de las directrices de marca y normativas locales. https://www.santander.com.pe | G82: Local Country | H82: 3. Hybrid cloud | K82: =Stakeholders!E82 -> ALFREDO LLONA ARIS | L82: Vendor Custom | N82: In Active | O82: =LOOKUP(C82,[2]APMT_Detalle!$B$82:$B$521,[2]APMT_Detalle!$S$2:$S$521) -> Santander Global Banking (GBM) | R82: =LOOKUP(C82,[2]APMT_Detalle!$B$2:$B$521,[2]APMT_Detalle!$M$2:$M$521) -> Sailpoint
B83: Santander Perú | C83: Motor TOP | D83: APMF0001013080 | F83: Base de datos local utilizada para el control y monitoreo de clientes con altas exposiciones crediticias. Permite consolidar información relevante para la gestión del riesgo, apoyar los procesos de seguimiento y cumplir con los lineamientos regulatorios y corporativos del banco. | G83: Local Country | H83: 3. Hybrid cloud | K83: =Stakeholders!E83 -> ALFREDO LLONA ARIS | L83: Vendor Custom | N83: In Active | O83: =LOOKUP(C83,[2]APMT_Detalle!$B$82:$B$521,[2]APMT_Detalle!$S$2:$S$521) -> Externo | R83: =LOOKUP(C83,[2]APMT_Detalle!$B$2:$B$521,[2]APMT_Detalle!$M$2:$M$521) -> Data Analytics
B84: Santander Perú | C84: Reporte Crediticio de Deudores | D84: APMF0001013070 | F84: Aplicación que genera informes de clientes con incumplimientos en sus obligaciones de pago, utilizando información del core bancario Nazca, para cumplimiento regulatorio. | G84: Local Country | H84: 6. Sharepoint | K84: =Stakeholders!E84 -> ALFREDO LLONA ARIS | L84: In House Developed | N84: In Active | O84: =LOOKUP(C84,[2]APMT_Detalle!$B$82:$B$521,[2]APMT_Detalle!$S$2:$S$521) -> Santander Digital Services | R84: =LOOKUP(C84,[2]APMT_Detalle!$B$2:$B$521,[2]APMT_Detalle!$M$2:$M$521) -> Quadrant
B85: Santander Perú | C85: Nazca AS400 | D85: APMF0001013061 | F85: Core del Banco Santander Perú, para el negocio de empresas (Commercial). Incluye el terminal que permite a los equipos de operaciones ejecutar diversas acciones (lanzar transacciones, consulta de información, etc). | G85: Mexico | H85: 3. Hybrid cloud | K85: =Stakeholders!E85 -> ALFREDO LLONA ARIS | L85: Vendor Custom | N85: In Active | O85: =LOOKUP(C85,[2]APMT_Detalle!$B$82:$B$521,[2]APMT_Detalle!$S$2:$S$521) -> Externo | R85: =LOOKUP(C85,[2]APMT_Detalle!$B$2:$B$521,[2]APMT_Detalle!$M$2:$M$521) -> Data Analytics
B86: Santander Perú | C86: Genesys Cloud | D86: APMF0001065199 | F86: Es una plataforma cloud para gestionar centros de contactos , comunicaciones y experiencia cliente / empleado con capacidades omnicanal. | G86: Azure | H86: 5. SaaS | K86: =Stakeholders!E86 -> 0 | L86: In House Developed | N86: In Active | O86: =LOOKUP(C86,[2]APMT_Detalle!$B$82:$B$521,[2]APMT_Detalle!$S$2:$S$521) -> Vector | R86: =LOOKUP(C86,[2]APMT_Detalle!$B$2:$B$521,[2]APMT_Detalle!$M$2:$M$521) -> Modulo Negociación
GR24997: C1 | GS24997: 1
IO64996: Yes
IO64997: Yes

Sheet Stakeholders
A1: Tool Id | B1: Business Unit Name | C1: Application Name | D1: Application Business Owner | E1: Application Technical (IT) Owner | F1: Application Technical Group | G1: Application Technical SPOC | FY1: Field Names
B2: ='Application Info'!B2 -> Surgir | C2: ='Application Info'!C2 -> SAP by Design | D2: DIANA OCHOA CASTILLO | E2: RENZO ALFREDO HUAYLLASCO CÁCERES | FY2: Business_Executive_Sponser
B3: ='Application Info'!B3 -> Surgir | C3: ='Application Info'!C3 -> App Surgir | D3: RENZO ALFREDO HUAYLLASCO CÁCERES | E3: RENZO ALFREDO HUAYLLASCO CÁCERES | FY3: Service_Delivery_Lead
B4: ='Application Info'!B4 -> Surgir | C4: ='Application Info'!C4 -> App Cliente | D4: RENZO ALFREDO HUAYLLASCO CÁCERES | E4: YELTSIN ANTONY ALAN SOTELO CAMONES | FY4: IT_Production_Support_Contact
B5: ='Application Info'!B5 -> Surgir | C5: ='Application Info'!C5 -> AMLUpdate - Name Screening | D5: ALONSO GUILLERMO SERRANO CARMONA | E5: RENZO ALFREDO HUAYLLASCO CÁCERES
B6: ='Application Info'!B6 -> Surgir | C6: ='Application Info'!C6 -> Portal Web Público | D6: RENZO ALFREDO HUAYLLASCO CÁCERES | E6: RENZO ALFREDO HUAYLLASCO CÁCERES
B7: ='Application Info'!B7 -> Surgir | C7: ='Application Info'!C7 -> Anura | D7: ARIANA PEREZ ESCOBAR | E7: RENZO ALFREDO HUAYLLASCO CÁCERES
B8: ='Application Info'!B8 -> Surgir | C8: ='Application Info'!C8 -> ERP Contanet | D8: GABRIELA SOLEDAD LASTARRIA FLORES | E8: RENZO ALFREDO HUAYLLASCO CÁCERES
B9: ='Application Info'!B9 -> Surgir | C9: ='Application Info'!C9 -> Datalake | D9: RENZO ALFREDO HUAYLLASCO CÁCERES | E9: RENZO ALFREDO HUAYLLASCO CÁCERES
B10: ='Application Info'!B10 -> Surgir | C10: ='Application Info'!C10 -> Cobis | D10: RENZO ALFREDO HUAYLLASCO CÁCERES | E10: RENZO ALFREDO HUAYLLASCO CÁCERES
B11: ='Application Info'!B11 -> Santander Fondos Colectivos | C11: ='Application Info'!C11 -> Emblue | D11: Luis Alberto Barandiaran | E11: Luis Alberto Barandiaran
B12: ='Application Info'!B12 -> Santander Fondos Colectivos | C12: ='Application Info'!C12 -> Facephi | D12: Luis Alberto Barandiaran | E12: Luis Alberto Barandiaran
B13: ='Application Info'!B13 -> Santander Fondos Colectivos | C13: ='Application Info'!C13 -> Mapfre | D13: Luis Alberto Barandiaran | E13: LUIS BOULLON GARCIA
B14: ='Application Info'!B14 -> Santander Fondos Colectivos | C14: ='Application Info'!C14 -> Tracklink | D14: Luis Alberto Barandiaran | E14: LUIS BOULLON GARCIA
B15: ='Application Info'!B15 -> Santander Fondos Colectivos | C15: ='Application Info'!C15 -> Docuclass | D15: Luis Alberto Barandiaran | E15: LUIS BOULLON GARCIA
B16: ='Application Info'!B16 -> Santander Fondos Colectivos | C16: ='Application Info'!C16 -> Diloo | D16: Luis Alberto Barandiaran | E16: LUIS BOULLON GARCIA
... B31: ='Application Info'!B31 -> Santander Consumer Perú | C31: ='Application Info'!C31 -> Contáctanos | D31: JESUS DIAZ VALENZUELA | E31: RENZO ALFREDO HUAYLLASCO CÁCERES
B32: ='Application Info'!B32 -> Santander Consumer Perú | C32: ='Application Info'!C32 -> Visor Cobranzas
B33: ='Application Info'!B33 -> Santander Consumer Perú | C33: ='Application Info'!C33 -> Api Market | D33: JESUS DIAZ VALENZUELA | E33: RENZO ALFREDO HUAYLLASCO CÁCERES
B34: ='Application Info'!B34 -> Santander Consumer Perú | C34: ='Application Info'!C34 -> AMLUpdate - Name Screening | D34: ALONSO GUILLERMO SERRANO CARMONA | E34: LUIS BOULLON GARCIA
B35: ='Application Info'!B35 -> Santander Consumer Perú | C35: ='Application Info'!C35 -> Facturación Electrónica - Auto | D35: CHRISTIAN POMAZÓN OBREGÓN | E35: LUIS BOULLON GARCIA
B36: ='Application Info'!B36 -> Santander Consumer Perú | C36: ='Application Info'!C36 -> Portal Web Público | D36: RENZO ALFREDO HUAYLLASCO CÁCERES | E36: LUIS BOULLON GARCIA
B37: ='Application Info'!B37 -> Santander Consumer Perú | C37: ='Application Info'!C37 -> SAP ByDesign - ERP | D37: PATRICIA DIAZ BUSTO | E37: LUIS BOULLON GARCIA
B38: ='Application Info'!B38 -> Santander Consumer Perú | C38: ='Application Info'!C38 -> Bantotal - Core Bancario | D38: JULIO EDUARDO NIÑO SUAREZ | E38: LUIS BOULLON GARCIA
B39: ='Application Info'!B39 -> Santander Consumer Perú | C39: ='Application Info'!C39 -> Motor de Crédito | D39: Darwin Curisinche Rojas | E39: LUIS BOULLON GARCIA
B40: ='Application Info'!B40 -> Santander Consumer Perú | C40: ='Application Info'!C40 -> Santi | D40: IVETTE DEL CARMEN CRUZ VARGAS DEL AGUILA | E40: LUIS BOULLON GARCIA
B41: ='Application Info'!B41 -> Santander Consumer Perú | C41: ='Application Info'!C41 -> Seguros La Positiva | D41: JULIO EDUARDO NIÑO SUAREZ | E41: LUIS BOULLON GARCIA
B42: ='Application Info'!B42 -> Santander Consumer Perú | C42: ='Application Info'!C42 -> Equifax | D42: Darwin Curisinche Rojas | E42: Darwin Curisinche Rojas
B43: ='Application Info'!B43 -> Santander Consumer Perú | C43: ='Application Info'!C43 -> Docuclass | D43: JULIO EDUARDO NIÑO SUAREZ | E43: LUIS BOULLON GARCIA
B44: ='Application Info'!B44 -> Santander Consumer Perú | C44: ='Application Info'!C44 -> Seir | D44: PATRICIA DIAZ BUSTO | E44: LUIS BOULLON GARCIA
B45: ='Application Info'!B45 -> Santander Consumer Perú | C45: ='Application Info'!C45 -> Pomelo
B46: ='Application Info'!B46 -> Santander Consumer Perú | C46: ='Application Info'!C46 -> Izypay
B47: ='Application Info'!B47 -> Santander Consumer Perú | C47: ='Application Info'!C47 -> Kasnet
B48: ='Application Info'!B48 -> Santander Consumer Perú | C48: ='Application Info'!C48 -> ChatBot
B49: ='Application Info'!B49 -> Santander Consumer Perú | C49: ='Application Info'!C49 -> Data Riesgos
B50: ='Application Info'!B50 -> Santander Consumer Perú | C50: ='Application Info'!C50 -> API OTP
B51: ='Application Info'!B51 -> Santander Consumer Perú | C51: ='Application Info'!C51 -> API Portal
B52: ='Application Info'!B52 -> Santander Consumer Perú | C52: ='Application Info'!C52 -> Venta Cartera
B53: ='Application Info'!B53 -> Santander Perú | C53: ='Application Info'!C53 -> Virtual Assistant P&C | D53: LUIS NAVARRO NARVAEZ | E53: ADOLFO UNDA LAZARO
B54: ='Application Info'!B54 -> Santander Perú | C54: ='Application Info'!C54 -> Masterbase | D54: ALEXANDRA DIAZ FIGUEROA | E54: ALFREDO LLONA ARIS
B55: ='Application Info'!B55 -> Santander Perú | C55: ='Application Info'!C55 -> Data Analytics | D55: ALFREDO LLONA ARIS | E55: ALFREDO LLONA ARIS
B56: ='Application Info'!B56 -> Santander Perú | C56: ='Application Info'!C56 -> Gestión Portafolio PMO | D56: MARIA FERNANDA HEROS CALLIRGOS | E56: MARIA FERNANDA HEROS CALLIRGOS
B57: ='Application Info'!B57 -> Santander Perú | C57: ='Application Info'!C57 -> Diloo | D57: ALEXANDRA DIAZ FIGUEROA | E57: ALFREDO LLONA ARIS
B58: ='Application Info'!B58 -> Santander Perú | C58: ='Application Info'!C58 -> Lynx | D58: CLAUDIA VASQUEZ ULLOA | E58: ALFREDO LLONA ARIS
B59: ='Application Info'!B59 -> Santander Perú | C59: ='Application Info'!C59 -> Astara/SK Berge | D59: DAVID PEDRO RIVAS QUINTANA | E59: ALFREDO LLONA ARIS
B60: ='Application Info'!B60 -> Santander Perú | C60: ='Application Info'!C60 -> Factoring Data Lake Leads | D60: RICARDO CATANI | E60: MARCO RISCO MEJIA
B61: ='Application Info'!B61 -> Santander Perú | C61: ='Application Info'!C61 -> Monitor Plus (ETL) - Transaction Monitorig | D61: ALONSO GUILLERMO SERRANO CARMONA | E61: ALFREDO LLONA ARIS
B62: ='Application Info'!B62 -> Santander Perú | C62: ='Application Info'!C62 -> Dashboards Analytics | D62: CARLOS JUSCAMAITA MOGROVEJO | E62: ALFREDO LLONA ARIS
B63: ='Application Info'!B63 -> Santander Perú | C63: ='Application Info'!C63 -> Loan Tape | D63: ANA MARIA PADILLA JIL | E63: ALFREDO LLONA ARIS
B64: ='Application Info'!B64 -> Santander Perú | C64: ='Application Info'!C64 -> Hiperfirmas | D64: EKATERINI KIDONIS MARCHENA
B65: ='Application Info'!B65 -> Santander Perú | C65: ='Application Info'!C65 -> Web Onboarding | D65: ALFREDO LLONA ARIS | E65: ALFREDO LLONA ARIS
B66: ='Application Info'!B66 -> Santander Perú | C66: ='Application Info'!C66 -> LBTR Novatronic | D66: ALFREDO PEREZ KLAUER | E66: ALFREDO LLONA ARIS
B67: ='Application Info'!B67 -> Santander Perú | C67: ='Application Info'!C67 -> Web Pago Interno | D67: ALEXANDRA DIAZ FIGUEROA | E67: ALFREDO LLONA ARIS
B68: ='Application Info'!B68 -> Santander Perú | C68: ='Application Info'!C68 -> Retenciones SUNAT | D68: EKATERINI KIDONIS MARCHENA
B69: ='Application Info'!B69 -> Santander Perú | C69: ='Application Info'!C69 -> Facturas Negociables | D69: RAFAEL ANTENOR JOSE RIZO PATRON ECHECOPAR | E69: ALFREDO LLONA ARIS
B70: ='Application Info'!B70 -> Santander Perú | C70: ='Application Info'!C70 -> GDS Modellica | D70: ROGGER ARTURO OSTOS CASIANO | E70: ALFREDO LLONA ARIS
B71: ='Application Info'!B71 -> Santander Perú | C71: ='Application Info'!C71 -> Qlik Sense | D71: CESAR NEVADO MURAKAMI | E71: ALFREDO LLONA ARIS
B72: ='Application Info'!B72 -> Santander Perú | C72: ='Application Info'!C72 -> Qlikview | D72: CESAR NEVADO MURAKAMI | E72: ALFREDO LLONA ARIS
B73: ='Application Info'!B73 -> Santander Perú | C73: ='Application Info'!C73 -> DATATEC | D73: JUAN MANUEL MENESES BUCHANAN | E73: JUAN MANUEL MENESES BUCHANAN
B74: ='Application Info'!B74 -> Santander Perú | C74: ='Application Info'!C74 -> Data Lakehouse Corporativo | D74: RENZO ALFREDO HUAYLLASCO CÁCERES | E74: RENZO ALFREDO HUAYLLASCO CÁCERES
B75: ='Application Info'!B75 -> Santander Perú | C75: ='Application Info'!C75 -> Lista Negativa | D75: EKATERINI KIDONIS MARCHENA | E75: EKATERINI KIDONIS MARCHENA
B76: ='Application Info'!B76 -> Santander Perú | C76: ='Application Info'!C76 -> Reporte Helios | D76: SAMUEL SANTIAGO VALDEOLMOS | E76: ALFREDO LLONA ARIS
B77: ='Application Info'!B77 -> Santander Perú | C77: ='Application Info'!C77 -> WorldSys | D77: ALONSO GUILLERMO SERRANO CARMONA | E77: ALFREDO LLONA ARIS
B78: ='Application Info'!B78 -> Santander Perú | C78: ='Application Info'!C78 -> AMLUpdate - Name Screening | D78: ALONSO GUILLERMO SERRANO CARMONA | E78: ALFREDO LLONA ARIS
B79: ='Application Info'!B79 -> Santander Perú | C79: ='Application Info'!C79 -> RatingPlus | D79: JORGE ALEJANDRO CASTILLO FUENTES | E79: ALFREDO LLONA ARIS
B80: ='Application Info'!B80 -> Santander Perú | C80: ='Application Info'!C80 -> Zapier | D80: RAFAEL ANTENOR JOSE RIZO PATRON ECHECOPAR
B81: ='Application Info'!B81 -> Santander Perú | C81: ='Application Info'!C81 -> SAP ByDesign | D81: DOLLY CLAUDIA GALDAMES REVOREDO
B82: ='Application Info'!B82 -> Santander Perú | C82: ='Application Info'!C82 -> Web Institucional | D82: DANIELLA MARIA LETICIA PALACIOS LIZIER | E82: ALFREDO LLONA ARIS
B83: ='Application Info'!B83 -> Santander Perú | C83: ='Application Info'!C83 -> Motor TOP | D83: ANA MARIA PADILLA JIL | E83: ALFREDO LLONA ARIS
B84: ='Application Info'!B84 -> Santander Perú | C84: ='Application Info'!C84 -> Reporte Crediticio de Deudores | D84: DIANA OCHOA CASTILLO | E84: ALFREDO LLONA ARIS
B85: ='Application Info'!B85 -> Santander Perú | C85: ='Application Info'!C85 -> Nazca AS400 | D85: ALFREDO PEREZ KLAUER | E85: ALFREDO LLONA ARIS
B86: ='Application Info'!B86 -> Santander Perú | C86: ='Application Info'!C86 -> Genesys Cloud
B87: ='Application Info'!B87 -> 0 | C87: ='Application Info'!C87 -> 0
B88: ='Application Info'!B88 -> 0 | C88: ='Application Info'!C88 -> 0
B89: ='Application Info'!B89 -> 0 | C89: ='Application Info'!C89 -> 0
B90: ='Application Info'!B90 -> 0 | C90: ='Application Info'!C90 -> 0
B91: ='Application Info'!B91 -> 0 | C91: ='Application Info'!C91 -> 0
B92: ='Application Info'!B92 -> 0 | C92: ='Application Info'!C92 -> 0
B93: ='Application Info'!B93 -> 0 | C93: ='Application Info'!C93 -> 0
B94: ='Application Info'!B94 -> 0 | C94: ='Application Info'!C94 -> 0
B95: ='Application Info'!B95 -> 0 | C95: ='Application Info'!C95 -> 0
B96: ='Application Info'!B96 -> 0 | C96: ='Application Info'!C96 -> 0
B97: ='Application Info'!B97 -> 0 | C97: ='Application Info'!C97 -> 0
... B102: ='Application Info'!B102 -> 0 | C102: ='Application Info'!C102 -> 0
GS25000: C1 | GT25000: 1
IP64999: Yes
IP65000: Yes

Sheet Business Info
A1: Tool Id | B1: Business Unit Name | C1: Application Name | D1: Strategic Business Group (SBG) - mapping from Organization | E1: Line Of Business (LOB)/ Strategic Business Unit (SBU)- mapping from Organization | F1: Application Class | G1: Business Criticality of the Application | H1: Confidentiality Classification | I1: Regulatory Compliance adequacy | J1: Functional Fitness | K1: Business User Satisfaction | L1: Application Owner Insights | FY1: Field Names | FZ1: D,E | GA1: 4 | GB1: <b>Strategic Business Group (SBG) - mapping from Organization</b> | GC1: <b>Line Of Business (LOB)/ Strategic Business Unit (SBU)- mapping from Organization</b> | GD1: <b>Application Class</b> | GE1: <b>Business Criticality of the Application</b> | GF1: <b>Confidentiality Classification</b> | GG1: <b>Regulatory Compliance adequacy</b> | GH1: <b>Functional Fitness</b> | GI1: <b>Business User Satisfaction</b>
B2: ='Application Info'!B2 -> Surgir | C2: ='Application Info'!C2 -> SAP by Design | F2: Tactical | G2: Critical | H2: C2 Internal | FY2: Strategic_bu_group | GA2: 5 | GB2: All | GC2: All | GD2: Strategic | GE2: Critical | GF2: C1 Public | GG2: 1 - Complies fully | GH2: 1-Does not fit at all | GI2: 5 Highest
B3: ='Application Info'!B3 -> Surgir | C3: ='Application Info'!C3 -> App Surgir | F3: technological | G3: Not Applicable | H3: C1 Public | FY3: Line_Of_Business | GD3: Tactical | GE3: High | GF3: C2 Internal | GG3: 1 - Not Applicable / Complies fully | GH3: 2-Below Average - Need major modification | GI3: 4
B4: ='Application Info'!B4 -> Surgir | C4: ='Application Info'!C4 -> App Cliente | F4: Tactical | G4: Critical | H4: C1 Public | FY4: Strategic_Indicator | GD4: Legacy | GE4: Medium | GF4: C3 Confidential | GG4: 2 - Minor Non compliance | GH4: 3-Average - Need moderate modification for business function fitment | GI4: 3
B5: ='Application Info'!B5 -> Surgir | C5: ='Application Info'!C5 -> AMLUpdate - Name Screening | F5: Strategic | G5: Critical | H5: C2 Internal | FY5: Infosec_Classification | GD5: technological | GE5: Not Applicable | GF5: Not Applicable | GG5: 4 - Major Non compliance | GH5: 5-Meets all Business needs | GI5: 1 Lowest
B6: ='Application Info'!B6 -> Surgir | C6: ='Application Info'!C6 -> Portal Web Público | F6: Tactical | G6: Critical | H6: C1 Public | FY6: Regulatory_Compilance | GE6: Unknown | GF6: Unknown | GG6: 5 - Extremely critical non compliance | GH6: Unknown | GI6: Unknown
B7: ='Application Info'!B7 -> Surgir | C7: ='Application Info'!C7 -> Anura | F7: Strategic | G7: Critical | H7: C3 Confidential | FY7: Functional_Fitness | GG7: Unknown
B8: ='Application Info'!B8 -> Surgir | C8: ='Application Info'!C8 -> ERP Contanet | F8: Strategic | G8: Critical | H8: C3 Confidential | FY8: Business_User_satisfication | GG8: Not Applicable
B9: ='Application Info'!B9 -> Surgir | C9: ='Application Info'!C9 -> Datalake | F9: Strategic | G9: Critical | H9: C2 Internal | FY9: Application_Owner_insights | GG9: Not Available
B10: ='Application Info'!B10 -> Surgir | C10: ='Application Info'!C10 -> Cobis | F10: Legacy | G10: Critical | H10: C2 Internal
B11: ='Application Info'!B11 -> Santander Fondos Colectivos | C11: ='Application Info'!C11 -> Emblue | F11: Tactical | G11: Medium | H11: Not Applicable
B12: ='Application Info'!B12 -> Santander Fondos Colectivos | C12: ='Application Info'!C12 -> Facephi | F12: Tactical | G12: Critical | H12: Not Applicable
B13: ='Application Info'!B13 -> Santander Fondos Colectivos | C13: ='Application Info'!C13 -> Mapfre | F13: technological | G13: Medium | H13: C2 Internal
B14: ='Application Info'!B14 -> Santander Fondos Colectivos | C14: ='Application Info'!C14 -> Tracklink | F14: Tactical | G14: Medium | H14: Not Applicable
B15: ='Application Info'!B15 -> Santander Fondos Colectivos | C15: ='Application Info'!C15 -> Docuclass | F15: Tactical | G15: Critical | H15: C2 Internal
B16: ='Application Info'!B16 -> Santander Fondos Colectivos | C16: ='Application Info'!C16 -> Diloo | F16: Tactical | G16: Medium | H16: Not Applicable
B17: ='Application Info'!B17 -> Santander Fondos Colectivos | C17: ='Application Info'!C17 -> Izipay Pagos en línea | F17: Strategic | G17: Critical | H17: C2 Internal
B18: ='Application Info'!B18 -> Santander Fondos Colectivos | C18: ='Application Info'!C18 -> IBK Recaudación | F18: Tactical | G18: Medium | H18: C2 Internal
B19: ='Application Info'!B19 -> Santander Fondos Colectivos | C19: ='Application Info'!C19 -> SAP by Design | F19: Legacy | G19: Critical | H19: C2 Internal
B20: ='Application Info'!B20 -> Santander Fondos Colectivos | C20: ='Application Info'!C20 -> Portal Web Público | F20: Legacy | G20: Critical | H20: C1 Public
B21: ='Application Info'!B21 -> Santander Fondos Colectivos | C21: ='Application Info'!C21 -> AMLUpdate - Name Screening | F21: Strategic | G21: Critical | H21: C2 Internal
... B28: ='Application Info'!B28 -> SCIB Perú | C28: ='Application Info'!C28 -> Sistema Office Banking | F28: Legacy | G28: Critical | H28: C2 Internal
B29: ='Application Info'!B29 -> Santander Consumer Perú | C29: ='Application Info'!C29 -> Diloo | G29: Medium | H29: Not Applicable
B30: ='Application Info'!B30 -> Santander Consumer Perú | C30: ='Application Info'!C30 -> Plataforma de Facturacion Electronica | F30: Strategic | G30: Medium | H30: C2 Internal
B31: ='Application Info'!B31 -> Santander Consumer Perú | C31: ='Application Info'!C31 -> Contáctanos | F31: Tactical | G31: Critical | H31: C1 Public
B32: ='Application Info'!B32 -> Santander Consumer Perú | C32: ='Application Info'!C32 -> Visor Cobranzas | G32: Critical
B33: ='Application Info'!B33 -> Santander Consumer Perú | C33: ='Application Info'!C33 -> Api Market | F33: Tactical | G33: Critical | H33: C2 Internal
B34: ='Application Info'!B34 -> Santander Consumer Perú | C34: ='Application Info'!C34 -> AMLUpdate - Name Screening | G34: Medium | H34: C2 Internal
B35: ='Application Info'!B35 -> Santander Consumer Perú | C35: ='Application Info'!C35 -> Facturación Electrónica - Auto | F35: Strategic | G35: Medium
B36: ='Application Info'!B36 -> Santander Consumer Perú | C36: ='Application Info'!C36 -> Portal Web Público | F36: technological | G36: Critical | H36: C1 Public
B37: ='Application Info'!B37 -> Santander Consumer Perú | C37: ='Application Info'!C37 -> SAP ByDesign - ERP | F37: technological | G37: Critical | H37: C2 Internal
B38: ='Application Info'!B38 -> Santander Consumer Perú | C38: ='Application Info'!C38 -> Bantotal - Core Bancario | F38: Tactical | G38: Critical | H38: C3 Confidential
B39: ='Application Info'!B39 -> Santander Consumer Perú | C39: ='Application Info'!C39 -> Motor de Crédito | F39: Legacy | G39: Critical
B40: ='Application Info'!B40 -> Santander Consumer Perú | C40: ='Application Info'!C40 -> Santi | F40: Legacy | G40: Critical | H40: C2 Internal
B41: ='Application Info'!B41 -> Santander Consumer Perú | C41: ='Application Info'!C41 -> Seguros La Positiva | F41: Legacy | G41: Medium | H41: C2 Internal
B42: ='Application Info'!B42 -> Santander Consumer Perú | C42: ='Application Info'!C42 -> Equifax | F42: Tactical | G42: Medium | H42: Not Applicable
B43: ='Application Info'!B43 -> Santander Consumer Perú | C43: ='Application Info'!C43 -> Docuclass | F43: Legacy | G43: Not Applicable | H43: C2 Internal
B44: ='Application Info'!B44 -> Santander Consumer Perú | C44: ='Application Info'!C44 -> Seir | F44: Strategic | G44: Critical
B45: ='Application Info'!B45 -> Santander Consumer Perú | C45: ='Application Info'!C45 -> Pomelo | F45: Legacy | G45: Medium
B46: ='Application Info'!B46 -> Santander Consumer Perú | C46: ='Application Info'!C46 -> Izypay | F46: Strategic | G46: Critical | H46: Not Applicable
B47: ='Application Info'!B47 -> Santander Consumer Perú | C47: ='Application Info'!C47 -> Kasnet | F47: Tactical | G47: Critical | H47: Not Applicable
B48: ='Application Info'!B48 -> Santander Consumer Perú | C48: ='Application Info'!C48 -> ChatBot | G48: Medium | H48: C1 Public
B49: ='Application Info'!B49 -> Santander Consumer Perú | C49: ='Application Info'!C49 -> Data Riesgos | F49: Tactical | G49: Medium
B50: ='Application Info'!B50 -> Santander Consumer Perú | C50: ='Application Info'!C50 -> API OTP | G50: Medium | H50: C2 Internal
B51: ='Application Info'!B51 -> Santander Consumer Perú | C51: ='Application Info'!C51 -> API Portal | F51: Tactical | G51: Medium | H51: C2 Internal
B52: ='Application Info'!B52 -> Santander Consumer Perú | C52: ='Application Info'!C52 -> Venta Cartera | F52: technological | G52: Medium
B53: ='Application Info'!B53 -> Santander Perú | C53: ='Application Info'!C53 -> Virtual Assistant P&C | F53: Legacy | G53: Not Applicable | H53: Not Applicable
B54: ='Application Info'!B54 -> Santander Perú | C54: ='Application Info'!C54 -> Masterbase | F54: Legacy | G54: Medium | H54: Not Applicable
B55: ='Application Info'!B55 -> Santander Perú | C55: ='Application Info'!C55 -> Data Analytics | F55: Legacy | G55: Critical
B56: ='Application Info'!B56 -> Santander Perú | C56: ='Application Info'!C56 -> Gestión Portafolio PMO | F56: Tactical | G56: Critical
B57: ='Application Info'!B57 -> Santander Perú | C57: ='Application Info'!C57 -> Diloo | F57: Tactical | G57: Medium | H57: Not Applicable
B58: ='Application Info'!B58 -> Santander Perú | C58: ='Application Info'!C58 -> Lynx | F58: Tactical | G58: Critical | H58: C3 Confidential
B59: ='Application Info'!B59 -> Santander Perú | C59: ='Application Info'!C59 -> Astara/SK Berge | F59: Tactical | G59: Medium | H59: C2 Internal
B60: ='Application Info'!B60 -> Santander Perú | C60: ='Application Info'!C60 -> Factoring Data Lake Leads | F60: Strategic | G60: Critical
B61: ='Application Info'!B61 -> Santander Perú | C61: ='Application Info'!C61 -> Monitor Plus (ETL) - Transaction Monitorig | F61: Strategic | G61: Medium
B62: ='Application Info'!B62 -> Santander Perú | C62: ='Application Info'!C62 -> Dashboards Analytics | F62: Tactical | G62: Medium
B63: ='Application Info'!B63 -> Santander Perú | C63: ='Application Info'!C63 -> Loan Tape | G63: Medium
B64: ='Application Info'!B64 -> Santander Perú | C64: ='Application Info'!C64 -> Hiperfirmas | F64: Tactical | G64: Medium
B65: ='Application Info'!B65 -> Santander Perú | C65: ='Application Info'!C65 -> Web Onboarding | F65: Strategic | G65: Medium | H65: C1 Public
B66: ='Application Info'!B66 -> Santander Perú | C66: ='Application Info'!C66 -> LBTR Novatronic | F66: Tactical | G66: Medium | H66: C2 Internal
B67: ='Application Info'!B67 -> Santander Perú | C67: ='Application Info'!C67 -> Web Pago Interno | F67: Strategic | G67: Medium | H67: C1 Public
B68: ='Application Info'!B68 -> Santander Perú | C68: ='Application Info'!C68 -> Retenciones SUNAT | F68: Strategic | G68: Medium
B69: ='Application Info'!B69 -> Santander Perú | C69: ='Application Info'!C69 -> Facturas Negociables | F69: Strategic | G69: Medium
B70: ='Application Info'!B70 -> Santander Perú | C70: ='Application Info'!C70 -> GDS Modellica | F70: Tactical | G70: Medium
B71: ='Application Info'!B71 -> Santander Perú | C71: ='Application Info'!C71 -> Qlik Sense | F71: Tactical | G71: Medium | H71: Not Applicable
B72: ='Application Info'!B72 -> Santander Perú | C72: ='Application Info'!C72 -> Qlikview | F72: Tactical | G72: Medium | H72: Not Applicable
B73: ='Application Info'!B73 -> Santander Perú | C73: ='Application Info'!C73 -> DATATEC | F73: Tactical | G73: Medium
B74: ='Application Info'!B74 -> Santander Perú | C74: ='Application Info'!C74 -> Data Lakehouse Corporativo | F74: Strategic | G74: Critical
B75: ='Application Info'!B75 -> Santander Perú | C75: ='Application Info'!C75 -> Lista Negativa | F75: Tactical | G75: Medium | H75: C3 Confidential
B76: ='Application Info'!B76 -> Santander Perú | C76: ='Application Info'!C76 -> Reporte Helios | F76: Strategic | G76: Medium | H76: C2 Internal
B77: ='Application Info'!B77 -> Santander Perú | C77: ='Application Info'!C77 -> WorldSys | F77: Tactical | G77: Critical | H77: Not Applicable
B78: ='Application Info'!B78 -> Santander Perú | C78: ='Application Info'!C78 -> AMLUpdate - Name Screening | F78: technological | G78: Critical | H78: C2 Internal
B79: ='Application Info'!B79 -> Santander Perú | C79: ='Application Info'!C79 -> RatingPlus | F79: Tactical | G79: Medium | H79: C2 Internal
B80: ='Application Info'!B80 -> Santander Perú | C80: ='Application Info'!C80 -> Zapier | G80: Not Applicable
B81: ='Application Info'!B81 -> Santander Perú | C81: ='Application Info'!C81 -> SAP ByDesign | F81: Tactical | G81: Critical | H81: C2 Internal
B82: ='Application Info'!B82 -> Santander Perú | C82: ='Application Info'!C82 -> Web Institucional | F82: Strategic | G82: Critical | H82: C1 Public
B83: ='Application Info'!B83 -> Santander Perú | C83: ='Application Info'!C83 -> Motor TOP | F83: Tactical | G83: Critical | H83: C2 Internal
B84: ='Application Info'!B84 -> Santander Perú | C84: ='Application Info'!C84 -> Reporte Crediticio de Deudores | F84: Tactical | G84: Critical | H84: C3 Confidential
B85: ='Application Info'!B85 -> Santander Perú | C85: ='Application Info'!C85 -> Nazca AS400 | F85: Legacy | G85: Critical | H85: C2 Internal
B86: ='Application Info'!B86 -> Santander Perú | C86: ='Application Info'!C86 -> Genesys Cloud | F86: technological | G86: Critical | H86: C2 Internal
B87: ='Application Info'!B87 -> 0 | C87: ='Application Info'!C87 -> 0
B88: ='Application Info'!B88 -> 0 | C88: ='Application Info'!C88 -> 0
B89: ='Application Info'!B89 -> 0 | C89: ='Application Info'!C89 -> 0
B90: ='Application Info'!B90 -> 0 | C90: ='Application Info'!C90 -> 0
B91: ='Application Info'!B91 -> 0 | C91: ='Application Info'!C91 -> 0
B92: ='Application Info'!B92 -> 0 | C92: ='Application Info'!C92 -> 0
B93: ='Application Info'!B93 -> 0 | C93: ='Application Info'!C93 -> 0
B94: ='Application Info'!B94 -> 0 | C94: ='Application Info'!C94 -> 0
B95: ='Application Info'!B95 -> 0 | C95: ='Application Info'!C95 -> 0
B96: ='Application Info'!B96 -> 0 | C96: ='Application Info'!C96 -> 0
B97: ='Application Info'!B97 -> 0 | C97: ='Application Info'!C97 -> 0
B98: ='Application Info'!B98 -> 0 | C98: ='Application Info'!C98 -> 0
... B100: ='Application Info'!B100 -> 0 | C100: ='Application Info'!C100 -> 0
GS24996: C1 | GT24996: 1
IP64995: Yes
IP64996: Yes

Sheet Technical Info
A1: Tool Id | B1: Business Unit Name | C1: Application Name | D1: Region | E1: Hosting | F1: Architecture Style of Application | G1: Presentation Layer Architecture | H1: Integration Architecture | I1: Solutions Technology components/platforms | J1: Virtualisation Support | K1: Application Interfaces (PROVIDERS) | L1: Application Interfaces (CONSUMERS) | M1: Criticality of the interfaces | N1: Application Complexity | O1: Pace Layer classification | GA1: Field Names | GB1: E,F,G | GC1: 5 | GD1: <b>Architecture Style of Application</b> | GE1: <b>Presentation Layer Architecture</b> | GF1: <b>Integration Architecture</b> | GG1: <b>Solutions Technology components/platforms</b> | GH1: <b>Virtualisation Support</b> | GI1: <b>Criticality of the interfaces</b> | GJ1: <b>Application Complexity</b> | GK1: <b>Pace Layer classification</b>
B2: ='Application Info'!B2 -> Surgir | C2: ='Application Info'!C2 -> SAP by Design | D2: =IF(C2='Application Info'!C2,'Application Info'!G2,"N/A") -> Azure | E2: =IF(C2='Application Info'!C2,'Application Info'!H2,"N/A") -> 5. SaaS | F2: Client-server | G2: Web - Thin Client | H2: Service Oriented Integration | I2: SAP PowerBuilder | J2: No | M2: Severe impact | N2: Medium | O2: Unknown | GA2: Architecture_Style | GC2: 6 | GD2: Client-server | GE2: Non Gui - Character oriented | GF2: File Transfer | GG2: ADO.NET | GH2: Yes | GI2: No Interface | GJ2: High | GK2: System of Innovation(SOI)
B3: ='Application Info'!B3 -> Surgir | C3: ='Application Info'!C3 -> App Surgir | D3: =IF(C3='Application Info'!C3,'Application Info'!G3,"N/A") -> Local Country | E3: =IF(C3='Application Info'!C3,'Application Info'!H3,"N/A") -> 3. Hybrid cloud | F3: Not Available | G3: Mobile Client | H3: Service Oriented Integration | J3: No | M3: Moderate impact | N3: Medium | O3: System of Differentiation(SDD) | GA3: Presentation_Layer | GC3: 7 | GD3: Mainframe | GE3: Non Web based Gui | GF3: RPC | GG3: AngularJS | GH3: No | GI3: Minimal Impact | GJ3: Medium | GK3: System of Differentiation(SDD)
B4: ='Application Info'!B4 -> Surgir | C4: ='Application Info'!C4 -> App Cliente | D4: =IF(C4='Application Info'!C4,'Application Info'!G4,"N/A") -> Local Country | E4: =IF(C4='Application Info'!C4,'Application Info'!H4,"N/A") -> 3. Hybrid cloud | F4: Not Available | G4: Mobile Client | H4: Service Oriented Integration | J4: No | M4: Moderate impact | N4: Medium | O4: System of Differentiation(SDD) | GA4: Integration_architecture | GD4: Monolithic | GE4: Web - Thin Client | GF4: Point to Point Message passing | GG4: Apache Tomcat | GH4: Not Available | GI4: Low impact | GJ4: Low | GK4: System of Record(SOR)
B5: ='Application Info'!B5 -> Surgir | C5: ='Application Info'!C5 -> AMLUpdate - Name Screening | D5: =IF(C5='Application Info'!C5,'Application Info'!G5,"N/A") -> Mexico | E5: =IF(C5='Application Info'!C5,'Application Info'!H5,"N/A") -> 8. On-Premise | F5: Monolithic | G5: Mobile Client | J5: No | GA5: Application_Dev_Tech | GD5: Multi-tier Non Web | GE5: Web - Smart Client / Rich Internet Application | GF5: Message Broker | GG5: Apache Tomcat 6.x | GH5: Not Applicable | GI5: Moderate impact | GJ5: Unknown | GK5: Unknown
B6: ='Application Info'!B6 -> Surgir | C6: ='Application Info'!C6 -> Portal Web Público | D6: =IF(C6='Application Info'!C6,'Application Info'!G6,"N/A") -> Local Country | E6: =IF(C6='Application Info'!C6,'Application Info'!H6,"N/A") -> 8. On-Premise | F6: Monolithic | G6: Web - Thin Client | J6: No | GA6: Virtualisation_support | GD6: SaaS / Cloud based | GE6: Mobile Client | GF6: Workflow based | GG6: Apache Tomcat 7.x | GI6: Severe impact | GJ6: Not Available | GK6: Not Available
B7: ='Application Info'!B7 -> Surgir | C7: ='Application Info'!C7 -> Anura | D7: =IF(C7='Application Info'!C7,'Application Info'!G7,"N/A") -> Local Country | E7: =IF(C7='Application Info'!C7,'Application Info'!H7,"N/A") -> 5. SaaS | F7: Monolithic | G7: Web - Thin Client | J7: No | GA7: App_Interface_Providers | GD7: Service Oriented | GE7: Terminal Services / VDI | GF7: Content Collaboration | GG7: Apache Tomcat 8.x | GI7: Unknown | GK7: Not Applicable
B8: ='Application Info'!B8 -> Surgir | C8: ='Application Info'!C8 -> ERP Contanet | D8: =IF(C8='Application Info'!C8,'Application Info'!G8,"N/A") -> Azure | E8: =IF(C8='Application Info'!C8,'Application Info'!H8,"N/A") -> 5. SaaS | F8: Monolithic | G8: Mobile Client | J8: No | GA8: App_Interface_Consumers | GD8: Web based Multi tier | GE8: Multichannel integrated - Mobile GUI / IVR / Social network support | GF8: Not Available | GG8: Apache Web Server | GI8: Not Applicable
B9: ='Application Info'!B9 -> Surgir | C9: ='Application Info'!C9 -> Datalake | D9: =IF(C9='Application Info'!C9,'Application Info'!G9,"N/A") -> Local Country | E9: =IF(C9='Application Info'!C9,'Application Info'!H9,"N/A") -> 3. Hybrid cloud | F9: Monolithic | G9: Web - Thin Client | H9: Data Feed/ ETL / Batch | J9: No | M9: Moderate impact | N9: High | O9: System of Record(SOR) | GA9: Criticality_Interface | GD9: Component Based | GE9: Not Available | GF9: Point to Point through shared database | GG9: Apache Web Server 2.0 | GI9: Not Available
B10: ='Application Info'!B10 -> Surgir | C10: ='Application Info'!C10 -> Cobis | D10: =IF(C10='Application Info'!C10,'Application Info'!G10,"N/A") -> AWS | E10: =IF(C10='Application Info'!C10,'Application Info'!H10,"N/A") -> 3. Hybrid cloud | F10: Monolithic | G10: Web - Thin Client | H10: Data Feed/ ETL / Batch | J10: No | M10: Severe impact | N10: High | O10: System of Record(SOR) | GA10: Application_Complexity | GD10: Not Available | GE10: Not Applicable | GF10: Data Feed/ ETL / Batch | GG10: Apache Web Server 2.2
B11: ='Application Info'!B11 -> Santander Fondos Colectivos | C11: ='Application Info'!C11 -> Emblue | D11: =IF(C11='Application Info'!C11,'Application Info'!G11,"N/A") -> Local Country | E11: =IF(C11='Application Info'!C11,'Application Info'!H11,"N/A") -> 7.Vendor sit | F11: Service Oriented | G11: Web - Smart Client / Rich Internet Application | H11: Service Oriented Integration | J11: No | M11: Low impact | N11: Medium | O11: System of Innovation(SOI) | GA11: Pace_Layer | GF11: Service Oriented Integration | GG11: Apache Web Server 2.4
B12: ='Application Info'!B12 -> Santander Fondos Colectivos | C12: ='Application Info'!C12 -> Facephi | D12: =IF(C12='Application Info'!C12,'Application Info'!G12,"N/A") -> Local Country | E12: =IF(C12='Application Info'!C12,'Application Info'!H12,"N/A") -> 7.Vendor sit | F12: Service Oriented | G12: Web - Smart Client / Rich Internet Application | H12: Service Oriented Integration | J12: No | M12: Moderate impact | N12: High | O12: System of Innovation(SOI) | GF12: EDI (Electronic Data Interchange) | GG12: Aspose Total 1.0
B13: ='Application Info'!B13 -> Santander Fondos Colectivos | C13: ='Application Info'!C13 -> Mapfre | D13: =IF(C13='Application Info'!C13,'Application Info'!G13,"N/A") -> Local Country | E13: =IF(C13='Application Info'!C13,'Application Info'!H13,"N/A") -> 5. SaaS | F13: Not Available | G13: Non Web based Gui | H13: Point to Point Message passing | J13: No | M13: Minimal Impact | N13: Low | GF13: Integration-as-a-Service | GG13: Bootstrap
B14: ='Application Info'!B14 -> Santander Fondos Colectivos | C14: ='Application Info'!C14 -> Tracklink | D14: =IF(C14='Application Info'!C14,'Application Info'!G14,"N/A") -> Local Country | E14: =IF(C14='Application Info'!C14,'Application Info'!H14,"N/A") -> 7.Vendor sit | F14: Service Oriented | G14: Web - Smart Client / Rich Internet Application | H14: Service Oriented Integration | J14: No | M14: Low impact | N14: Medium | O14: System of Innovation(SOI) | GF14: No Integration / Standalone | GG14: Citrix XenApp 6.5
B15: ='Application Info'!B15 -> Santander Fondos Colectivos | C15: ='Application Info'!C15 -> Docuclass | D15: =IF(C15='Application Info'!C15,'Application Info'!G15,"N/A") -> Local Country | E15: =IF(C15='Application Info'!C15,'Application Info'!H15,"N/A") -> 8. On-Premise | F15: Monolithic | G15: Web - Smart Client / Rich Internet Application | H15: Service Oriented Integration | J15: No | M15: Low impact | N15: Medium | O15: System of Innovation(SOI) | GF15: Not Applicable | GG15: Citrix XenApp Terminal Services
B16: ='Application Info'!B16 -> Santander Fondos Colectivos | C16: ='Application Info'!C16 -> Diloo | D16: =IF(C16='Application Info'!C16,'Application Info'!G16,"N/A") -> US | E16: =IF(C16='Application Info'!C16,'Application Info'!H16,"N/A") -> 7.Vendor sit | F16: Client-server | G16: Web - Smart Client / Rich Internet Application | H16: Service Oriented Integration | J16: No | M16: Low impact | N16: Medium | O16: System of Innovation(SOI) | GG16: Citrix XenMobile 10.x
B17: ='Application Info'!B17 -> Santander Fondos Colectivos | C17: ='Application Info'!C17 -> Izipay Pagos en línea | D17: =IF(C17='Application Info'!C17,'Application Info'!G17,"N/A") -> Local Country | E17: =IF(C17='Application Info'!C17,'Application Info'!H17,"N/A") -> 3. Hybrid cloud | F17: Monolithic | G17: Web - Smart Client / Rich Internet Application | H17: Point to Point Message passing | I17: JBoss 5.1 | J17: No | M17: Severe impact | N17: High | O17: Unknown | GG17: Cordova 1.0
B18: ='Application Info'!B18 -> Santander Fondos Colectivos | C18: ='Application Info'!C18 -> IBK Recaudación | D18: =IF(C18='Application Info'!C18,'Application Info'!G18,"N/A") -> Local Country | E18: =IF(C18='Application Info'!C18,'Application Info'!H18,"N/A") -> 8. On-Premise | F18: Service Oriented | G18: Not Available | H18: Point to Point Message passing | I18: JBoss 5.1 | J18: No | M18: Severe impact | N18: High | O18: Unknown | GG18: Eclipse
B19: ='Application Info'!B19 -> Santander Fondos Colectivos | C19: ='Application Info'!C19 -> SAP by Design | D19: =IF(C19='Application Info'!C19,'Application Info'!G19,"N/A") -> Mexico | E19: =IF(C19='Application Info'!C19,'Application Info'!H19,"N/A") -> 5. SaaS | F19: Service Oriented | G19: Not Applicable | H19: Integration-as-a-Service | J19: No | M19: Severe impact | N19: High | O19: Not Available | GG19: IBM Rational Application Developer
B20: ='Application Info'!B20 -> Santander Fondos Colectivos | C20: ='Application Info'!C20 -> Portal Web Público | D20: =IF(C20='Application Info'!C20,'Application Info'!G20,"N/A") -> Mexico | E20: =IF(C20='Application Info'!C20,'Application Info'!H20,"N/A") -> 8. On-Premise | F20: Service Oriented | G20: Web - Thin Client | H20: Service Oriented Integration | J20: No | M20: Severe impact | N20: High | O20: System of Innovation(SOI) | GG20: Java Runtime 6
B21: ='Application Info'!B21 -> Santander Fondos Colectivos | C21: ='Application Info'!C21 -> AMLUpdate - Name Screening | D21: =IF(C21='Application Info'!C21,'Application Info'!G21,"N/A") -> Local Country | E21: =IF(C21='Application Info'!C21,'Application Info'!H21,"N/A") -> 5. SaaS | F21: Service Oriented | G21: Non Web based Gui | H21: Integration-as-a-Service | J21: No | M21: Severe impact | N21: High | O21: Not Applicable | GG21: JBoss 5.1
B22: ='Application Info'!B22 -> Santander Fondos Colectivos | C22: ='Application Info'!C22 -> Santo | D22: =IF(C22='Application Info'!C22,'Application Info'!G22,"N/A") -> Local Country | E22: =IF(C22='Application Info'!C22,'Application Info'!H22,"N/A") -> 3. Hybrid cloud | F22: SaaS / Cloud based | G22: Web - Thin Client | H22: Service Oriented Integration | J22: No | M22: Severe impact | N22: High | O22: System of Record(SOR) | GG22: Kendo UI
B23: ='Application Info'!B23 -> SCIB Perú | C23: ='Application Info'!C23 -> Nuevo Office Banking | D23: =IF(C23='Application Info'!C23,'Application Info'!G23,"N/A") -> US | E23: =IF(C23='Application Info'!C23,'Application Info'!H23,"N/A") -> 5. SaaS | F23: SaaS / Cloud based | G23: Web - Thin Client | H23: Service Oriented Integration | J23: No | M23: Severe impact | N23: High | O23: System of Innovation(SOI) | GG23: Microsoft .NET Framework
B24: ='Application Info'!B24 -> SCIB Perú | C24: ='Application Info'!C24 -> CEEFFC | D24: =IF(C24='Application Info'!C24,'Application Info'!G24,"N/A") -> Mexico | E24: =IF(C24='Application Info'!C24,'Application Info'!H24,"N/A") -> 8. On-Premise | F24: Monolithic | G24: Non Web based Gui | H24: Integration-as-a-Service | J24: No | M24: Severe impact | N24: High | O24: Not Applicable | GG24: Microsoft .NET Framework 2.0
B25: ='Application Info'!B25 -> SCIB Perú | C25: ='Application Info'!C25 -> Lbtr | D25: =IF(C25='Application Info'!C25,'Application Info'!G25,"N/A") -> Local Country | E25: =IF(C25='Application Info'!C25,'Application Info'!H25,"N/A") -> 8. On-Premise | F25: Service Oriented | G25: Not Available | H25: Point to Point Message passing | I25: JBoss 5.1 | J25: No | M25: Severe impact | N25: High | O25: Unknown | GG25: Microsoft .NET Framework 3.5
B26: ='Application Info'!B26 -> SCIB Perú | C26: ='Application Info'!C26 -> Cash Nexus | D26: =IF(C26='Application Info'!C26,'Application Info'!G26,"N/A") -> Local Country | E26: =IF(C26='Application Info'!C26,'Application Info'!H26,"N/A") -> 3. Hybrid cloud | F26: Client-server | G26: Non Web based Gui | H26: Integration-as-a-Service | J26: No | M26: Severe impact | N26: High | O26: Not Applicable | GG26: Microsoft .NET Framework 4.0
B27: ='Application Info'!B27 -> SCIB Perú | C27: ='Application Info'!C27 -> Host to Host | D27: =IF(C27='Application Info'!C27,'Application Info'!G27,"N/A") -> Local Country | E27: =IF(C27='Application Info'!C27,'Application Info'!H27,"N/A") -> 8. On-Premise | F27: Service Oriented | G27: Not Available | H27: Point to Point Message passing | I27: JBoss 5.1 | J27: No | M27: Severe impact | N27: High | O27: Unknown | GG27: Microsoft .NET Framework 4.5
B28: ='Application Info'!B28 -> SCIB Perú | C28: ='Application Info'!C28 -> Sistema Office Banking | D28: =IF(C28='Application Info'!C28,'Application Info'!G28,"N/A") -> Azure | E28: =IF(C28='Application Info'!C28,'Application Info'!H28,"N/A") -> 3. Hybrid cloud | F28: Service Oriented | G28: Web - Thin Client | H28: Service Oriented Integration | J28: No | M28: Severe impact | N28: High | O28: System of Innovation(SOI) | GG28: Microsoft .NET Framework 4.5.1
B29: ='Application Info'!B29 -> Santander Consumer Perú | C29: ='Application Info'!C29 -> Diloo | D29: =IF(C29='Application Info'!C29,'Application Info'!G29,"N/A") -> US | E29: =IF(C29='Application Info'!C29,'Application Info'!H29,"N/A") -> 7.Vendor sit | F29: Web based Multi tier | G29: Web - Smart Client / Rich Internet Application | H29: Service Oriented Integration | J29: No | M29: Low impact | N29: Medium | O29: System of Innovation(SOI) | GG29: Microsoft .NET Framework 4.5.2
B30: ='Application Info'!B30 -> Santander Consumer Perú | C30: ='Application Info'!C30 -> Plataforma de Facturacion Electronica | D30: =IF(C30='Application Info'!C30,'Application Info'!G30,"N/A") -> AWS | E30: =IF(C30='Application Info'!C30,'Application Info'!H30,"N/A") -> 8. On-Premise | F30: SaaS / Cloud based | G30: Web - Thin Client | H30: Point to Point Message passing | J30: No | M30: Moderate impact | N30: Medium | GG30: Microsoft Active Directory Domain Services 1.0
B31: ='Application Info'!B31 -> Santander Consumer Perú | C31: ='Application Info'!C31 -> Contáctanos | D31: =IF(C31='Application Info'!C31,'Application Info'!G31,"N/A") -> Local Country | E31: =IF(C31='Application Info'!C31,'Application Info'!H31,"N/A") -> 6. Sharepoint | F31: Monolithic | G31: Web - Thin Client | H31: Service Oriented Integration | J31: No | M31: Minimal Impact | N31: Low | O31: Not Applicable | GG31: Microsoft Active Directory Federation Services 2012 R2
B32: ='Application Info'!B32 -> Santander Consumer Perú | C32: ='Application Info'!C32 -> Visor Cobranzas | D32: =IF(C32='Application Info'!C32,'Application Info'!G32,"N/A") -> Local Country | E32: =IF(C32='Application Info'!C32,'Application Info'!H32,"N/A") -> 6. Sharepoint | G32: Web - Thin Client | H32: Point to Point Message passing | J32: No | M32: Moderate impact | N32: Medium | GG32: Microsoft .Net Framework client-side 4
B33: ='Application Info'!B33 -> Santander Consumer Perú | C33: ='Application Info'!C33 -> Api Market | D33: =IF(C33='Application Info'!C33,'Application Info'!G33,"N/A") -> Local Country | E33: =IF(C33='Application Info'!C33,'Application Info'!H33,"N/A") -> 3. Hybrid cloud | F33: Monolithic | G33: Not Applicable | H33: Service Oriented Integration | J33: No | M33: Moderate impact | N33: Medium | O33: System of Innovation(SOI) | GG33: Microsoft .Net Framework CSOM (Client Side Object Model)
B34: ='Application Info'!B34 -> Santander Consumer Perú | C34: ='Application Info'!C34 -> AMLUpdate - Name Screening | D34: =IF(C34='Application Info'!C34,'Application Info'!G34,"N/A") -> Azure | E34: =IF(C34='Application Info'!C34,'Application Info'!H34,"N/A") -> 5. SaaS | F34: Multi-tier Non Web | G34: Non Web based Gui | H34: Integration-as-a-Service | J34: No | M34: Severe impact | N34: High | O34: Not Applicable | GG34: Microsoft Internet Explorer 11
B35: ='Application Info'!B35 -> Santander Consumer Perú | C35: ='Application Info'!C35 -> Facturación Electrónica - Auto | D35: =IF(C35='Application Info'!C35,'Application Info'!G35,"N/A") -> Mexico | E35: =IF(C35='Application Info'!C35,'Application Info'!H35,"N/A") -> 8. On-Premise | F35: Monolithic | G35: Non Web based Gui | H35: Service Oriented Integration | J35: No | M35: Moderate impact | N35: Medium | O35: Not Applicable | GG35: Microsoft Sharepoint Designer
B36: ='Application Info'!B36 -> Santander Consumer Perú | C36: ='Application Info'!C36 -> Portal Web Público | D36: =IF(C36='Application Info'!C36,'Application Info'!G36,"N/A") -> Mexico | E36: =IF(C36='Application Info'!C36,'Application Info'!H36,"N/A") -> 8. On-Premise | F36: Not Available | G36: Web - Thin Client | H36: Service Oriented Integration | J36: No | M36: Severe impact | N36: High | O36: System of Innovation(SOI) | GG36: Microsoft Team Foundation Server
B37: ='Application Info'!B37 -> Santander Consumer Perú | C37: ='Application Info'!C37 -> SAP ByDesign - ERP | D37: =IF(C37='Application Info'!C37,'Application Info'!G37,"N/A") -> Local Country | E37: =IF(C37='Application Info'!C37,'Application Info'!H37,"N/A") -> 3. Hybrid cloud | F37: Service Oriented | G37: Not Applicable | H37: Integration-as-a-Service | J37: No | M37: Severe impact | N37: High | O37: Not Available | GG37: Microsoft Visual Studio
B38: ='Application Info'!B38 -> Santander Consumer Perú | C38: ='Application Info'!C38 -> Bantotal - Core Bancario | D38: =IF(C38='Application Info'!C38,'Application Info'!G38,"N/A") -> Azure | E38: =IF(C38='Application Info'!C38,'Application Info'!H38,"N/A") -> 3. Hybrid cloud | F38: Web based Multi tier | G38: Web - Thin Client | H38: Service Oriented Integration | J38: No | M38: Severe impact | N38: High | O38: System of Record(SOR) | GG38: Microsoft Visual Studio 2005
B39: ='Application Info'!B39 -> Santander Consumer Perú | C39: ='Application Info'!C39 -> Motor de Crédito | D39: =IF(C39='Application Info'!C39,'Application Info'!G39,"N/A") -> Local Country | E39: =IF(C39='Application Info'!C39,'Application Info'!H39,"N/A") -> 8. On-Premise | F39: Monolithic | G39: Non Web based Gui | H39: Point to Point Message passing | J39: No | M39: Moderate impact | N39: Medium | O39: Not Available | GG39: Microsoft Visual Studio 2010
B40: ='Application Info'!B40 -> Santander Consumer Perú | C40: ='Application Info'!C40 -> Santi | D40: =IF(C40='Application Info'!C40,'Application Info'!G40,"N/A") -> Local Country | E40: =IF(C40='Application Info'!C40,'Application Info'!H40,"N/A") -> 8. On-Premise | F40: Service Oriented | G40: Web - Thin Client | H40: Point to Point Message passing | J40: No | M40: Severe impact | N40: High | O40: Not Available | GG40: Microsoft Visual Studio 2013
B41: ='Application Info'!B41 -> Santander Consumer Perú | C41: ='Application Info'!C41 -> Seguros La Positiva | D41: =IF(C41='Application Info'!C41,'Application Info'!G41,"N/A") -> Local Country | E41: =IF(C41='Application Info'!C41,'Application Info'!H41,"N/A") -> 8. On-Premise | F41: Monolithic | G41: Non Gui - Character oriented | H41: Point to Point Message passing | J41: No | M41: Minimal Impact | N41: Medium | O41: Not Available | GG41: Model View ViewModel (MVVM)
B42: ='Application Info'!B42 -> Santander Consumer Perú | C42: ='Application Info'!C42 -> Equifax | D42: =IF(C42='Application Info'!C42,'Application Info'!G42,"N/A") -> Local Country | E42: =IF(C42='Application Info'!C42,'Application Info'!H42,"N/A") -> 5. SaaS | F42: Monolithic | G42: Web - Smart Client / Rich Internet Application | H42: Service Oriented Integration | J42: No | M42: Low impact | N42: Medium | O42: System of Innovation(SOI) | GG42: Netweaver Single-Sign-On 2.0
B43: ='Application Info'!B43 -> Santander Consumer Perú | C43: ='Application Info'!C43 -> Docuclass | D43: =IF(C43='Application Info'!C43,'Application Info'!G43,"N/A") -> Mexico | E43: =IF(C43='Application Info'!C43,'Application Info'!H43,"N/A") -> 8. On-Premise | F43: Monolithic | G43: Web - Smart Client / Rich Internet Application | H43: Service Oriented Integration | J43: No | M43: Low impact | N43: Medium | O43: System of Innovation(SOI) | GG43: Network File Store
B44: ='Application Info'!B44 -> Santander Consumer Perú | C44: ='Application Info'!C44 -> Seir | D44: =IF(C44='Application Info'!C44,'Application Info'!G44,"N/A") -> 0 | E44: =IF(C44='Application Info'!C44,'Application Info'!H44,"N/A") -> 3. Hybrid cloud | F44: Service Oriented | G44: Not Applicable | H44: Point to Point Message passing | J44: No | M44: Moderate impact | N44: High | O44: Not Available | GG44: Nhibernate
B45: ='Application Info'!B45 -> Santander Consumer Perú | C45: ='Application Info'!C45 -> Pomelo | D45: =IF(C45='Application Info'!C45,'Application Info'!G45,"N/A") -> Local Country | E45: =IF(C45='Application Info'!C45,'Application Info'!H45,"N/A") -> 8. On-Premise | F45: Monolithic | G45: Web - Smart Client / Rich Internet Application | H45: Service Oriented Integration | J45: No | M45: Severe impact | N45: Medium | O45: System of Innovation(SOI) | GG45: Hibernate
B46: ='Application Info'!B46 -> Santander Consumer Perú | C46: ='Application Info'!C46 -> Izypay | D46: =IF(C46='Application Info'!C46,'Application Info'!G46,"N/A") -> Mexico | E46: =IF(C46='Application Info'!C46,'Application Info'!H46,"N/A") -> 8. On-Premise | F46: Client-server | G46: Non Web based Gui | H46: Point to Point Message passing | I46: JBoss 5.1 | J46: No | M46: Severe impact | N46: High | O46: Unknown | GG46: Not Available
B47: ='Application Info'!B47 -> Santander Consumer Perú | C47: ='Application Info'!C47 -> Kasnet | D47: =IF(C47='Application Info'!C47,'Application Info'!G47,"N/A") -> Mexico | E47: =IF(C47='Application Info'!C47,'Application Info'!H47,"N/A") -> 8. On-Premise | F47: Monolithic | G47: Non Web based Gui | H47: Point to Point Message passing | I47: JBoss 5.1 | J47: No | M47: Severe impact | N47: High | O47: Unknown | GG47: Oracle APEX
B48: ='Application Info'!B48 -> Santander Consumer Perú | C48: ='Application Info'!C48 -> ChatBot | D48: =IF(C48='Application Info'!C48,'Application Info'!G48,"N/A") -> US | E48: =IF(C48='Application Info'!C48,'Application Info'!H48,"N/A") -> 5. SaaS | F48: SaaS / Cloud based | G48: Non Web based Gui | H48: Point to Point Message passing | I48: JBoss 5.1 | J48: No | M48: Minimal Impact | N48: Low | O48: Unknown | GG48: Oracle PL/SQL Developer
B49: ='Application Info'!B49 -> Santander Consumer Perú | C49: ='Application Info'!C49 -> Data Riesgos | D49: =IF(C49='Application Info'!C49,'Application Info'!G49,"N/A") -> 0 | E49: =IF(C49='Application Info'!C49,'Application Info'!H49,"N/A") -> 3. Hybrid cloud | F49: Multi-tier Non Web | G49: Web - Thin Client | H49: Data Feed/ ETL / Batch | J49: No | M49: Moderate impact | N49: High | O49: System of Record(SOR) | GG49: PeopleSoft Application Designer
B50: ='Application Info'!B50 -> Santander Consumer Perú | C50: ='Application Info'!C50 -> API OTP | D50: =IF(C50='Application Info'!C50,'Application Info'!G50,"N/A") -> Mexico | E50: =IF(C50='Application Info'!C50,'Application Info'!H50,"N/A") -> 3. Hybrid cloud | F50: Monolithic | G50: Not Applicable | H50: Service Oriented Integration | J50: No | M50: Moderate impact | N50: Medium | O50: System of Innovation(SOI) | GG50: Privilege Elevation Tool 2
B51: ='Application Info'!B51 -> Santander Consumer Perú | C51: ='Application Info'!C51 -> API Portal | D51: =IF(C51='Application Info'!C51,'Application Info'!G51,"N/A") -> Mexico | E51: =IF(C51='Application Info'!C51,'Application Info'!H51,"N/A") -> 3. Hybrid cloud | F51: Service Oriented | G51: Not Applicable | H51: Service Oriented Integration | J51: No | M51: Moderate impact | N51: Medium | O51: System of Innovation(SOI) | GG51: SAP PowerBuilder
B52: ='Application Info'!B52 -> Santander Consumer Perú | C52: ='Application Info'!C52 -> Venta Cartera | D52: =IF(C52='Application Info'!C52,'Application Info'!G52,"N/A") -> Mexico | E52: =IF(C52='Application Info'!C52,'Application Info'!H52,"N/A") -> 3. Hybrid cloud | F52: Service Oriented | G52: Web - Thin Client | H52: Point to Point Message passing | J52: No | M52: Severe impact | N52: Medium | O52: Not Available | GG52: Text Editor
B53: ='Application Info'!B53 -> Santander Perú | C53: ='Application Info'!C53 -> Virtual Assistant P&C | D53: =IF(C53='Application Info'!C53,'Application Info'!G53,"N/A") -> 0 | E53: =IF(C53='Application Info'!C53,'Application Info'!H53,"N/A") -> 3. Hybrid cloud | F53: Monolithic | G53: Not Available | H53: Point to Point Message passing | J53: No | M53: Not Applicable | N53: Not Available | O53: Not Available
B54: ='Application Info'!B54 -> Santander Perú | C54: ='Application Info'!C54 -> Masterbase | D54: =IF(C54='Application Info'!C54,'Application Info'!G54,"N/A") -> Mexico | E54: =IF(C54='Application Info'!C54,'Application Info'!H54,"N/A") -> 5. SaaS | F54: Mainframe | G54: Web - Thin Client | H54: Point to Point Message passing | J54: No | M54: Moderate impact | N54: Medium | O54: Not Available | GG54: Vmware vSphere ESXi 5.5
B55: ='Application Info'!B55 -> Santander Perú | C55: ='Application Info'!C55 -> Data Analytics | D55: =IF(C55='Application Info'!C55,'Application Info'!G55,"N/A") -> Mexico | E55: =IF(C55='Application Info'!C55,'Application Info'!H55,"N/A") -> 5. SaaS | F55: Multi-tier Non Web | G55: Web - Thin Client | H55: Data Feed/ ETL / Batch | J55: No | M55: Moderate impact | N55: High | O55: System of Record(SOR)
B56: ='Application Info'!B56 -> Santander Perú | C56: ='Application Info'!C56 -> Gestión Portafolio PMO | D56: =IF(C56='Application Info'!C56,'Application Info'!G56,"N/A") -> Local Country | E56: =IF(C56='Application Info'!C56,'Application Info'!H56,"N/A") -> 5. SaaS | F56: Monolithic | G56: Web - Thin Client | H56: Point to Point Message passing | J56: No | M56: Minimal Impact | N56: Low | O56: Not Available | GG56: Unknown
B57: ='Application Info'!B57 -> Santander Perú | C57: ='Application Info'!C57 -> Diloo | D57: =IF(C57='Application Info'!C57,'Application Info'!G57,"N/A") -> US | E57: =IF(C57='Application Info'!C57,'Application Info'!H57,"N/A") -> 7.Vendor sit | F57: Service Oriented | G57: Web - Smart Client / Rich Internet Application | H57: Service Oriented Integration | J57: No | M57: Low impact | N57: Medium | O57: System of Innovation(SOI) | GG57: Microsoft Visual Studio 2013 Ultimate
B58: ='Application Info'!B58 -> Santander Perú | C58: ='Application Info'!C58 -> Lynx | D58: =IF(C58='Application Info'!C58,'Application Info'!G58,"N/A") -> Mexico | E58: =IF(C58='Application Info'!C58,'Application Info'!H58,"N/A") -> 8. On-Premise | F58: Monolithic | G58: Non Web based Gui | H58: Point to Point Message passing | J58: No | M58: Severe impact | N58: High | O58: Not Available | GG58: Microsoft Visual Studio 2008 Pro
B59: ='Application Info'!B59 -> Santander Perú | C59: ='Application Info'!C59 -> Astara/SK Berge | D59: =IF(C59='Application Info'!C59,'Application Info'!G59,"N/A") -> Local Country | E59: =IF(C59='Application Info'!C59,'Application Info'!H59,"N/A") -> 3. Hybrid cloud | F59: Monolithic | G59: Non Web based Gui | H59: Integration-as-a-Service | J59: No | M59: Severe impact | N59: High | O59: Not Applicable | GG59: ASP.NET MVC 4
B60: ='Application Info'!B60 -> Santander Perú | C60: ='Application Info'!C60 -> Factoring Data Lake Leads | D60: =IF(C60='Application Info'!C60,'Application Info'!G60,"N/A") -> Local Country | E60: =IF(C60='Application Info'!C60,'Application Info'!H60,"N/A") -> 3. Hybrid cloud | F60: Mainframe | G60: Non Web based Gui | H60: Service Oriented Integration | J60: No | M60: Moderate impact | N60: Medium | O60: Not Applicable | GG60: Not Applicable
B61: ='Application Info'!B61 -> Santander Perú | C61: ='Application Info'!C61 -> Monitor Plus (ETL) - Transaction Monitorig | D61: =IF(C61='Application Info'!C61,'Application Info'!G61,"N/A") -> Azure | E61: =IF(C61='Application Info'!C61,'Application Info'!H61,"N/A") -> 5. SaaS | F61: Monolithic | G61: Non Web based Gui | H61: Point to Point Message passing | J61: No | M61: Low impact | N61: Low | O61: Not Available
B62: ='Application Info'!B62 -> Santander Perú | C62: ='Application Info'!C62 -> Dashboards Analytics | D62: =IF(C62='Application Info'!C62,'Application Info'!G62,"N/A") -> Local Country | E62: =IF(C62='Application Info'!C62,'Application Info'!H62,"N/A") -> 8. On-Premise | F62: SaaS / Cloud based | G62: Web - Thin Client | H62: Data Feed/ ETL / Batch | J62: No | M62: Moderate impact | N62: High | O62: System of Record(SOR)
B63: ='Application Info'!B63 -> Santander Perú | C63: ='Application Info'!C63 -> Loan Tape | D63: =IF(C63='Application Info'!C63,'Application Info'!G63,"N/A") -> Local Country | E63: =IF(C63='Application Info'!C63,'Application Info'!H63,"N/A") -> 8. On-Premise | F63: Service Oriented | G63: Non Web based Gui | H63: Point to Point Message passing | J63: No | M63: Severe impact | N63: Medium | O63: Not Available
B64: ='Application Info'!B64 -> Santander Perú | C64: ='Application Info'!C64 -> Hiperfirmas | D64: =IF(C64='Application Info'!C64,'Application Info'!G64,"N/A") -> Local Country | E64: =IF(C64='Application Info'!C64,'Application Info'!H64,"N/A") -> 8. On-Premise | F64: Multi-tier Non Web | G64: Web - Smart Client / Rich Internet Application | H64: Service Oriented Integration | J64: No | M64: Moderate impact | N64: High | O64: System of Innovation(SOI)
B65: ='Application Info'!B65 -> Santander Perú | C65: ='Application Info'!C65 -> Web Onboarding | D65: =IF(C65='Application Info'!C65,'Application Info'!G65,"N/A") -> Mexico | E65: =IF(C65='Application Info'!C65,'Application Info'!H65,"N/A") -> 3. Hybrid cloud | F65: SaaS / Cloud based | G65: Web - Thin Client | H65: Service Oriented Integration | J65: No | M65: Severe impact | N65: High | O65: System of Innovation(SOI)
B66: ='Application Info'!B66 -> Santander Perú | C66: ='Application Info'!C66 -> LBTR Novatronic | D66: =IF(C66='Application Info'!C66,'Application Info'!G66,"N/A") -> Mexico | E66: =IF(C66='Application Info'!C66,'Application Info'!H66,"N/A") -> 8. On-Premise | F66: Mainframe | G66: Not Available | H66: Point to Point Message passing | I66: JBoss 5.1 | J66: No | M66: Severe impact | N66: High | O66: Unknown
B67: ='Application Info'!B67 -> Santander Perú | C67: ='Application Info'!C67 -> Web Pago Interno | D67: =IF(C67='Application Info'!C67,'Application Info'!G67,"N/A") -> Local Country | E67: =IF(C67='Application Info'!C67,'Application Info'!H67,"N/A") -> 8. On-Premise | F67: Monolithic | G67: Web - Thin Client | H67: Service Oriented Integration | J67: No | M67: Severe impact | N67: High | O67: System of Innovation(SOI)
B68: ='Application Info'!B68 -> Santander Perú | C68: ='Application Info'!C68 -> Retenciones SUNAT | D68: =IF(C68='Application Info'!C68,'Application Info'!G68,"N/A") -> Local Country | E68: =IF(C68='Application Info'!C68,'Application Info'!H68,"N/A") -> 3. Hybrid cloud | F68: Monolithic | G68: Non Web based Gui | H68: Point to Point Message passing | I68: JBoss 5.1 | J68: No | M68: Severe impact | N68: High | O68: Unknown
B69: ='Application Info'!B69 -> Santander Perú | C69: ='Application Info'!C69 -> Facturas Negociables | D69: =IF(C69='Application Info'!C69,'Application Info'!G69,"N/A") -> Local Country | E69: =IF(C69='Application Info'!C69,'Application Info'!H69,"N/A") -> 8. On-Premise | F69: Monolithic | G69: Web - Thin Client | H69: Service Oriented Integration | J69: No | M69: Moderate impact | N69: Medium | O69: Not Applicable
B70: ='Application Info'!B70 -> Santander Perú | C70: ='Application Info'!C70 -> GDS Modellica | D70: =IF(C70='Application Info'!C70,'Application Info'!G70,"N/A") -> US | E70: =IF(C70='Application Info'!C70,'Application Info'!H70,"N/A") -> 7.Vendor sit | F70: SaaS / Cloud based | G70: Web - Smart Client / Rich Internet Application | H70: Service Oriented Integration | J70: No | M70: Low impact | N70: Medium | O70: System of Innovation(SOI)
B71: ='Application Info'!B71 -> Santander Perú | C71: ='Application Info'!C71 -> Qlik Sense | D71: =IF(C71='Application Info'!C71,'Application Info'!G71,"N/A") -> Local Country | E71: =IF(C71='Application Info'!C71,'Application Info'!H71,"N/A") -> 8. On-Premise | F71: Not Available | G71: Web - Smart Client / Rich Internet Application | H71: Service Oriented Integration | J71: No | M71: Low impact | N71: Medium | O71: System of Innovation(SOI)
B72: ='Application Info'!B72 -> Santander Perú | C72: ='Application Info'!C72 -> Qlikview | D72: =IF(C72='Application Info'!C72,'Application Info'!G72,"N/A") -> Local Country | E72: =IF(C72='Application Info'!C72,'Application Info'!H72,"N/A") -> 8. On-Premise | F72: Not Available | G72: Web - Smart Client / Rich Internet Application | H72: Service Oriented Integration | J72: No | M72: Low impact | N72: Medium | O72: System of Innovation(SOI)
B73: ='Application Info'!B73 -> Santander Perú | C73: ='Application Info'!C73 -> DATATEC | D73: =IF(C73='Application Info'!C73,'Application Info'!G73,"N/A") -> AWS | E73: =IF(C73='Application Info'!C73,'Application Info'!H73,"N/A") -> 7.Vendor sit | F73: SaaS / Cloud based | G73: Web - Smart Client / Rich Internet Application | H73: Service Oriented Integration | J73: No | M73: Moderate impact | N73: High | O73: System of Innovation(SOI)
B74: ='Application Info'!B74 -> Santander Perú | C74: ='Application Info'!C74 -> Data Lakehouse Corporativo | D74: =IF(C74='Application Info'!C74,'Application Info'!G74,"N/A") -> Local Country | E74: =IF(C74='Application Info'!C74,'Application Info'!H74,"N/A") -> 3. Hybrid cloud | F74: Service Oriented | G74: Web - Thin Client | H74: Data Feed/ ETL / Batch | J74: No | M74: Moderate impact | N74: High | O74: System of Record(SOR)
B75: ='Application Info'!B75 -> Santander Perú | C75: ='Application Info'!C75 -> Lista Negativa | D75: =IF(C75='Application Info'!C75,'Application Info'!G75,"N/A") -> Local Country | E75: =IF(C75='Application Info'!C75,'Application Info'!H75,"N/A") -> 8. On-Premise | F75: Monolithic | G75: Non Gui - Character oriented | H75: Service Oriented Integration | J75: No | M75: Moderate impact | N75: Medium | O75: Not Applicable
B76: ='Application Info'!B76 -> Santander Perú | C76: ='Application Info'!C76 -> Reporte Helios | D76: =IF(C76='Application Info'!C76,'Application Info'!G76,"N/A") -> Azure | E76: =IF(C76='Application Info'!C76,'Application Info'!H76,"N/A") -> 5. SaaS | F76: Service Oriented | G76: Non Web based Gui | H76: Point to Point Message passing | J76: No | M76: Moderate impact | N76: Medium | O76: Not Available
B77: ='Application Info'!B77 -> Santander Perú | C77: ='Application Info'!C77 -> WorldSys | D77: =IF(C77='Application Info'!C77,'Application Info'!G77,"N/A") -> Local Country | E77: =IF(C77='Application Info'!C77,'Application Info'!H77,"N/A") -> 8. On-Premise | F77: Service Oriented | G77: Non Web based Gui | H77: Point to Point Message passing | J77: No | M77: Moderate impact | N77: High | O77: Not Available
B78: ='Application Info'!B78 -> Santander Perú | C78: ='Application Info'!C78 -> AMLUpdate - Name Screening | D78: =IF(C78='Application Info'!C78,'Application Info'!G78,"N/A") -> Mexico | E78: =IF(C78='Application Info'!C78,'Application Info'!H78,"N/A") -> 5. SaaS | F78: SaaS / Cloud based | G78: Non Web based Gui | H78: Integration-as-a-Service | J78: No | M78: Severe impact | N78: High | O78: Not Applicable
B79: ='Application Info'!B79 -> Santander Perú | C79: ='Application Info'!C79 -> RatingPlus | D79: =IF(C79='Application Info'!C79,'Application Info'!G79,"N/A") -> Mexico | E79: =IF(C79='Application Info'!C79,'Application Info'!H79,"N/A") -> 3. Hybrid cloud | F79: Service Oriented | G79: Non Web based Gui | H79: Point to Point Message passing | J79: No | M79: Severe impact | N79: Medium | O79: Not Available
B80: ='Application Info'!B80 -> Santander Perú | C80: ='Application Info'!C80 -> Zapier | D80: =IF(C80='Application Info'!C80,'Application Info'!G80,"N/A") -> 0 | E80: =IF(C80='Application Info'!C80,'Application Info'!H80,"N/A") -> 5. SaaS | G80: Non Web based Gui | H80: Point to Point Message passing | J80: No | M80: Not Applicable | N80: Medium | O80: Not Available
B81: ='Application Info'!B81 -> Santander Perú | C81: ='Application Info'!C81 -> SAP ByDesign | D81: =IF(C81='Application Info'!C81,'Application Info'!G81,"N/A") -> US | E81: =IF(C81='Application Info'!C81,'Application Info'!H81,"N/A") -> 5. SaaS | F81: Service Oriented | G81: Not Applicable | H81: Integration-as-a-Service | J81: No | M81: Severe impact | N81: High | O81: Not Available
B82: ='Application Info'!B82 -> Santander Perú | C82: ='Application Info'!C82 -> Web Institucional | D82: =IF(C82='Application Info'!C82,'Application Info'!G82,"N/A") -> Local Country | E82: =IF(C82='Application Info'!C82,'Application Info'!H82,"N/A") -> 3. Hybrid cloud | F82: Service Oriented | G82: Web - Thin Client | H82: Service Oriented Integration | J82: No | M82: Severe impact | N82: High | O82: System of Innovation(SOI)
B83: ='Application Info'!B83 -> Santander Perú | C83: ='Application Info'!C83 -> Motor TOP | D83: =IF(C83='Application Info'!C83,'Application Info'!G83,"N/A") -> Local Country | E83: =IF(C83='Application Info'!C83,'Application Info'!H83,"N/A") -> 3. Hybrid cloud | F83: Service Oriented | G83: Non Web based Gui | H83: Point to Point Message passing | J83: No | M83: Moderate impact | N83: Medium | O83: Not Available
B84: ='Application Info'!B84 -> Santander Perú | C84: ='Application Info'!C84 -> Reporte Crediticio de Deudores | D84: =IF(C84='Application Info'!C84,'Application Info'!G84,"N/A") -> Local Country | E84: =IF(C84='Application Info'!C84,'Application Info'!H84,"N/A") -> 6. Sharepoint | F84: Service Oriented | G84: Non Web based Gui | H84: Point to Point Message passing | J84: No | M84: Severe impact | N84: High | O84: Not Available
B85: ='Application Info'!B85 -> Santander Perú | C85: ='Application Info'!C85 -> Nazca AS400 | D85: =IF(C85='Application Info'!C85,'Application Info'!G85,"N/A") -> Mexico | E85: =IF(C85='Application Info'!C85,'Application Info'!H85,"N/A") -> 3. Hybrid cloud | F85: Mainframe | G85: Terminal Services / VDI | H85: Message Broker | J85: No | M85: Severe impact | N85: High | O85: System of Record(SOR)
B86: ='Application Info'!B86 -> Santander Perú | C86: ='Application Info'!C86 -> Genesys Cloud | D86: =IF(C86='Application Info'!C86,'Application Info'!G86,"N/A") -> Azure | E86: =IF(C86='Application Info'!C86,'Application Info'!H86,"N/A") -> 5. SaaS | F86: Not Available | G86: Non Gui - Character oriented | H86: Data Feed/ ETL / Batch | J86: No | M86: Low impact | N86: Low | O86: Unknown
B87: ='Application Info'!B87 -> 0 | C87: ='Application Info'!C87 -> 0 | J87: No
B88: ='Application Info'!B88 -> 0 | C88: ='Application Info'!C88 -> 0 | J88: No
B89: ='Application Info'!B89 -> 0 | C89: ='Application Info'!C89 -> 0 | J89: No
B90: ='Application Info'!B90 -> 0 | C90: ='Application Info'!C90 -> 0 | J90: No
B91: ='Application Info'!B91 -> 0 | C91: ='Application Info'!C91 -> 0 | J91: No
B92: ='Application Info'!B92 -> 0 | C92: ='Application Info'!C92 -> 0 | J92: No
B93: ='Application Info'!B93 -> 0 | C93: ='Application Info'!C93 -> 0 | J93: No
B94: ='Application Info'!B94 -> 0 | C94: ='Application Info'!C94 -> 0 | J94: No
B95: ='Application Info'!B95 -> 0 | C95: ='Application Info'!C95 -> 0 | J95: No
B96: ='Application Info'!B96 -> 0 | C96: ='Application Info'!C96 -> 0 | J96: No
B97: ='Application Info'!B97 -> 0 | C97: ='Application Info'!C97 -> 0 | J97: No
B98: ='Application Info'!B98 -> 0 | C98: ='Application Info'!C98 -> 0 | J98: No
... B100: ='Application Info'!B100 -> 0 | C100: ='Application Info'!C100 -> 0 | J100: No
B101: ='Application Info'!B101 -> 0 | C101: ='Application Info'!C101 -> 0
...

Sheet Technical Platforms
A1: Tool Id | B1: Business Unit Name | C1: Application Name | D1: Business Logic Layer | E1: Data Layer Platforms | F1: Hardware Platforms | G1: Operating System | H1: Software Programming Language | FY1: Field Names | FZ1: D,E,F,G,H | GA1: 4 | GB1: <strong>Business Logic Layer</strong> | GC1: <strong>Data Layer Platforms</strong> | GD1: <strong>Hardware Platforms</strong> | GE1: <strong>Operating System</strong> | GF1: <b>Software Programming Language</b>
B2: ='Application Info'!B2 -> Surgir | C2: ='Application Info'!C2 -> SAP by Design | D2: SAP | E2: Oracle Database Version - 18.0.0.0.0 | H2: ABAP | FY2: business_layer | GA2: 5 | GB2: Alfabet Suite 10.1 | GC2: Entity Framework 6.0 | GD2: CISCO UCS B200 M4 Server | GE2: Red Hat Enterprise Linux 5 | GF2: Assembly Language
B3: ='Application Info'!B3 -> Surgir | C3: ='Application Info'!C3 -> App Surgir | FY3: data_layer | GA3: 6 | GB3: Apache Tomcat | GC3: Microsoft SQL Server | GD3: Cloud Hosted | GE3: Red Hat Enterprise Linux 5.11 | GF3: Bootstrap
B4: ='Application Info'!B4 -> Surgir | C4: ='Application Info'!C4 -> App Cliente | FY4: hardware_plat | GA4: 7 | GB4: Apache Tomcat 6.x | GC4: Microsoft SQL Server 2008 | GD4: Dell Desktop | GE4: Red Hat Enterprise Linux 6.x | GF4: C
B5: ='Application Info'!B5 -> Surgir | C5: ='Application Info'!C5 -> AMLUpdate - Name Screening | FY5: operating_sys | GA5: 8 | GB5: Apache Tomcat 7.x | GC5: Microsoft SQL Server 2010 | GD5: Dell PowerEdge 2950 Server | GE5: Red Hat Enterprise Linux 7.x | GF5: C++
B6: ='Application Info'!B6 -> Surgir | C6: ='Application Info'!C6 -> Portal Web Público | FY6: Programmin_tech | GB6: Apache Tomcat 8.x | GC6: Microsoft SQL Server 2012 | GD6: Dell PowerEdge M610 Blade Server | GE6: Windows 10 | GF6: Cobol
B7: ='Application Info'!B7 -> Surgir | C7: ='Application Info'!C7 -> Anura | GB7: Apache Web Server | GC7: Microsoft SQL Server 2012 EE | GD7: Dell PowerEdge M620 Blade Server | GE7: Windows 7 | GF7: ColdFusion
B8: ='Application Info'!B8 -> Surgir | C8: ='Application Info'!C8 -> ERP Contanet | GB8: Apache Web Server 2.0 | GC8: Microsoft SQL Server 2012 R2 | GD8: Dell PowerEdge M630 Blade Server | GE8: Windows 8 | GF8: CSS
B9: ='Application Info'!B9 -> Surgir | C9: ='Application Info'!C9 -> Datalake | GB9: Apache Web Server 2.2 | GC9: Microsoft SQL Server 2012 R2 Std | GD9: Dell PowerEdge M710 Blade Server | GE9: Microsoft Windows Server 2003 | GF9: Delphi
B10: ='Application Info'!B10 -> Surgir | C10: ='Application Info'!C10 -> Cobis | GB10: Apache Web Server 2.4 | GC10: Microsoft SQL Server 2014 | GD10: Dell PowerEdge M820 Blade Server | GE10: Microsoft Windows Server 2003 Enterprise Edition | GF10: HTML
B11: ='Application Info'!B11 -> Santander Fondos Colectivos | C11: ='Application Info'!C11 -> Emblue | GB11: Aris Publisher 9.8 | GC11: Microsoft SQL Server 2015 | GD11: Dell PowerEdge R710 Rack Server | GE11: Windows Server 2008 | GF11: HTML 5
B12: ='Application Info'!B12 -> Santander Fondos Colectivos | C12: ='Application Info'!C12 -> Facephi | GB12: ASP.NET | GC12: Microsoft SQL Server EE/SE 2008 | GD12: Dell PowerEdge R800 Rack Server | GE12: Windows Server 2008 R2 | GF12: Java 1.8
B13: ='Application Info'!B13 -> Santander Fondos Colectivos | C13: ='Application Info'!C13 -> Mapfre | GB13: ASP.NET 2.0 | GC13: Microsoft SQL Server EE/SE 2008 R2 6.1 | GD13: HP 3000 | GE13: Windows Server 2008 R2 6.1 | GF13: Java 2
B14: ='Application Info'!B14 -> Santander Fondos Colectivos | C14: ='Application Info'!C14 -> Tracklink | GB14: ASP.NET 3.0 | GC14: Microsoft SQL Server EE/SE 2012 | GD14: Iaas | GE14: Windows Server 2008 R2 EE | GF14: JavaScript
B15: ='Application Info'!B15 -> Santander Fondos Colectivos | C15: ='Application Info'!C15 -> Docuclass | GB15: ASP.NET 3.5 | GC15: Microsoft SQL Server EE/SE 2014 | GD15: Not Available | GE15: Windows Server 2008 R2 EE 64-Bit | GF15: jQuery
B16: ='Application Info'!B16 -> Santander Fondos Colectivos | C16: ='Application Info'!C16 -> Diloo | GB16: Citrix XenApp 6.5 | GC16: Microsoft SQL Server EE/SE 2016 | GD16: Paas | GE16: Windows Server 2008 R2 Standard | GF16: Lotus Script
B17: ='Application Info'!B17 -> Santander Fondos Colectivos | C17: ='Application Info'!C17 -> Izipay Pagos en línea | GB17: Citrix XenApp Terminal Services | GC17: Microsoft SQL Server Integration Services | GD17: Vendor Hosted | GE17: Windows Server 2012 | GF17: Microsoft Visual Basic
B18: ='Application Info'!B18 -> Santander Fondos Colectivos | C18: ='Application Info'!C18 -> IBK Recaudación | GB18: COM/DCOM | GC18: Microsoft SQL Server Integration Services 2012 | GD18: Virtual Machine | GE18: Windows Server 2012 R2 | GF18: Microsoft Visual Basic .NET
B19: ='Application Info'!B19 -> Santander Fondos Colectivos | C19: ='Application Info'!C19 -> SAP by Design | D19: SAP | E19: Oracle Database Version - 18.0.0.0.0 | H19: ABAP | GB19: Confirmit Horizons 19 | GC19: Microsoft SQL Server Integration Services 2014 | GD19: Virtual Machine 2CPU | GE19: Windows Server 2012 R2 6.3 | GF19: Microsoft Visual C
B20: ='Application Info'!B20 -> Santander Fondos Colectivos | C20: ='Application Info'!C20 -> Portal Web Público | GB20: Domino / Lotus Notes 9.0.1 | GC20: Microsoft SQL Server Integration Services 2016 | GD20: Virtual Machine 4CPU | GE20: Windows Server 2012 R2 Data center Edition | GF20: Microsoft Visual Basic 2008
B21: ='Application Info'!B21 -> Santander Fondos Colectivos | C21: ='Application Info'!C21 -> AMLUpdate - Name Screening | GB21: EMC Documentum Administrator Application 7.3 | GC21: Microsoft SQL server Management studio | GD21: Virtual Machine 8Core | GE21: Windows Server 2012 R2 Standard | GF21: Microsoft Visual Basic 6.0
B22: ='Application Info'!B22 -> Santander Fondos Colectivos | C22: ='Application Info'!C22 -> Santo | GB22: EMC Documentum Content Server 7.1 | GC22: Microsoft SQL Server Management Studio 2012 | GD22: Virtual Machine VMware | GE22: Windows Server 2012 R2 Std | GF22: Microsoft Visual Basic Macro
B23: ='Application Info'!B23 -> SCIB Perú | C23: ='Application Info'!C23 -> Nuevo Office Banking | GB23: EMC Documentum Document Transformation Server 7.3 | GC23: Microsoft SQL Server Reporting Services 2014 | GD23: Virtual Machine vSphere ESXi 5.5 | GE23: Windows Server 2012 R2 Std SP2 | GF23: Not Available
B24: ='Application Info'!B24 -> SCIB Perú | C24: ='Application Info'!C24 -> CEEFFC | GB24: EMC Documentum Records Manager 6.7 | GC24: Microsoft SQL Server Reporting Services 2016 | GD24: Virtual Machine XenApp 6.5 | GE24: Windows XP | GF24: Perl
B25: ='Application Info'!B25 -> SCIB Perú | C25: ='Application Info'!C25 -> Lbtr | GB25: EMC Documentum Webtop 6.8.5 | GC25: Not Applicable | GD25: Dell | GE25: Unknown | GF25: PowerBuilder
B26: ='Application Info'!B26 -> SCIB Perú | C26: ='Application Info'!C26 -> Cash Nexus | GB26: EMC Documentum WebTop Application 6.8.2 | GC26: Not Available | GD26: Dell Server | GE26: Not Available | GF26: Python
B27: ='Application Info'!B27 -> SCIB Perú | C27: ='Application Info'!C27 -> Host to Host | GB27: EMC Documentum Xplore | GC27: Oracle Database | GD27: Hitachi Blade Server | GE27: Windows | GF27: Rexx
B28: ='Application Info'!B28 -> SCIB Perú | C28: ='Application Info'!C28 -> Sistema Office Banking | GB28: EMC Documentum Xplore 1.5 | GC28: Oracle Database 10g R2 | GD28: HP | GE28: Vendor Proprietary Operating System | GF28: Ruby
B29: ='Application Info'!B29 -> Santander Consumer Perú | C29: ='Application Info'!C29 -> Diloo | GB29: EMC Documentum xPlore 1.6 | GC29: Oracle Database 11g R1 | GD29: IBM | GE29: Linux | GF29: Shell
B30: ='Application Info'!B30 -> Santander Consumer Perú | C30: ='Application Info'!C30 -> Plataforma de Facturacion Electronica | GB30: HP Enterprise Content Manager | GC30: Oracle Database 11g R2 | GD30: Not Applicable | GE30: Windows Server | GF30: Shell Script
B31: ='Application Info'!B31 -> Santander Consumer Perú | C31: ='Application Info'!C31 -> Contáctanos | GB31: HP Enterprise Content Manager 9 | GC31: Oracle Database 12 | GD31: Sun | GE31: Not Applicable | GF31: C#
B32: ='Application Info'!B32 -> Santander Consumer Perú | C32: ='Application Info'!C32 -> Visor Cobranzas | GB32: IBM Business Process Manager 8.5.6 | GC32: Oracle Database 12c | GD32: Lenovo | GE32: Red Hat Enterprise Linux 6 | GF32: SQL
B33: ='Application Info'!B33 -> Santander Consumer Perú | C33: ='Application Info'!C33 -> Api Market | D33: Microsoft .NET Webservices | F33: Windows Server 2019 | G33: MICROSOFT 2012 6.2.9200 STANDARD SERVER EDITION | GB33: IBM Domino Designer | GC33: Oracle Database Appliance 12c | GD33: Dell 2.4 | GE33: REDHAT LINUX V5 SERVER | GF33: Tcl
B34: ='Application Info'!B34 -> Santander Consumer Perú | C34: ='Application Info'!C34 -> AMLUpdate - Name Screening | GB34: IBM Lotus Notes | GC34: Oracle Essbase 11.1.1.x | GD34: HP 9000/800/N4000-55 | GE34: REDHAT LINUX V6 SERVER | GF34: C# 3.0
B35: ='Application Info'!B35 -> Santander Consumer Perú | C35: ='Application Info'!C35 -> Facturación Electrónica - Auto | GB35: IBM Websphere | GC35: Oracle Essbase 11.1.2.x | GD35: HP 9K | GE35: REDHAT LINUX V7 SERVER | GF35: T-SQL
B36: ='Application Info'!B36 -> Santander Consumer Perú | C36: ='Application Info'!C36 -> Portal Web Público | GB36: IBM Websphere 8.5 | GC36: Oracle Forms | GD36: HP Blade (SAN) 4532 | GE36: MICROSOFT 2012 6.2.9200 STANDARD SERVER EDITION | GF36: C# 3.5
B37: ='Application Info'!B37 -> Santander Consumer Perú | C37: ='Application Info'!C37 -> SAP ByDesign - ERP | D37: SAP | E37: Oracle Database Version - 18.0.0.0.0 | H37: ABAP | GB37: Internet Information Services (IIS) | GC37: Oracle mySQL | GD37: HP Blade 9000 | GE37: MICROSOFT 2008 R2 6.1.7601 | GF37: Unknown
B38: ='Application Info'!B38 -> Santander Consumer Perú | C38: ='Application Info'!C38 -> Bantotal - Core Bancario | D38: Not Applicable | E38: Oracle Database Version - 18.0.0.0.0 | F38: Windows Server 2019 | G38: Windows Server 2012 R2 Standard | H38: Not Applicable | GB38: Internet Information Services (IIS)7.5 | GC38: Oracle mySQL 4 | GD38: HP Blade BL 460c | GE38: MICROSOFT 2008 R2 6.1.7601 ENTERPRISE EDITION | GF38: C# 4.5
B39: ='Application Info'!B39 -> Santander Consumer Perú | C39: ='Application Info'!C39 -> Motor de Crédito | GB39: Microsoft .NET Webservices | GC39: Oracle mySQL 5.5.x | GD39: HP DL 385G5 | GF39: ABAP
B40: ='Application Info'!B40 -> Santander Consumer Perú | C40: ='Application Info'!C40 -> Santi | GB40: Microsoft .NET Webservices 2.0 | GC40: Oracle mySQL 5.6.x | GD40: HP G-09 | GF40: Not Applicable
B41: ='Application Info'!B41 -> Santander Consumer Perú | C41: ='Application Info'!C41 -> Seguros La Positiva | GB41: Microsoft .NET Webservices 3.5 | GC41: Oracle PL/SQL | GD41: HP MPEix 6.5 | GF41: Application API
B42: ='Application Info'!B42 -> Santander Consumer Perú | C42: ='Application Info'!C42 -> Equifax | GB42: Microsoft .NET Webservices 4.5 | GC42: Oracle PL/SQL 10 | GD42: HP Proliant G4 | GF42: .NET 3.5
B43: ='Application Info'!B43 -> Santander Consumer Perú | C43: ='Application Info'!C43 -> Docuclass | GB43: Microsoft .NET Webservices 4.6.2 | GC43: Oracle Provider for OLE DB | GD43: HP Risc/Itanium S5 | GF43: Java 1.5
B44: ='Application Info'!B44 -> Santander Consumer Perú | C44: ='Application Info'!C44 -> Seir | GB44: Microsoft Access 2010 | GC44: Oracle Real Application Cluster (RAC) 11gR2 | GD44: HP Unix 11 I | GF44: Java 1.6
B45: ='Application Info'!B45 -> Santander Consumer Perú | C45: ='Application Info'!C45 -> Pomelo | GB45: Microsoft Dynamics | GC45: PostgreSQL 9.x | GD45: HP wintel R07 | GF45: Java 1.7
B46: ='Application Info'!B46 -> Santander Consumer Perú | C46: ='Application Info'!C46 -> Izypay | GB46: Microsoft Excel | GC46: PostgreSQL 10 | GD46: HP3K H032 | GF46: Java SE 10
B47: ='Application Info'!B47 -> Santander Consumer Perú | C47: ='Application Info'!C47 -> Kasnet | GB47: Microsoft Internet Information Server | GC47: Unknown | GD47: HP-UX 11.23i | GF47: Java SE 11
B48: ='Application Info'!B48 -> Santander Consumer Perú | C48: ='Application Info'!C48 -> ChatBot | GB48: Microsoft Internet Information Server 10 | GC48: EMC VNX5700 Data Mover | GD48: HP-UX 11i | GF48: Java SE 12
B49: ='Application Info'!B49 -> Santander Consumer Perú | C49: ='Application Info'!C49 -> Data Riesgos | GB49: Microsoft Internet Information Server 7 | GC49: Microsoft SQL Server Reporting Services | GD49: HP-UX 11iv1 | GF49: Java SE 13
B50: ='Application Info'!B50 -> Santander Consumer Perú | C50: ='Application Info'!C50 -> API OTP | D50: Microsoft .NET Webservices 4.6.2 | E50: Unknown | F50: Windows Server 2019 | G50: MICROSOFT 2012 6.2.9200 STANDARD SERVER EDITION | GB50: Microsoft Internet Information Server 7.5 | GC50: MS SQL 2008+ | GD50: HP-UX B.11 | GF50: Java SE 14
B51: ='Application Info'!B51 -> Santander Consumer Perú | C51: ='Application Info'!C51 -> API Portal | D51: Microsoft .NET Webservices 4.6.2 | E51: Microsoft SQL Server EE/SE 2016 | F51: Windows Server 2019 | G51: MICROSOFT 2012 6.2.9200 STANDARD SERVER EDITION | GB51: Microsoft Internet Information Server 8 | GC51: Oracle Database 10 | GD51: HP-UX B.11.11 | GF51: Java SE 9
B52: ='Application Info'!B52 -> Santander Consumer Perú | C52: ='Application Info'!C52 -> Venta Cartera | GB52: Microsoft Internet Information Server 8.5 | GC52: Oracle Database 11 | GD52: HP-UX B.11.11 U | GF52: Microsoft Visual Basic .NET 4.5
B53: ='Application Info'!B53 -> Santander Perú | C53: ='Application Info'!C53 -> Virtual Assistant P&C
B54: ='Application Info'!B54 -> Santander Perú | C54: ='Application Info'!C54 -> Masterbase | GB54: Microsoft Office 2010 | GC54: Oracle Database 18C | GD54: HP-UX eux110 B.11.11 U 800 | GF54: Python 2.7
B55: ='Application Info'!B55 -> Santander Perú | C55: ='Application Info'!C55 -> Data Analytics
B56: ='Application Info'!B56 -> Santander Perú | C56: ='Application Info'!C56 -> Gestión Portafolio PMO | GB56: Microsoft Office 2013 | GC56: Oracle Database version - 10.2.0.5.0 | GD56: HP-UX eux110 B.11.11 U 9000 | GF56: Python 3.2.2
B57: ='Application Info'!B57 -> Santander Perú | C57: ='Application Info'!C57 -> Diloo | GB57: Microsoft Sharepoint | GC57: Oracle Database Version - 12.1.0.2.0 | GD57: IBM 3850 series 4123 S6 | GF57: Shell Script in Pascal
B58: ='Application Info'!B58 -> Santander Perú | C58: ='Application Info'!C58 -> Lynx | GB58: Microsoft Sharepoint 2010 | GC58: Oracle Database Version - 18.0.0.0.0 | GD58: IBM AIX N25 | GF58: Unix scripts - conda
B59: ='Application Info'!B59 -> Santander Perú | C59: ='Application Info'!C59 -> Astara/SK Berge | GB59: Microsoft Sharepoint 2013 | GD59: IBM G32 | GF59: Unix scripts - perl
B60: ='Application Info'!B60 -> Santander Perú | C60: ='Application Info'!C60 -> Factoring Data Lake Leads | GB60: Microsoft Sharepoint 2016 | GD60: IBM Risc W23 | GF60: VB 10.0
B61: ='Application Info'!B61 -> Santander Perú | C61: ='Application Info'!C61 -> Monitor Plus (ETL) - Transaction Monitorig | GB61: Microsoft Sharepoint Client Side Object Model (CSOM) | GD61: IBM x Series 3550 M2 | GF61: VB 11.0
B62: ='Application Info'!B62 -> Santander Perú | C62: ='Application Info'!C62 -> Dashboards Analytics | GB62: NetWeaver Application Server ABAP v.7.4 | GD62: IBM X Series X05 | GF62: VB 12.0
B63: ='Application Info'!B63 -> Santander Perú | C63: ='Application Info'!C63 -> Loan Tape | GB63: NetWeaver Application Server JAVA v.7.4 | GD63: IBM x346 3.9 | GF63: VB 14.0
B64: ='Application Info'!B64 -> Santander Perú | C64: ='Application Info'!C64 -> Hiperfirmas | GB64: Not Applicable | GD64: IBM x3650 2.0 | GF64: VB 15.x
B65: ='Application Info'!B65 -> Santander Perú | C65: ='Application Info'!C65 -> Web Onboarding | GB65: Not Available | GD65: IBM X3850 M2 | GF65: VB 16.0
B66: ='Application Info'!B66 -> Santander Perú | C66: ='Application Info'!C66 -> LBTR Novatronic | GB66: OneDesk (v Win7) | GD66: IBM x3950 M2 | GF66: VB 6.0
B67: ='Application Info'!B67 -> Santander Perú | C67: ='Application Info'!C67 -> Web Pago Interno | GB67: OpenText Content Server | GD67: Windows Server 2003 | GF67: VB 9.0
B68: ='Application Info'!B68 -> Santander Perú | C68: ='Application Info'!C68 -> Retenciones SUNAT | GB68: Opentext Edocs | GD68: Windows Server 2005
B69: ='Application Info'!B69 -> Santander Perú | C69: ='Application Info'!C69 -> Facturas Negociables | GB69: Oracle Taleo 12B.10 | GD69: Windows Server 2008
B70: ='Application Info'!B70 -> Santander Perú | C70: ='Application Info'!C70 -> GDS Modellica | GB70: Oracle Taleo 12C.5 | GD70: Windows Server 2008 R2
B71: ='Application Info'!B71 -> Santander Perú | C71: ='Application Info'!C71 -> Qlik Sense | GB71: Oracle Tuxedo Web Server 10.3 | GD71: Windows Server 2012
B72: ='Application Info'!B72 -> Santander Perú | C72: ='Application Info'!C72 -> Qlikview | GB72: Oracle WebLogic | GD72: Windows Server 2012 R2
B73: ='Application Info'!B73 -> Santander Perú | C73: ='Application Info'!C73 -> DATATEC | GB73: PeopleSoft | GD73: Windows Server 2016
B74: ='Application Info'!B74 -> Santander Perú | C74: ='Application Info'!C74 -> Data Lakehouse Corporativo | GB74: PeopleSoft 8 | GD74: Windows Server 2019
B75: ='Application Info'!B75 -> Santander Perú | C75: ='Application Info'!C75 -> Lista Negativa | GB75: PeopleSoft 8.8
B76: ='Application Info'!B76 -> Santander Perú | C76: ='Application Info'!C76 -> Reporte Helios | GB76: PeopleSoft 8.9
B77: ='Application Info'!B77 -> Santander Perú | C77: ='Application Info'!C77 -> WorldSys | GB77: PeopleSoft People Tools
B78: ='Application Info'!B78 -> Santander Perú | C78: ='Application Info'!C78 -> AMLUpdate - Name Screening | GB78: PeopleSoft People Tools 8.5.1
B79: ='Application Info'!B79 -> Santander Perú | C79: ='Application Info'!C79 -> RatingPlus | GB79: Profile Picture Synchronization 1.5
B80: ='Application Info'!B80 -> Santander Perú | C80: ='Application Info'!C80 -> Zapier | GB80: SAP
B81: ='Application Info'!B81 -> Santander Perú | C81: ='Application Info'!C81 -> SAP ByDesign | D81: SAP | E81: Oracle Database Version - 18.0.0.0.0 | H81: ABAP | GB81: SAP ARIBA
B82: ='Application Info'!B82 -> Santander Perú | C82: ='Application Info'!C82 -> Web Institucional | GB82: SAP Netweaver
B83: ='Application Info'!B83 -> Santander Perú | C83: ='Application Info'!C83 -> Motor TOP | GB83: Secure FTP
B84: ='Application Info'!B84 -> Santander Perú | C84: ='Application Info'!C84 -> Reporte Crediticio de Deudores | GB84: Skype for Business Lync Server v.2013
B85: ='Application Info'!B85 -> Santander Perú | C85: ='Application Info'!C85 -> Nazca AS400 | GB85: Tibco Spotfire
B86: ='Application Info'!B86 -> Santander Perú | C86: ='Application Info'!C86 -> Genesys Cloud | GB86: Weblogic Application Server 10.6.3
B87: ='Application Info'!B87 -> 0 | C87: ='Application Info'!C87 -> 0 | GB87: WebServices
B88: ='Application Info'!B88 -> 0 | C88: ='Application Info'!C88 -> 0 | GB88: Websphere Portal 8.5
B89: ='Application Info'!B89 -> 0 | C89: ='Application Info'!C89 -> 0 | GB89: Unknown
B90: ='Application Info'!B90 -> 0 | C90: ='Application Info'!C90 -> 0 | GB90: Microsoft Access 2013
B91: ='Application Info'!B91 -> 0 | C91: ='Application Info'!C91 -> 0 | GB91: Microsoft Excel 2013
B92: ='Application Info'!B92 -> 0 | C92: ='Application Info'!C92 -> 0
B93: ='Application Info'!B93 -> 0 | C93: ='Application Info'!C93 -> 0
B94: ='Application Info'!B94 -> 0 | C94: ='Application Info'!C94 -> 0
B95: ='Application Info'!B95 -> 0 | C95: ='Application Info'!C95 -> 0
B96: ='Application Info'!B96 -> 0 | C96: ='Application Info'!C96 -> 0
B97: ='Application Info'!B97 -> 0 | C97: ='Application Info'!C97 -> 0
B98: ='Application Info'!B98 -> 0 | C98: ='Application Info'!C98 -> 0
B99: ='Application Info'!B99 -> 0 | C99: ='Application Info'!C99 -> 0
B100: ='Application Info'!B100 -> 0 | C100: ='Application Info'!C100 -> 0
...

Sheet Usage
A1: Tool Id | B1: Business Unit Name | C1: Application Name | D1: No of Application Users | E1: User Types | F1: Usage growth trend | G1: Application response | H1: Stability and Performance Issues | I1: Technical SME's feedback on Pains and Challenges with the application | J1: Application Load Variation | FY1: Field Names | GB1: <b>No of Application Users</b> | GC1: <b>User Types</b> | GD1: <b>Usage growth trend</b> | GE1: <b>Application response</b> | GF1: <b>Stability and Performance Issues</b> | GG1: <b>Application Load Variation</b>
B2: ='Application Info'!B2 -> Surgir | C2: ='Application Info'!C2 -> SAP by Design | FY2: No_of_App_Users | GB2: 0 | GC2: External | GD2: Remains the same | GE2: 1. Unacceptable performance | GF2: No Issue | GG2: Yes
B3: ='Application Info'!B3 -> Surgir | C3: ='Application Info'!C3 -> App Surgir | E3: Internal | FY3: Audience | GB3: 1-100 | GC3: Internal | GD3: Partially increase | GE3: 2. Frequently unresponsive | GF3: 1-5 performance or stability issue/3 months | GG3: No
B4: ='Application Info'!B4 -> Surgir | C4: ='Application Info'!C4 -> App Cliente | E4: Internal | FY4: Usage_growth_trend | GB4: 101-500 | GC4: Both | GD4: Heavily increase | GE4: 3. Slow at times | GF4: 5-15 performance or stability issues/3 months | GG4: Unknown
B5: ='Application Info'!B5 -> Surgir | C5: ='Application Info'!C5 -> AMLUpdate - Name Screening | E5: Internal | FY5: Stability_Performance_Issue | GB5: 501-1,000 | GC5: Not Available | GD5: Heavily decrease | GE5: 5. Excellent response | GF5: > 30 performance or stability issues/3 months
B6: ='Application Info'!B6 -> Surgir | C6: ='Application Info'!C6 -> Portal Web Público | FY6: Technical_SME_Feedback | GB6: 1,001-5,000 | GD6: Unknown | GE6: Unknown | GF6: Unknown
B7: ='Application Info'!B7 -> Surgir | C7: ='Application Info'!C7 -> Anura | E7: Not Available | FY7: Application_Load_Variation | GB7: 5,000-10,000 | GD7: Not Available | GE7: Not Available | GF7: Not Available
B8: ='Application Info'!B8 -> Surgir | C8: ='Application Info'!C8 -> ERP Contanet | GB8: 10,000+
B9: ='Application Info'!B9 -> Surgir | C9: ='Application Info'!C9 -> Datalake | GB9: Not Applicable
B10: ='Application Info'!B10 -> Surgir | C10: ='Application Info'!C10 -> Cobis | GB10: Not Available
B11: ='Application Info'!B11 -> Santander Fondos Colectivos | C11: ='Application Info'!C11 -> Emblue | GB11: Unknown
B12: ='Application Info'!B12 -> Santander Fondos Colectivos | C12: ='Application Info'!C12 -> Facephi
B13: ='Application Info'!B13 -> Santander Fondos Colectivos | C13: ='Application Info'!C13 -> Mapfre
B14: ='Application Info'!B14 -> Santander Fondos Colectivos | C14: ='Application Info'!C14 -> Tracklink
B15: ='Application Info'!B15 -> Santander Fondos Colectivos | C15: ='Application Info'!C15 -> Docuclass
B16: ='Application Info'!B16 -> Santander Fondos Colectivos | C16: ='Application Info'!C16 -> Diloo
B17: ='Application Info'!B17 -> Santander Fondos Colectivos | C17: ='Application Info'!C17 -> Izipay Pagos en línea
B18: ='Application Info'!B18 -> Santander Fondos Colectivos | C18: ='Application Info'!C18 -> IBK Recaudación
B19: ='Application Info'!B19 -> Santander Fondos Colectivos | C19: ='Application Info'!C19 -> SAP by Design
B20: ='Application Info'!B20 -> Santander Fondos Colectivos | C20: ='Application Info'!C20 -> Portal Web Público
B21: ='Application Info'!B21 -> Santander Fondos Colectivos | C21: ='Application Info'!C21 -> AMLUpdate - Name Screening | E21: Internal
B22: ='Application Info'!B22 -> Santander Fondos Colectivos | C22: ='Application Info'!C22 -> Santo
B23: ='Application Info'!B23 -> SCIB Perú | C23: ='Application Info'!C23 -> Nuevo Office Banking
B24: ='Application Info'!B24 -> SCIB Perú | C24: ='Application Info'!C24 -> CEEFFC
B25: ='Application Info'!B25 -> SCIB Perú | C25: ='Application Info'!C25 -> Lbtr
B26: ='Application Info'!B26 -> SCIB Perú | C26: ='Application Info'!C26 -> Cash Nexus
B27: ='Application Info'!B27 -> SCIB Perú | C27: ='Application Info'!C27 -> Host to Host
B28: ='Application Info'!B28 -> SCIB Perú | C28: ='Application Info'!C28 -> Sistema Office Banking
B29: ='Application Info'!B29 -> Santander Consumer Perú | C29: ='Application Info'!C29 -> Diloo
B30: ='Application Info'!B30 -> Santander Consumer Perú | C30: ='Application Info'!C30 -> Plataforma de Facturacion Electronica
B31: ='Application Info'!B31 -> Santander Consumer Perú | C31: ='Application Info'!C31 -> Contáctanos
B32: ='Application Info'!B32 -> Santander Consumer Perú | C32: ='Application Info'!C32 -> Visor Cobranzas
B33: ='Application Info'!B33 -> Santander Consumer Perú | C33: ='Application Info'!C33 -> Api Market | E33: Internal
B34: ='Application Info'!B34 -> Santander Consumer Perú | C34: ='Application Info'!C34 -> AMLUpdate - Name Screening | E34: Internal
B35: ='Application Info'!B35 -> Santander Consumer Perú | C35: ='Application Info'!C35 -> Facturación Electrónica - Auto
B36: ='Application Info'!B36 -> Santander Consumer Perú | C36: ='Application Info'!C36 -> Portal Web Público
B37: ='Application Info'!B37 -> Santander Consumer Perú | C37: ='Application Info'!C37 -> SAP ByDesign - ERP
B38: ='Application Info'!B38 -> Santander Consumer Perú | C38: ='Application Info'!C38 -> Bantotal - Core Bancario
B39: ='Application Info'!B39 -> Santander Consumer Perú | C39: ='Application Info'!C39 -> Motor de Crédito
B40: ='Application Info'!B40 -> Santander Consumer Perú | C40: ='Application Info'!C40 -> Santi
B41: ='Application Info'!B41 -> Santander Consumer Perú | C41: ='Application Info'!C41 -> Seguros La Positiva
B42: ='Application Info'!B42 -> Santander Consumer Perú | C42: ='Application Info'!C42 -> Equifax
B43: ='Application Info'!B43 -> Santander Consumer Perú | C43: ='Application Info'!C43 -> Docuclass
B44: ='Application Info'!B44 -> Santander Consumer Perú | C44: ='Application Info'!C44 -> Seir
B45: ='Application Info'!B45 -> Santander Consumer Perú | C45: ='Application Info'!C45 -> Pomelo
B46: ='Application Info'!B46 -> Santander Consumer Perú | C46: ='Application Info'!C46 -> Izypay
... B49: ='Application Info'!B49 -> Santander Consumer Perú | C49: ='Application Info'!C49 -> Data Riesgos
B50: ='Application Info'!B50 -> Santander Consumer Perú | C50: ='Application Info'!C50 -> API OTP | E50: Internal
B51: ='Application Info'!B51 -> Santander Consumer Perú | C51: ='Application Info'!C51 -> API Portal | E51: Internal
B52: ='Application Info'!B52 -> Santander Consumer Perú | C52: ='Application Info'!C52 -> Venta Cartera
B53: ='Application Info'!B53 -> Santander Perú | C53: ='Application Info'!C53 -> Virtual Assistant P&C
B54: ='Application Info'!B54 -> Santander Perú | C54: ='Application Info'!C54 -> Masterbase
B55: ='Application Info'!B55 -> Santander Perú | C55: ='Application Info'!C55 -> Data Analytics
B56: ='Application Info'!B56 -> Santander Perú | C56: ='Application Info'!C56 -> Gestión Portafolio PMO
B57: ='Application Info'!B57 -> Santander Perú | C57: ='Application Info'!C57 -> Diloo
B58: ='Application Info'!B58 -> Santander Perú | C58: ='Application Info'!C58 -> Lynx
B59: ='Application Info'!B59 -> Santander Perú | C59: ='Application Info'!C59 -> Astara/SK Berge | D59: 1-100 | E59: External | G59: Unknown | H59: No Issue | I59: El producto funciona bien | J59: Yes
B60: ='Application Info'!B60 -> Santander Perú | C60: ='Application Info'!C60 -> Factoring Data Lake Leads
B61: ='Application Info'!B61 -> Santander Perú | C61: ='Application Info'!C61 -> Monitor Plus (ETL) - Transaction Monitorig
B62: ='Application Info'!B62 -> Santander Perú | C62: ='Application Info'!C62 -> Dashboards Analytics
B63: ='Application Info'!B63 -> Santander Perú | C63: ='Application Info'!C63 -> Loan Tape
B64: ='Application Info'!B64 -> Santander Perú | C64: ='Application Info'!C64 -> Hiperfirmas
B65: ='Application Info'!B65 -> Santander Perú | C65: ='Application Info'!C65 -> Web Onboarding
B66: ='Application Info'!B66 -> Santander Perú | C66: ='Application Info'!C66 -> LBTR Novatronic
B67: ='Application Info'!B67 -> Santander Perú | C67: ='Application Info'!C67 -> Web Pago Interno
B68: ='Application Info'!B68 -> Santander Perú | C68: ='Application Info'!C68 -> Retenciones SUNAT
B69: ='Application Info'!B69 -> Santander Perú | C69: ='Application Info'!C69 -> Facturas Negociables
B70: ='Application Info'!B70 -> Santander Perú | C70: ='Application Info'!C70 -> GDS Modellica
B71: ='Application Info'!B71 -> Santander Perú | C71: ='Application Info'!C71 -> Qlik Sense
... B77: ='Application Info'!B77 -> Santander Perú | C77: ='Application Info'!C77 -> WorldSys
B78: ='Application Info'!B78 -> Santander Perú | C78: ='Application Info'!C78 -> AMLUpdate - Name Screening | E78: Internal
B79: ='Application Info'!B79 -> Santander Perú | C79: ='Application Info'!C79 -> RatingPlus
B80: ='Application Info'!B80 -> Santander Perú | C80: ='Application Info'!C80 -> Zapier
B81: ='Application Info'!B81 -> Santander Perú | C81: ='Application Info'!C81 -> SAP ByDesign
B82: ='Application Info'!B82 -> Santander Perú | C82: ='Application Info'!C82 -> Web Institucional
B83: ='Application Info'!B83 -> Santander Perú | C83: ='Application Info'!C83 -> Motor TOP
B84: ='Application Info'!B84 -> Santander Perú | C84: ='Application Info'!C84 -> Reporte Crediticio de Deudores
B85: ='Application Info'!B85 -> Santander Perú | C85: ='Application Info'!C85 -> Nazca AS400
B86: ='Application Info'!B86 -> Santander Perú | C86: ='Application Info'!C86 -> Genesys Cloud
B87: ='Application Info'!B87 -> 0 | C87: ='Application Info'!C87 -> 0
B88: ='Application Info'!B88 -> 0 | C88: ='Application Info'!C88 -> 0
B89: ='Application Info'!B89 -> 0 | C89: ='Application Info'!C89 -> 0
B90: ='Application Info'!B90 -> 0 | C90: ='Application Info'!C90 -> 0
... B100: ='Application Info'!B100 -> 0 | C100: ='Application Info'!C100 -> 0
GS24998: C1 | GT24998: 1
IP64997: Yes
IP64998: Yes

Sheet Maintenance
A1: Tool Id | B1: Business Unit Name | C1: Application Name | D1: # of Tickets in last 3 months | E1: # of business change request in last 3 months | F1: Application Last Accessed | FY1: Field Names | GB1: <b># of Tickets in last 3 months</b> | GC1: <b># of business change request in last 3 months</b> | GD1: <b>Application Last Accessed</b>
B2: ='Application Info'!B2 -> Surgir | C2: ='Application Info'!C2 -> SAP by Design | FY2: Tickets_3_months | GB2: 0-10 | GC2: 0-5 | GD2: Last 3 months
B3: ='Application Info'!B3 -> Surgir | C3: ='Application Info'!C3 -> App Surgir | FY3: Business_change_3_months | GB3: 11-50 | GC3: 6-10 | GD3: Last 1 year
B4: ='Application Info'!B4 -> Surgir | C4: ='Application Info'!C4 -> App Cliente | FY4: Application_last_accessed | GB4: 51-100 | GC4: 11-30 | GD4: Between 1 - 5 years
B5: ='Application Info'!B5 -> Surgir | C5: ='Application Info'!C5 -> AMLUpdate - Name Screening | GB5: >200 | GC5: >50 | GD5: Unknown
B6: ='Application Info'!B6 -> Surgir | C6: ='Application Info'!C6 -> Portal Web Público | GB6: Not Applicable | GC6: Not Applicable
B7: ='Application Info'!B7 -> Surgir | C7: ='Application Info'!C7 -> Anura | GB7: Not Available | GC7: Not Available
B8: ='Application Info'!B8 -> Surgir | C8: ='Application Info'!C8 -> ERP Contanet
B9: ='Application Info'!B9 -> Surgir | C9: ='Application Info'!C9 -> Datalake
B10: ='Application Info'!B10 -> Surgir | C10: ='Application Info'!C10 -> Cobis
B11: ='Application Info'!B11 -> Santander Fondos Colectivos | C11: ='Application Info'!C11 -> Emblue
B12: ='Application Info'!B12 -> Santander Fondos Colectivos | C12: ='Application Info'!C12 -> Facephi
B13: ='Application Info'!B13 -> Santander Fondos Colectivos | C13: ='Application Info'!C13 -> Mapfre
B14: ='Application Info'!B14 -> Santander Fondos Colectivos | C14: ='Application Info'!C14 -> Tracklink
B15: ='Application Info'!B15 -> Santander Fondos Colectivos | C15: ='Application Info'!C15 -> Docuclass
B16: ='Application Info'!B16 -> Santander Fondos Colectivos | C16: ='Application Info'!C16 -> Diloo
B17: ='Application Info'!B17 -> Santander Fondos Colectivos | C17: ='Application Info'!C17 -> Izipay Pagos en línea
B18: ='Application Info'!B18 -> Santander Fondos Colectivos | C18: ='Application Info'!C18 -> IBK Recaudación
B19: ='Application Info'!B19 -> Santander Fondos Colectivos | C19: ='Application Info'!C19 -> SAP by Design
... B58: ='Application Info'!B58 -> Santander Perú | C58: ='Application Info'!C58 -> Lynx
B59: ='Application Info'!B59 -> Santander Perú | C59: ='Application Info'!C59 -> Astara/SK Berge | D59: Not Applicable | E59: Not Applicable | F59: Last 1 year
B60: ='Application Info'!B60 -> Santander Perú | C60: ='Application Info'!C60 -> Factoring Data Lake Leads
B61: ='Application Info'!B61 -> Santander Perú | C61: ='Application Info'!C61 -> Monitor Plus (ETL) - Transaction Monitorig
B62: ='Application Info'!B62 -> Santander Perú | C62: ='Application Info'!C62 -> Dashboards Analytics
B63: ='Application Info'!B63 -> Santander Perú | C63: ='Application Info'!C63 -> Loan Tape
B64: ='Application Info'!B64 -> Santander Perú | C64: ='Application Info'!C64 -> Hiperfirmas
B65: ='Application Info'!B65 -> Santander Perú | C65: ='Application Info'!C65 -> Web Onboarding
B66: ='Application Info'!B66 -> Santander Perú | C66: ='Application Info'!C66 -> LBTR Novatronic
B67: ='Application Info'!B67 -> Santander Perú | C67: ='Application Info'!C67 -> Web Pago Interno
B68: ='Application Info'!B68 -> Santander Perú | C68: ='Application Info'!C68 -> Retenciones SUNAT
B69: ='Application Info'!B69 -> Santander Perú | C69: ='Application Info'!C69 -> Facturas Negociables
B70: ='Application Info'!B70 -> Santander Perú | C70: ='Application Info'!C70 -> GDS Modellica
B71: ='Application Info'!B71 -> Santander Perú | C71: ='Application Info'!C71 -> Qlik Sense
... B100: ='Application Info'!B100 -> 0 | C100: ='Application Info'!C100 -> 0
GS24998: C1 | GT24998: 1
IP64997: Yes
IP64998: Yes

Sheet Costs - Optional
A1: Tool Id | B1: Business Unit Name | C1: Application Name | D1: Annual Software Maintenance Cost | E1: Annual Hardware Maintenance Cost | F1: Annual Application Support Cost | G1: Application Server – Facility Cost | H1: Application License Cost | FY1: Field Names
FY2: Annual_software
FY3: Annual_hardware
FY4: Annual_application_support
FY5: Applicatino_license
GS25000: C1 | GT25000: 1
IP64999: Yes
IP65000: Yes

Sheet Sheet1
